Workbook

Sheet Index
A1: =Assumptions!A1 -> Bharti Airtel Ltd.
B3: 📥 INPUTS
B5: Assumptions
B6: P&L Input
B7: BS Input
B8: CF Input
B9: Market Data
B10: Equity Beta
B11: Comps Data
B14: 📊Calculation & Analysis
B16: Common Sizing
B17: Revenue Build-up
B18: Working Capital
... B27: FAS

Sheet Assumptions
A1: Bharti Airtel Ltd.
B7: Company Description | C7: Bharti Airtel Ltd.
B8: ISIN Code | C8: INE397D01024
B9: Sector Name | C9: Telecommunication
B10: Industry | C10: Telecom Services
B11: Exchange Name | C11: BSE:532454 NSE:BHARTIARTL
B12: Website | C12: https://www.airtel.in
B13: Company Description | C13: Bharti Airtel Limited is one of India's leading telecommunications companies and a global provider of communication and digital services. Founded in 1995 and headquartered in Gurugram, Haryana, the company operates across India and 14 countries in Africa. Airtel offers a diversified portfolio including mobile services, broadband, digital TV, enterprise solutions, data centers, cloud services, and fintech through Airtel Payments Bank. The company serves over 590 million customers globally and has established a strong market position through continuous investments in network infrastructure, spectrum assets, and digital technologies. Airtel's business model is supported by multiple revenue streams across consumer, enterprise, home broadband, and infrastructure services. For FY2025–26, Bharti Airtel reported consolidated revenue of ₹2,109.7 billion and net profit of ₹338.2 billion, reflecting strong operational performance driven by customer additions, higher data consumption, premiumization, and expansion of digital services.
B14: Current Market Price | C14: 1949
B17: Scenario | D17: Case
B18: Base case | D18: =IF(B18="Best case",1,IF(B18="Base case",2,3)) -> 2
B21: Company data
B22: Particulars | D22: Amount
B23: No of Outstanding shares | C23: Nos | D23: 6094393000
B24: Face Value per share | C24: Rs. | D24: 5
B25: Current Market Price | C25: Rs. | D25: =C14 -> 1949
B26: Market Capitalisation | C26: INR in Crs | D26: =D23*D25/10^7 -> 1187797.2
B29: Assumptions
B30: Perpetual Growth rate | C30: % | D30: 0.04
B31: 10 year Bond yield rate | C31: % | D31: 0.06707
B32: Interest rate | C32: % | D32: =AVERAGE('Income Statement'!C31/('Balance Sheet'!C50+'Balance Sheet'!C61+'Balance Sheet'!C51+'Balance Sheet'!C62),'Income Statement'!D31/('Balance Sheet'!D50+'Balance Sheet'!D61+'Balance Sheet'!D51+'Balance Sheet'!D62),'Income Statement'!E31/('Balance Sheet'!E50+'Balance Sheet'!E61+'Balance Sheet'!E51+'Balance Sheet'!E62),'Income Statement'!F31/('Balance Sheet'!F50+'Balance Sheet'!F61+'Balance Sheet'!F51+'Balance Sheet'!F62),'Income Statement'!G31/('Balance Sheet'!G50+'Balance Sheet'!G61+'Balance Sheet'!G51+'Balance Sheet'!G62))*(1-'Cost Builup'!G34) -> 0.074948986
H34: (INR in millions)
B35: Company Revenue by Geography
B36: Year | C36: India | E36: Africa | G36: South Asia | I36: Others
B37: 2022 | C37: 777402 | E37: 345611 | G37: 3716 | I37: 38740
B38: =B37+1 -> 2023 | C38: 928568 | E38: 416024 | G38: 2669 | I38: 44187
B39: =B38+1 -> 2024 | C39: 1041523 | E39: 404995 | G39: 3469 | I39: 49837
B40: =B39+1 -> 2025 | C40: 1264125 | E40: 413798 | G40: 878 | I40: 51051
B41: =B40+1 -> 2026 | C41: 1550658 | E41: 520330 | G41: 8719 | I41: 30021
B46: Headings | C46: Reference | D46: Assumptions
B47: Revenue Buildup | C47: H29:Q29 | D47: Revenue Forecasting Assumptions • Mobile Services India: Forecast based on the 5-year historical average growth with gradual annual tapering. • Mobile Services Africa: Forecast based on historical average growth with gradual tapering. • Airtel Business: Forecast based on historical average growth and gradual moderation. • Passive Infrastructure Services: Forecast based on historical average growth with gradual tapering. • Homes Services: Forecast based on historical average growth and gradual tapering. • Other Operating Revenue: Forecast based on historical average/median growth. • Exceptional Items: Forecast based on historical average progression. No abnormal future gains assumed. • Discontinued revenue segments have not been projected beyond the historical period.
C48: H18:Q18 G12:Q12 | D48: Other Income and Exceptional Items for the forecast period 2027–2036 are projected as a constant percentage of total revenue, calculated based on the 5-year average audited for Other Income and the 3-year average audited for Exceptional Items.
B49: Cost Buildup | C49: H22:Q22 H28:Q28 | D49: Employee Benefit Expenses and Other Expenses for the forecast period 2027–2036 are projected as a constant percentage of total revenue, based on the 5-year audited average.
C50: H31:Q31 | D50: Finance Costs are estimated using a fixed borrowing rate, derived from the five-year average of interest expenses relative to total debt, and applied consistently throughout the projected period.
C51: H34:Q34 | D51: Tax rate is derived from the latest audited figures, starting at 25% in FY2026 after a 0.5% uplift. It is expected to rise by 1% every two years over the forecast period.
B52: FAS | C52: H173:Q173 | D52: Since FY2026 audited financial data is not available, FY2025 figures have been used as the base for forecasting the additions, disposals and depreciation of Property, Plant & Equipment (PPE), Intangible Assets and ROU Assets. A conservative growth rate of 4% has been assumed for the first projected year and every 3 years thereafter.
C53: H173:Q173 | D53: Capital WIP is forecasted at same absolute growth and increased by 4% for every 3 years.
B54: BS Items | C54: H12:Q12 H61:Q61 | D54: Balance sheet items are projected as % on Revenue using the latest previous year's % as base otherwise as mentioned and Borrowings are adjusted (assumed to be taken/repaid) based on availability of Cash & Cash equivalents
B55: Working Capital | C55: H11:Q11 H12:Q12 | D55: Trade Receivables and Trade Payables are projected as a fixed percentage of revenue, based on the average proportions observed over the last five audited years.
B56: Income Statement | C56: H48:Q48 | D56: Total dividend payments have been projected by assuming a constant dividend payout ratio of 21%, based on the latest historical payout trend. The payout ratio has been maintained throughout the forecast period (FY2027–FY2036).
B57: Balance Sheet | C57: H35:Q35 | D57: Cash and Cash equivalents are taken as the Balancing Figure

Sheet P&L Input
A1: Bharti Airtel Ltd
F6: (INR in millions)
B7: P&L Input
B8: Particulars | C8: 2022 | D8: =C8+1 -> 2023 | E8: =D8+1 -> 2024 | F8: =E8+1 -> 2025 | G8: =F8+1 -> 2026
C9: Audited | D9: Audited | E9: Audited | F9: Audited | G9: Audited
B11: Revenue from Sale of Service | C11: 1165469 | D11: 1391448 | E11: 1499824 | F11: 1729852 | G11: 2109728
B12: Other Operating Revenue | C12: 5343 | D12: 9366 | E12: 14354 | F12: 15737 | G12: 28173
B14: Total Income | C14: =SUM(C11:C12) -> 1170812 | D14: =SUM(D11:D12) -> 1400814 | E14: =SUM(E11:E12) -> 1514178 | F14: =SUM(F11:F12) -> 1745589 | G14: =SUM(G11:G12) -> 2137901
B16: Expenses
B17: Network operating expenses | C17: 250205 | D17: 285433 | E17: 300188 | F17: 335043 | G17: 397500
B18: Access charges | C18: 67611 | D18: 76207 | E18: 75185 | F18: 71713 | G18: 55416
B19: License fee / Spectrum charges | C19: 110636 | D19: 117517 | E19: 120358 | F19: 138290 | G19: 153729
B20: Employee benefits expense | C20: 44333 | D20: 48308 | E20: 53231 | F20: 63089 | G20: 75813
B21: Sales and marketing expenses | C21: 53035 | D21: 72454 | E21: 107882 | F21: 114601 | G21: 131073
B22: Other expenses | C22: 64310 | D22: 78794 | E22: 60062 | F22: 75524 | G22: 99452
B24: Total Expenses | C24: =SUM(C17:C23) -> 590130 | D24: =SUM(D17:D23) -> 678713 | E24: =SUM(E17:E23) -> 716906 | F24: =SUM(F17:F23) -> 798260 | G24: =SUM(G17:G23) -> 912983
B26: EBITDA | C26: =C14-C24 -> 580682 | D26: =D14-D24 -> 722101 | E26: =E14-E24 -> 797272 | F26: =F14-F24 -> 947329 | G26: =G14-G24 -> 1224918
B28: Depreciation & Amortisation | C28: 330907 | D28: 364318 | E28: 395376 | F28: 455703 | G28: 527108
B30: EBIT | C30: =C26-C28 -> 249775 | D30: =D26-D28 -> 357783 | E30: =E26-E28 -> 401896 | F30: =F26-F28 -> 491626 | G30: =G26-G28 -> 697810
B32: Finance Costs | C32: 166162 | D32: 192999 | E32: 226477 | F32: 217539 | G32: 215553
B33: Share of Profit/(Loss) of Associates | C33: -24232 | D33: -7521 | E33: -27094 | F33: -37030 | G33: -3645
B35: Profit before exceptional items | C35: =C30-C32-C33 -> 107845 | D35: =D30-D32-D33 -> 172305 | E35: =E30-E32-E33 -> 202513 | F35: =F30-F32-F33 -> 311117 | G35: =G30-G32-G33 -> 485902
B37: Exceptional items | C37: -16986 | D37: 6698 | E37: 75723 | F37: -72868 | G37: 34175
B39: Profit before Tax | C39: =C35-C37 -> 124831 | D39: =D35-D37 -> 165607 | E39: =E35-E37 -> 126790 | F39: =F35-F37 -> 383985 | G39: =G35-G37 -> 451727
B41: Taxes | C41: 41779 | D41: 42733 | E41: 41210 | F41: 9172 | G41: 113499
B43: Net Profit | C43: =C39-C41 -> 83052 | D43: =D39-D41 -> 122874 | E43: =E39-E41 -> 85580 | F43: =F39-F41 -> 374813 | G43: =G39-G41 -> 338228
B46: KPIs
B47: Revenue % (y-o-y) | C47: - | D47: =D11/C11-1 -> 0.19389533 | E47: =E11/D11-1 -> 0.077887208 | F47: =F11/E11-1 -> 0.15337 | G47: =G11/F11-1 -> 0.21960029
B48: EBITDA% | C48: =C26/C14 -> 0.49596519 | D48: =D26/D14 -> 0.51548671 | E48: =E26/E14 -> 0.52653783 | F48: =F26/F14 -> 0.54269877 | G48: =G26/G14 -> 0.57295357
B49: EBIT % | C49: =C30/C14 -> 0.21333485 | D49: =D30/D14 -> 0.25541078 | E49: =E30/E14 -> 0.2654219 | F49: =F30/F14 -> 0.28163903 | G49: =G30/G14 -> 0.32639959
B50: NP % | C50: =C43/C14 -> 0.070935385 | D50: =D43/D14 -> 0.087716142 | E50: =E43/E14 -> 0.056519115 | F50: =F43/F14 -> 0.21472007 | G50: =G43/G14 -> 0.15820564
B51: ROA | C51: =C43/'BS Input'!C38 -> 0.022838067 | D51: =D43/'BS Input'!D38 -> 0.027511166 | E51: =E43/'BS Input'!E38 -> 0.019251751 | F51: =F43/'BS Input'!F38 -> 0.072869723 | G51: =G43/'BS Input'!G38 -> 0.061256365
B52: Asset Turnover | C52: =C11/'BS Input'!C38 -> 0.32048667 | D52: =D11/'BS Input'!D38 -> 0.31154155 | E52: =E11/'BS Input'!E38 -> 0.33739469 | F52: =F11/'BS Input'!F38 -> 0.33631127 | G52: =G11/'BS Input'!G38 -> 0.38209216
B53: Assets / Equity | C53: ='BS Input'!C38/'BS Input'!C45 -> 3.9555773 | D53: ='BS Input'!D38/'BS Input'!D45 -> 4.1959335 | E53: ='BS Input'!E38/'BS Input'!E45 -> 4.2110134 | F53: ='BS Input'!F38/'BS Input'!F45 -> 3.3515873 | G53: ='BS Input'!G38/'BS Input'!G45 -> 2.8176261
B54: ROE | C54: =C50*C52*C53 -> 0.089925482 | D54: =D50*D52*D53 -> 0.11466321 | E54: =E50*E52*E53 -> 0.080300865 | F54: =F50*F52*F53 -> 0.24202744 | G54: =G50*G52*G53 -> 0.17032307

Sheet BS Input
A1: Bharti Airtel Ltd
B5: Blue- Hard Coded, Black- Calculation & Green- Linkages
G6: (INR in millions)
B7: Particulars | C7: 2022 | D7: 2023 | E7: 2024 | F7: 2025 | G7: 2026
B8: ASSETS
B9: Non-current assets
B10: Property, Plant & Equipment | C10: 905725 | D10: 952241 | E10: 1066121 | F10: 1432724 | G10: 1570659
B11: Capital Work-in-Progress | C11: 42386 | D11: 110293 | E11: 89077 | F11: 105962 | G11: 126131
B12: Right-of-use Assets | C12: 322286 | D12: 546466 | E12: 559367 | F12: 602415 | G12: 673244
B13: Goodwill | C13: 338313 | D13: 337741 | E13: 265017 | F13: 516974 | G13: 566859
B14: Other Intangible Assets | C14: 874509 | D14: 937490 | E14: 1142526 | F14: 1332569 | G14: 1252604
B15: Intangible Assets Under Development | C15: 17161 | D15: 383961 | E15: 79964 | F15: 4027 | G15: 3250
B16: Investment in Joint Ventures & Associates | C16: 284268 | D16: 281838 | E16: 312404 | F16: 36416 | G16: 40622
B17: Financial Assets
B18: Investments | C18: 609 | D18: 656 | E18: 924 | F18: 5435 | G18: 11385
B19: Derivative instruments | C19: 218 | D19: 854 | E19: 65 | F19: - | G19: -
B20: Trade Receivables | E20: 1805 | F20: 2131 | G20: 2544
B21: Loans | C21: – | D21: – | E21: - | F21: 865 | G21: –
B22: Other Financial Assets | C22: 22515 | D22: 25963 | E22: 26557 | F22: 37471 | G22: 35700
B23: Income Tax Assets (Net) | C23: 17479 | D23: 20399 | E23: 14135 | F23: 24978 | G23: 20181
B24: Deferred Tax Assets (Net) | C24: 199250 | D24: 189519 | E24: 192428 | F24: 249111 | G24: 191413
B25: Other Non-current Assets | C25: 91562 | D25: 103898 | E25: 112159 | F25: 116638 | G25: 124770
B26: Total Non-current Assets | C26: =SUM(C10:C25) -> 3116281 | D26: =SUM(D10:D25) -> 3891319 | E26: =SUM(E10:E25) -> 3862549 | F26: =SUM(F10:F25) -> 4467716 | G26: =SUM(G10:G25) -> 4619362
B27: Current Assets
B28: Inventories | C28: 3750 | D28: 2576 | E28: 3639 | F28: 4517 | G28: 6009
B29: Investments | C29: 8614 | D29: 47045 | E29: 2695 | F29: 16532 | G29: 137006
B30: Derivative Instruments | C30: 561 | D30: 1283 | E30: 1168 | F30: 813 | G30: 5040
B31: Trade Receivables | C31: 40562 | D31: 39815 | E31: 47277 | F31: 74557 | G31: 79776
B32: Cash & Cash Equivalents | C32: 60959 | D32: 71794 | E32: 69155 | F32: 61056 | G32: 137222
B33: Other Bank Balances | C33: 73984 | D33: 62392 | E33: 94244 | F33: 106143 | G33: 166546
B34: Other Financial Assets | C34: 214697 | D34: 220865 | E34: 249544 | F34: 267662 | G34: 244264
B35: Other Current Assets | C35: 117152 | D35: 129243 | E35: 115039 | F35: 144608 | G35: 125718
B36: Assets Held for Sale | C36: – | D36: – | E36: – | F36: – | G36: 573
B37: Total Current Assets | C37: =SUM(C28:C36) -> 520279 | D37: =SUM(D28:D36) -> 575013 | E37: =SUM(E28:E36) -> 582761 | F37: =SUM(F28:F36) -> 675888 | G37: =SUM(G28:G36) -> 902154
B38: TOTAL ASSETS | C38: =C26+C37 -> 3636560 | D38: =D26+D37 -> 4466332 | E38: =E26+E37 -> 4445310 | F38: =F26+F37 -> 5143604 | G38: =G26+G37 -> 5521516
B40: EQUITY & LIABILITIES
B41: Share Capital | C41: 27950 | D41: 28366 | E41: 28766 | F41: 29001 | G41: 30468
B42: Other Equity | C42: 637593 | D42: 747263 | E42: 791422 | F42: 1107718 | G42: 1460098
B43: Equity attributable to Owners | C43: =SUM(C41:C42) -> 665543 | D43: =SUM(D41:D42) -> 775629 | E43: =SUM(E41:E42) -> 820188 | F43: =SUM(F41:F42) -> 1136719 | G43: =SUM(G41:G42) -> 1490566
B44: Non-controlling Interests | C44: 253807 | D44: 288814 | E44: 235451 | F44: 397958 | G44: 469068
B45: Total Equity | C45: =SUM(C43:C44) -> 919350 | D45: =SUM(D43:D44) -> 1064443 | E45: =SUM(E43:E44) -> 1055639 | F45: =SUM(F43:F44) -> 1534677 | G45: =SUM(G43:G44) -> 1959634
B46: Non-current liabilities
B47: Financial liabilities
B48: • Borrowings | C48: 1135350 | D48: 1515686 | E48: 1309626 | F48: 1048638 | G48: 1000849
B49: • Lease liabilities | C49: 290562 | D49: 508295 | E49: 539271 | F49: 556701 | G49: 644996
B50: • Derivative instruments | C50: 174 | D50: 3523 | E50: 2890
B51: • Other financial liabilities | C51: 90116 | D51: 97311 | E51: 85036 | F51: 38642 | G51: 26320
B52: Deferred revenue | C52: 30258 | D52: 30901 | E52: 34139 | F52: 35185 | G52: 40185
B53: Provisions | C53: 4639 | D53: 4744 | E53: 5443 | F53: 30396 | G53: 35189
B54: Deferred tax liabilities (net) | C54: 24488 | D54: 20762 | E54: 25118 | F54: 93549 | G54: 67789
B55: Other non-current liabilities | C55: 1363 | D55: 1029 | E55: 1470 | F55: 1414 | G55: 1497
B56: Total non-current liabilities | C56: =SUM(C48:C55) -> 1576950 | D56: =SUM(D48:D55) -> 2182251 | E56: =SUM(E48:E55) -> 2002993 | F56: =SUM(F48:F55) -> 1804525 | G56: =SUM(G48:G55) -> 1816825
B57: Current liabilities
B58: Financial liabilities
B59: • Borrowings | C59: 193795 | D59: 139762 | E59: 209539 | F59: 434485 | G59: 215865
B60: • Lease liabilities | C60: 77072 | D60: 96460 | E60: 97487 | F60: 96597 | G60: 92407
B61: • Derivative instruments | C61: 995 | D61: 1117 | E61: 12207 | F61: 1921 | G61: 1918
B62: • Trade payables | C62: 292741 | D62: 328946 | E62: 351325 | F62: 381537 | G62: 450152
B63: • Other financial liabilities | C63: 194415 | D63: 241951 | E63: 253456 | F63: 333024 | G63: 408659
B64: Deferred revenue | C64: 75929 | D64: 84995 | E64: 87262 | F64: 97729 | G64: 109487
B65: Provisions | C65: 243449 | D65: 257292 | E65: 283282 | F65: 361552 | G65: 357828
B66: Current tax liabilities (net) | C66: 20725 | D66: 17972 | E66: 33031 | F66: 20035 | G66: 31400
B67: Other current liabilities | C67: 41139 | D67: 51143 | E67: 59089 | F67: 77522 | G67: 77341
B68: Total current liabilities | C68: =SUM(C59:C67) -> 1140260 | D68: =SUM(D59:D67) -> 1219638 | E68: =SUM(E59:E67) -> 1386678 | F68: =SUM(F59:F67) -> 1804402 | G68: =SUM(G59:G67) -> 1745057
B69: Total liabilities | C69: =SUM(C56+C68) -> 2717210 | D69: =SUM(D56+D68) -> 3401889 | E69: =SUM(E56+E68) -> 3389671 | F69: =SUM(F56+F68) -> 3608927 | G69: =SUM(G56+G68) -> 3561882
B70: Total equity and liabilities | C70: =C69+C45 -> 3636560 | D70: =D69+D45 -> 4466332 | E70: =E69+E45 -> 4445310 | F70: =F69+F45 -> 5143604 | G70: =G69+G45 -> 5521516
B73: CHECK | C73: =C38=C70 -> TRUE | D73: =D38=D70 -> TRUE | E73: =E38=E70 -> TRUE | F73: =F38=F70 -> TRUE | G73: =G38=G70 -> TRUE
B76: KPIs
B77: Liquidity ratios
B78: Current ratio | C78: =C37/C68 -> 0.45628102 | D78: =D37/D68 -> 0.47146202 | E78: =E37/E68 -> 0.4202569 | F78: =F37/F68 -> 0.37457728 | G78: =G37/G68 -> 0.51697681
B79: Quick ratio | C79: =(SUM(C29:C35)/C68) -> 0.4529923 | D79: =(SUM(D29:D35)/D68) -> 0.46934992 | E79: =(SUM(E29:E35)/E68) -> 0.41763264 | F79: =(SUM(F29:F35)/F68) -> 0.37207396 | G79: =(SUM(G29:G35)/G68) -> 0.51320501
B80: Cash ratio | C80: =(C32+C33)/C68 -> 0.11834406 | D80: =(D32+D33)/D68 -> 0.11002117 | E80: =(E32+E33)/E68 -> 0.11783485 | F80: =(F32+F33)/F68 -> 0.092661724 | G80: =(G32+G33)/G68 -> 0.1740734
B81: Solvency ratios
B82: Debt ratio | C82: =(C48+C59)/C70 -> 0.36549514 | D82: =(D48+D59)/D70 -> 0.37065046 | E82: =(E48+E59)/E70 -> 0.34174557 | F82: =(F48+F59)/F70 -> 0.28834315 | G82: =(G48+G59)/G70 -> 0.22035868
B83: Debt-Equity ratio | C83: =(C48+C59)/C45 -> 1.4457443 | D83: =(D48+D59)/D45 -> 1.5552247 | E83: =(E48+E59)/E45 -> 1.4390952 | F83: =(F48+F59)/F45 -> 0.96640726 | G83: =(G48+G59)/G45 -> 0.62088839
B84: Interest coverage ratio | C84: ='P&L Input'!C30/'P&L Input'!C32 -> 1.5032017 | D84: ='P&L Input'!D30/'P&L Input'!D32 -> 1.8538075 | E84: ='P&L Input'!E30/'P&L Input'!E32 -> 1.7745555 | F84: ='P&L Input'!F30/'P&L Input'!F32 -> 2.2599442 | G84: ='P&L Input'!G30/'P&L Input'!G32 -> 3.2373013
B85: Debt-service coverage ratio | C85: ='P&L Input'!C26/('P&L Input'!C32+'BS Input'!C48+'BS Input'!C59) -> 0.38833631 | D85: ='P&L Input'!D26/('P&L Input'!D32+'BS Input'!D48+'BS Input'!D59) -> 0.3906528 | E85: ='P&L Input'!E26/('P&L Input'!E32+'BS Input'!E48+'BS Input'!E59) -> 0.45672137 | F85: ='P&L Input'!F26/('P&L Input'!F32+'BS Input'!F48+'BS Input'!F59) -> 0.55703544 | G85: ='P&L Input'!G26/('P&L Input'!G32+'BS Input'!G48+'BS Input'!G59) -> 0.8552302

Sheet CF Input
A1: Bharti Airtel Ltd
B7: Cash Flows from Operating Activities
G8: (INR in millions)
B9: Particulars | C9: FY2022 | D9: FY2023 | E9: FY2024 | F9: FY2025 | G9: FY2026
B10: Profit before tax | C10: 124831 | D10: 165607 | E10: 126790 | F10: 383985 | G10: 451727
B11: Adjustments for:
B12: Depreciation and amortisation expenses | C12: 330907 | D12: 364318 | E12: 395376 | F12: 455703 | G12: 527108
B13: Finance costs | C13: 165241 | D13: 188434 | E13: 219337 | F13: 216258 | G13: 214485
B14: Net gain on FVTPL instruments | C14: -1067 | D14: -2474 | E14: -2645 | F14: -2048 | G14: -3369
B15: Dividend income | C15: - | D15: - | E15: - | F15: - | G15: -272
B16: Interest income | C16: -2206 | D16: -3080 | E16: -6493 | F16: -5306 | G16: -11158
B17: Net (gain)/loss on derivative financial instruments | C17: 947 | D17: 3013 | E17: 6319 | F17: 420 | G17: -2017
B18: Share of profit of associates and JVs (net) | C18: -24232 | D18: -7521 | E18: -27094 | F18: -37030 | G18: -3645
B19: Exceptional items (net) | C19: -11705 | D19: 6698 | E19: 75723 | F19: -72868 | G19: 34175
B20: Employee share based payment expense | C20: 776 | D20: 1115 | E20: 1194 | F20: 1669 | G20: 3157
B21: (Profit)/Loss on sale of PP&E | C21: 74 | D21: 22 | E21: 44 | F21: -1031 | G21: -2985
B22: Provision for doubtful debts / bad debts written off | C22: 3048 | D22: 5664 | E22: 4278 | F22: 3741 | G22: 3586
B23: Other non-cash items | C23: -222 | D23: 485 | E23: 823 | F23: 396 | G23: 2301
B24: Operating cash flows before changes in assets/liabilities | C24: =SUM(C10:C23) -> 586392 | D24: =SUM(D10:D23) -> 722281 | E24: =SUM(E10:E23) -> 793652 | F24: =SUM(F10:F23) -> 943889 | G24: =SUM(G10:G23) -> 1213093
B25: Changes in assets and liabilities
B26: Trade receivables | C26: -7131 | D26: -5583 | E26: -14941 | F26: 29658 | G26: -5654
B27: Trade payables | C27: -4877 | D27: 12671 | E27: 6398 | F27: 8586 | G27: 24977
B28: Inventories | C28: -1181 | D28: -1157 | E28: -771 | F28: -1416 | G28: -1982
B29: Provisions | C29: 2736 | D29: 6494 | E29: 17332 | F29: 22699 | G29: 18276
B30: Other financial and non-financial liabilities | C30: 11655 | D30: -11991 | E30: 41516 | F30: 48154 | G30: 33760
B31: Other financial and non-financial assets | C31: -15674 | D31: -31554 | E31: -25398 | F31: -23868 | G31: 2665
B32: Net cash generated from operations before tax | C32: 571920 | D32: 691161 | E32: 817788 | F32: 1027702 | G32: 1285135
B33: Income tax paid (net) | C33: -21754 | D33: -37915 | E33: -28806 | F33: -44380 | G33: -62839
B34: Net cash generated from operating activities (a) | C34: =C32+C33 -> 550166 | D34: =D32+D33 -> 653246 | E34: =E32+E33 -> 788982 | F34: =F32+F33 -> 983322 | G34: =G32+G33 -> 1222296
B36: Cash Flows from Investing Activities
B37: Purchase of PP&E and capital WIP | C37: -265406 | D37: -260566 | E37: -381915 | F37: -379077 | G37: -451756
B38: Proceeds from sale of PP&E | C38: 13791 | D38: 885 | E38: 1228 | F38: 3382 | G38: 11680
B39: Purchase of intangible assets | C39: -8593 | D39: -4819 | E39: -18600 | F39: -17722 | G39: -15386
B40: Payment towards spectrum* | C40: -174482 | D40: -123684 | E40: -121547 | F40: -213487 | G40: -8546
B41: Proceeds from sale of spectrum | C41: 10048 | D41: - | E41: - | F41: - | G41: -
B42: Proceeds from sale of business | C42: 998 | D42: - | E42: - | F42: - | G42: -
B43: (Purchase)/proceeds sale of current investments (net) | C43: 21298 | D43: -12000 | E43: 19015 | F43: 7100 | G43: -126994
B44: Proceeds from sale of non-current investments | C44: - | D44: 311 | E44: 69 | F44: 300 | G44: 90
B45: Purchase of non-current investments | C45: -89 | D45: -323 | E45: -304 | F45: -734 | G45: -1241
B46: Proceeds from sale of tower subsidiary (net) | C46: 5887 | D46: - | E46: - | F46: - | G46: -
B47: Investment in JV / associates | C47: -26208 | D47: -8106 | E47: -300 | F47: -8788 | G47: -
B48: Repayment of loan given to JV | C48: 8 | D48: - | E48: - | F48: - | G48: 907
B49: Acquisition of subsidiary, net of cash | C49: - | D49: - | E49: -6428 | F49: - | G49: -
B50: Cash disposed off on sale of subsidiaries | C50: - | D50: - | E50: - | F50: -69 | G50: -
B51: Cash acquired on acquisition of subsidiary | C51: - | D51: - | E51: - | F51: 1023 | G51: -
B52: Proceeds from sale of investment in JV | C52: - | D52: - | E52: - | F52: 45 | G52: -
B53: Dividend received | C53: - | D53: 13992 | E53: 1072 | F53: 1090 | G53: 1813
B54: Interest received | C54: 4052 | D54: 3508 | E54: 5671 | F54: 4239 | G54: 4088
B55: Net cash used in investing activities (b) | C55: =SUM(C37:C54) -> -418696 | D55: =SUM(D37:D54) -> -390802 | E55: =SUM(E37:E54) -> -502039 | F55: =SUM(F37:F54) -> -602698 | G55: =SUM(G37:G54) -> -585345
B57: Cash Flows from Financing Activities
B58: Net proceeds from issue of shares | C58: 52226 | D58: 52242 | E58: - | F58: - | G58: 156949
B59: Proceeds from borrowings | C59: 254785 | D59: 136077 | E59: 67123 | F59: 235597 | G59: 140131
B60: Repayment of borrowings | C60: -337212 | D60: -178227 | E60: -100803 | F60: -178594 | G60: -420773
B61: Payment of lease liabilities | C61: -76427 | D61: -75986 | E61: -78552 | F61: -71538 | G61: -67197
B62: (Repayment of)/proceeds from short-term borrowings (net) | C62: 63649 | D62: -70972 | E62: 15516 | F62: 36927 | G62: -44087
B63: Purchase of treasury shares | C63: -598 | D63: -499 | E63: -1368 | F63: -3675 | G63: -1467
B64: Interest and other finance charges paid | C64: -131588 | D64: -66893 | E64: -140263 | F64: -175476 | G64: -148876
B65: Proceeds from exercise of share options | C65: 7 | D65: 3 | E65: 6 | F65: 14 | G65: 20
B66: Dividend paid | C66: -14438 | D66: -35898 | E66: -41845 | F66: -69349 | G66: -113277
B67: Proceeds from issuance of compulsorily convertible preference shares | C67: 10880 | D67: - | E67: - | F67: - | G67: -
B68: Net proceeds from issuance of equity shares to NCI | C68: - | D68: - | E68: - | F68: - | G68: 75
B69: Redemption of perpetual bonds | C69: - | D69: - | E69: - | F69: -86292 | G69: -
B70: Buyback of perpetual bonds from NCI | C70: - | D70: - | E70: -1693 | F70: - | G70: -
B71: Purchase of shares from NCI | C71: -13523 | D71: -641 | E71: -870 | F71: -37348 | G71: -19056
B72: Payment/(proceeds) on maturity of derivatives (net) | C72: -704 | D72: -3901 | E72: 573 | F72: -16427 | G72: -5368
B73: Proceeds from sale of shares of subsidiary to NCI | C73: 40911 | D73: - | E73: 4391 | F73: 829 | G73: -
B74: Net cash used in financing activities (c) | C74: =SUM(C58:C73) -> -152032 | D74: =SUM(D58:D73) -> -244695 | E74: =SUM(E58:E73) -> -277785 | F74: =SUM(F58:F73) -> -365332 | G74: =SUM(G58:G73) -> -522926
B76: Net Increase / (Decrease) in Cash and Cash equivalents (A+B+C) | C76: =SUM(C34,C55,C74) -> -20562 | D76: =SUM(D34,D55,D74) -> 17749 | E76: =SUM(E34,E55,E74) -> 9158 | F76: =SUM(F34,F55,F74) -> 15292 | G76: =SUM(G34,G55,G74) -> 114025
H77: =SUM(H46,H63,H74,H75) -> 0
B78: Effect of exchange rate on cash & cash equivalents | C78: 3919 | D78: -1522 | E78: -8851 | F78: 718 | G78: 23291
B79: Cash & Cash Equivalents at Beginning of the Year | C79: 90630 | D79: =C80 -> 73987 | E79: =D80 -> 90214 | F79: =E80 -> 90521 | G79: =F80 -> 106531
B80: Closing Cash Balance | C80: =SUM(C76:C79) -> 73987 | D80: =SUM(D76:D79) -> 90214 | E80: =SUM(E76:E79) -> 90521 | F80: =SUM(F76:F79) -> 106531 | G80: =SUM(G76:G79) -> 243847

Sheet Common Sizing
A1: Bharti Airtel Ltd
G6: (INR in millions)
B7: Common Sizing
B8: Particulars | C8: 2022 | D8: =C8+1 -> 2023 | E8: =D8+1 -> 2024 | F8: =E8+1 -> 2025 | G8: =F8+1 -> 2026
C9: Audited | D9: Audited | E9: Audited | F9: Audited | G9: Audited
B11: Revenue from Sale of Service | C11: ='P&L Input'!C11/'P&L Input'!C$14 -> 0.9954365 | D11: ='P&L Input'!D11/'P&L Input'!D$14 -> 0.99331389 | E11: ='P&L Input'!E11/'P&L Input'!E$14 -> 0.99052027 | F11: ='P&L Input'!F11/'P&L Input'!F$14 -> 0.9909847 | G11: ='P&L Input'!G11/'P&L Input'!G$14 -> 0.98682212
B12: Other Operating Revenue | C12: ='P&L Input'!C12/'P&L Input'!C$14 -> 0.0045634995 | D12: ='P&L Input'!D12/'P&L Input'!D$14 -> 0.0066861125 | E12: ='P&L Input'!E12/'P&L Input'!E$14 -> 0.0094797309 | F12: ='P&L Input'!F12/'P&L Input'!F$14 -> 0.0090152951 | G12: ='P&L Input'!G12/'P&L Input'!G$14 -> 0.013177879
B14: Total Income | C14: ='P&L Input'!C14/'P&L Input'!C$14 -> 1 | D14: ='P&L Input'!D14/'P&L Input'!D$14 -> 1 | E14: ='P&L Input'!E14/'P&L Input'!E$14 -> 1 | F14: ='P&L Input'!F14/'P&L Input'!F$14 -> 1 | G14: ='P&L Input'!G14/'P&L Input'!G$14 -> 1
B16: Expenses | C16: ='P&L Input'!C16/'P&L Input'!C$14 -> 0 | D16: ='P&L Input'!D16/'P&L Input'!D$14 -> 0 | E16: ='P&L Input'!E16/'P&L Input'!E$14 -> 0 | F16: ='P&L Input'!F16/'P&L Input'!F$14 -> 0 | G16: ='P&L Input'!G16/'P&L Input'!G$14 -> 0
B17: Network operating expenses | C17: ='P&L Input'!C17/'P&L Input'!C$14 -> 0.21370211 | D17: ='P&L Input'!D17/'P&L Input'!D$14 -> 0.20376224 | E17: ='P&L Input'!E17/'P&L Input'!E$14 -> 0.19825146 | F17: ='P&L Input'!F17/'P&L Input'!F$14 -> 0.19193693 | G17: ='P&L Input'!G17/'P&L Input'!G$14 -> 0.18593003
B18: Access charges | C18: ='P&L Input'!C18/'P&L Input'!C$14 -> 0.057747102 | D18: ='P&L Input'!D18/'P&L Input'!D$14 -> 0.054401941 | E18: ='P&L Input'!E18/'P&L Input'!E$14 -> 0.049654004 | F18: ='P&L Input'!F18/'P&L Input'!F$14 -> 0.041082408 | G18: ='P&L Input'!G18/'P&L Input'!G$14 -> 0.025920751
B19: License fee / Spectrum charges | C19: ='P&L Input'!C19/'P&L Input'!C$14 -> 0.094495103 | D19: ='P&L Input'!D19/'P&L Input'!D$14 -> 0.083891937 | E19: ='P&L Input'!E19/'P&L Input'!E$14 -> 0.079487352 | F19: ='P&L Input'!F19/'P&L Input'!F$14 -> 0.079222543 | G19: ='P&L Input'!G19/'P&L Input'!G$14 -> 0.07190651
B20: Employee benefits expense | C20: ='P&L Input'!C20/'P&L Input'!C$14 -> 0.037865174 | D20: ='P&L Input'!D20/'P&L Input'!D$14 -> 0.034485663 | E20: ='P&L Input'!E20/'P&L Input'!E$14 -> 0.035155048 | F20: ='P&L Input'!F20/'P&L Input'!F$14 -> 0.036141956 | G20: ='P&L Input'!G20/'P&L Input'!G$14 -> 0.035461418
B21: Sales and marketing expenses | C21: ='P&L Input'!C21/'P&L Input'!C$14 -> 0.045297623 | D21: ='P&L Input'!D21/'P&L Input'!D$14 -> 0.051722784 | E21: ='P&L Input'!E21/'P&L Input'!E$14 -> 0.071247898 | F21: ='P&L Input'!F21/'P&L Input'!F$14 -> 0.065651766 | G21: ='P&L Input'!G21/'P&L Input'!G$14 -> 0.0613092
B22: Other expenses | C22: ='P&L Input'!C22/'P&L Input'!C$14 -> 0.054927691 | D22: ='P&L Input'!D22/'P&L Input'!D$14 -> 0.056248724 | E22: ='P&L Input'!E22/'P&L Input'!E$14 -> 0.039666406 | F22: ='P&L Input'!F22/'P&L Input'!F$14 -> 0.043265626 | G22: ='P&L Input'!G22/'P&L Input'!G$14 -> 0.046518524
B24: Total Expenses | C24: ='P&L Input'!C24/'P&L Input'!C$14 -> 0.50403481 | D24: ='P&L Input'!D24/'P&L Input'!D$14 -> 0.48451329 | E24: ='P&L Input'!E24/'P&L Input'!E$14 -> 0.47346217 | F24: ='P&L Input'!F24/'P&L Input'!F$14 -> 0.45730123 | G24: ='P&L Input'!G24/'P&L Input'!G$14 -> 0.42704643
B26: EBITDA | C26: ='P&L Input'!C26/'P&L Input'!C$14 -> 0.49596519 | D26: ='P&L Input'!D26/'P&L Input'!D$14 -> 0.51548671 | E26: ='P&L Input'!E26/'P&L Input'!E$14 -> 0.52653783 | F26: ='P&L Input'!F26/'P&L Input'!F$14 -> 0.54269877 | G26: ='P&L Input'!G26/'P&L Input'!G$14 -> 0.57295357
... B43: Net Profit | C43: ='P&L Input'!C43/'P&L Input'!C$14 -> 0.070935385 | D43: ='P&L Input'!D43/'P&L Input'!D$14 -> 0.087716142 | E43: ='P&L Input'!E43/'P&L Input'!E$14 -> 0.056519115 | F43: ='P&L Input'!F43/'P&L Input'!F$14 -> 0.21472007 | G43: ='P&L Input'!G43/'P&L Input'!G$14 -> 0.15820564
B46: ASSETS
B47: Non-current assets
B48: Property, Plant & Equipment | C48: ='BS Input'!C10/'BS Input'!C$38 -> 0.24906093 | D48: ='BS Input'!D10/'BS Input'!D$38 -> 0.21320426 | E48: ='BS Input'!E10/'BS Input'!E$38 -> 0.23983052 | F48: ='BS Input'!F10/'BS Input'!F$38 -> 0.27854477 | G48: ='BS Input'!G10/'BS Input'!G$38 -> 0.28446155
B49: Capital Work-in-Progress | C49: ='BS Input'!C11/'BS Input'!C$38 -> 0.011655521 | D49: ='BS Input'!D11/'BS Input'!D$38 -> 0.024694313 | E49: ='BS Input'!E11/'BS Input'!E$38 -> 0.020038423 | F49: ='BS Input'!F11/'BS Input'!F$38 -> 0.020600731 | G49: ='BS Input'!G11/'BS Input'!G$38 -> 0.022843545
B50: Right-of-use Assets | C50: ='BS Input'!C12/'BS Input'!C$38 -> 0.088623864 | D50: ='BS Input'!D12/'BS Input'!D$38 -> 0.1223523 | E50: ='BS Input'!E12/'BS Input'!E$38 -> 0.12583307 | F50: ='BS Input'!F12/'BS Input'!F$38 -> 0.11711924 | G50: ='BS Input'!G12/'BS Input'!G$38 -> 0.12193101
B51: Goodwill | C51: ='BS Input'!C13/'BS Input'!C$38 -> 0.093031051 | D51: ='BS Input'!D13/'BS Input'!D$38 -> 0.075619323 | E51: ='BS Input'!E13/'BS Input'!E$38 -> 0.059617215 | F51: ='BS Input'!F13/'BS Input'!F$38 -> 0.10050813 | G51: ='BS Input'!G13/'BS Input'!G$38 -> 0.10266365
B52: Other Intangible Assets | C52: ='BS Input'!C14/'BS Input'!C$38 -> 0.24047699 | D52: ='BS Input'!D14/'BS Input'!D$38 -> 0.20990155 | E52: ='BS Input'!E14/'BS Input'!E$38 -> 0.2570183 | F52: ='BS Input'!F14/'BS Input'!F$38 -> 0.25907302 | G52: ='BS Input'!G14/'BS Input'!G$38 -> 0.22685871
B53: Intangible Assets Under Development | C53: ='BS Input'!C15/'BS Input'!C$38 -> 0.0047190202 | D53: ='BS Input'!D15/'BS Input'!D$38 -> 0.085967859 | E53: ='BS Input'!E15/'BS Input'!E$38 -> 0.017988397 | F53: ='BS Input'!F15/'BS Input'!F$38 -> 0.00078291408 | G53: ='BS Input'!G15/'BS Input'!G$38 -> 0.00058860646
B54: Investment in Joint Ventures & Associates | C54: ='BS Input'!C16/'BS Input'!C$38 -> 0.078169479 | D54: ='BS Input'!D16/'BS Input'!D$38 -> 0.063102788 | E54: ='BS Input'!E16/'BS Input'!E$38 -> 0.070277214 | F54: ='BS Input'!F16/'BS Input'!F$38 -> 0.0070798607 | G54: ='BS Input'!G16/'BS Input'!G$38 -> 0.0073570375
B55: Financial Assets
B56: Investments | C56: ='BS Input'!C18/'BS Input'!C$38 -> 0.00016746596 | D56: ='BS Input'!D18/'BS Input'!D$38 -> 0.00014687668 | E56: ='BS Input'!E18/'BS Input'!E$38 -> 0.00020785952 | F56: ='BS Input'!F18/'BS Input'!F$38 -> 0.0010566521 | G56: ='BS Input'!G18/'BS Input'!G$38 -> 0.0020619337
B57: Derivative instruments | C57: ='BS Input'!C19/'BS Input'!C$38 -> 5.9946763e-05 | D57: ='BS Input'!D19/'BS Input'!D$38 -> 0.00019120836 | E57: ='BS Input'!E19/'BS Input'!E$38 -> 1.4622152e-05 | F57: - | G57: -
B58: Trade Receivables | C58: ='BS Input'!C20/'BS Input'!C$38 -> 0 | D58: ='BS Input'!D20/'BS Input'!D$38 -> 0 | E58: ='BS Input'!E20/'BS Input'!E$38 -> 0.00040604592 | F58: ='BS Input'!F20/'BS Input'!F$38 -> 0.00041430095 | G58: ='BS Input'!G20/'BS Input'!G$38 -> 0.00046074303
B59: Loans | F59: ='BS Input'!F21/'BS Input'!F$38 -> 0.00016817002 | G59: -
B60: Other Financial Assets | C60: ='BS Input'!C22/'BS Input'!C$38 -> 0.0061912907 | D60: ='BS Input'!D22/'BS Input'!D$38 -> 0.0058130475 | E60: ='BS Input'!E22/'BS Input'!E$38 -> 0.0059741615 | F60: ='BS Input'!F22/'BS Input'!F$38 -> 0.0072849698 | G60: ='BS Input'!G22/'BS Input'!G$38 -> 0.0064656156
B61: Income Tax Assets (Net) | C61: ='BS Input'!C23/'BS Input'!C$38 -> 0.0048064655 | D61: ='BS Input'!D23/'BS Input'!D$38 -> 0.0045672825 | E61: ='BS Input'!E23/'BS Input'!E$38 -> 0.0031797557 | F61: ='BS Input'!F23/'BS Input'!F$38 -> 0.0048561281 | G61: ='BS Input'!G23/'BS Input'!G$38 -> 0.0036549745
B62: Deferred Tax Assets (Net) | C62: ='BS Input'!C24/'BS Input'!C$38 -> 0.054790791 | D62: ='BS Input'!D24/'BS Input'!D$38 -> 0.042432806 | E62: ='BS Input'!E24/'BS Input'!E$38 -> 0.04328787 | F62: ='BS Input'!F24/'BS Input'!F$38 -> 0.048431217 | G62: ='BS Input'!G24/'BS Input'!G$38 -> 0.034666747
B63: Other Non-current Assets | C63: ='BS Input'!C25/'BS Input'!C$38 -> 0.02517819 | D63: ='BS Input'!D25/'BS Input'!D$38 -> 0.023262489 | E63: ='BS Input'!E25/'BS Input'!E$38 -> 0.025230861 | F63: ='BS Input'!F25/'BS Input'!F$38 -> 0.022676318 | G63: ='BS Input'!G25/'BS Input'!G$38 -> 0.022597055
B64: Total Non-current Assets | C64: ='BS Input'!C26/'BS Input'!C$38 -> 0.856931 | D64: ='BS Input'!D26/'BS Input'!D$38 -> 0.8712561 | E64: ='BS Input'!E26/'BS Input'!E$38 -> 0.86890431 | F64: ='BS Input'!F26/'BS Input'!F$38 -> 0.86859642 | G64: ='BS Input'!G26/'BS Input'!G$38 -> 0.83661118
B65: Current Assets | C65: ='BS Input'!C27/'BS Input'!C$38 -> 0 | D65: ='BS Input'!D27/'BS Input'!D$38 -> 0 | E65: ='BS Input'!E27/'BS Input'!E$38 -> 0 | F65: ='BS Input'!F27/'BS Input'!F$38 -> 0 | G65: ='BS Input'!G27/'BS Input'!G$38 -> 0
B66: Inventories | C66: ='BS Input'!C28/'BS Input'!C$38 -> 0.0010311943 | D66: ='BS Input'!D28/'BS Input'!D$38 -> 0.00057675963 | E66: ='BS Input'!E28/'BS Input'!E$38 -> 0.00081861557 | F66: ='BS Input'!F28/'BS Input'!F$38 -> 0.00087817802 | G66: ='BS Input'!G28/'BS Input'!G$38 -> 0.0010882881
B67: Investments | C67: ='BS Input'!C29/'BS Input'!C$38 -> 0.0023687221 | D67: ='BS Input'!D29/'BS Input'!D$38 -> 0.010533252 | E67: ='BS Input'!E29/'BS Input'!E$38 -> 0.00060625693 | F67: ='BS Input'!F29/'BS Input'!F$38 -> 0.0032140888 | G67: ='BS Input'!G29/'BS Input'!G$38 -> 0.024813113
B68: Derivative Instruments | C68: ='BS Input'!C30/'BS Input'!C$38 -> 0.00015426667 | D68: ='BS Input'!D30/'BS Input'!D$38 -> 0.00028726033 | E68: ='BS Input'!E30/'BS Input'!E$38 -> 0.00026274883 | F68: ='BS Input'!F30/'BS Input'!F$38 -> 0.00015806038 | G68: ='BS Input'!G30/'BS Input'!G$38 -> 0.00091279279
B69: Trade Receivables | C69: ='BS Input'!C31/'BS Input'!C$38 -> 0.011153948 | D69: ='BS Input'!D31/'BS Input'!D$38 -> 0.0089144739 | E69: ='BS Input'!E31/'BS Input'!E$38 -> 0.010635254 | F69: ='BS Input'!F31/'BS Input'!F$38 -> 0.014495089 | G69: ='BS Input'!G31/'BS Input'!G$38 -> 0.014448206
B70: Cash & Cash Equivalents | C70: ='BS Input'!C32/'BS Input'!C$38 -> 0.01676282 | D70: ='BS Input'!D32/'BS Input'!D$38 -> 0.016074488 | E70: ='BS Input'!E32/'BS Input'!E$38 -> 0.015556845 | F70: ='BS Input'!F32/'BS Input'!F$38 -> 0.011870276 | G70: ='BS Input'!G32/'BS Input'!G$38 -> 0.024852233
B71: Other Bank Balances | C71: ='BS Input'!C33/'BS Input'!C$38 -> 0.020344501 | D71: ='BS Input'!D33/'BS Input'!D$38 -> 0.013969405 | E71: ='BS Input'!E33/'BS Input'!E$38 -> 0.021200771 | F71: ='BS Input'!F33/'BS Input'!F$38 -> 0.02063592 | G71: ='BS Input'!G33/'BS Input'!G$38 -> 0.030163093
... B73: Other Current Assets | C73: ='BS Input'!C35/'BS Input'!C$38 -> 0.03221506 | D73: ='BS Input'!D35/'BS Input'!D$38 -> 0.028937168 | E73: ='BS Input'!E35/'BS Input'!E$38 -> 0.025878735 | F73: ='BS Input'!F35/'BS Input'!F$38 -> 0.028114139 | G73: ='BS Input'!G35/'BS Input'!G$38 -> 0.022768747
B74: Assets Held for Sale | C74: - | D74: - | E74: - | F74: - | G74: ='BS Input'!G36/'BS Input'!G$38 -> 0.00010377585
B75: Total Current Assets | C75: ='BS Input'!C37/'BS Input'!C$38 -> 0.143069 | D75: ='BS Input'!D37/'BS Input'!D$38 -> 0.1287439 | E75: ='BS Input'!E37/'BS Input'!E$38 -> 0.13109569 | F75: ='BS Input'!F37/'BS Input'!F$38 -> 0.13140358 | G75: ='BS Input'!G37/'BS Input'!G$38 -> 0.16338882
B76: TOTAL ASSETS | C76: ='BS Input'!C38/'BS Input'!C$38 -> 1 | D76: ='BS Input'!D38/'BS Input'!D$38 -> 1 | E76: ='BS Input'!E38/'BS Input'!E$38 -> 1 | F76: ='BS Input'!F38/'BS Input'!F$38 -> 1 | G76: ='BS Input'!G38/'BS Input'!G$38 -> 1
B78: EQUITY & LIABILITIES
B79: Share Capital | C79: ='BS Input'!C41/'BS Input'!C$70 -> 0.007685835 | D79: ='BS Input'!D41/'BS Input'!D$70 -> 0.0063510729 | E79: ='BS Input'!E41/'BS Input'!E$70 -> 0.0064710898 | F79: ='BS Input'!F41/'BS Input'!F$70 -> 0.0056382645 | G79: ='BS Input'!G41/'BS Input'!G$70 -> 0.0055180498
B80: Other Equity | C80: ='BS Input'!C42/'BS Input'!C$70 -> 0.17532861 | D80: ='BS Input'!D42/'BS Input'!D$70 -> 0.16731022 | E80: ='BS Input'!E42/'BS Input'!E$70 -> 0.17803528 | F80: ='BS Input'!F42/'BS Input'!F$70 -> 0.21535834 | G80: ='BS Input'!G42/'BS Input'!G$70 -> 0.26443788
B81: Equity attributable to Owners | C81: ='BS Input'!C43/'BS Input'!C$70 -> 0.18301444 | D81: ='BS Input'!D43/'BS Input'!D$70 -> 0.1736613 | E81: ='BS Input'!E43/'BS Input'!E$70 -> 0.18450637 | F81: ='BS Input'!F43/'BS Input'!F$70 -> 0.2209966 | G81: ='BS Input'!G43/'BS Input'!G$70 -> 0.26995593
B82: Non-controlling Interests | C82: ='BS Input'!C44/'BS Input'!C$70 -> 0.069793156 | D82: ='BS Input'!D44/'BS Input'!D$70 -> 0.064664696 | E82: ='BS Input'!E44/'BS Input'!E$70 -> 0.05296616 | F82: ='BS Input'!F44/'BS Input'!F$70 -> 0.077369486 | G82: ='BS Input'!G44/'BS Input'!G$70 -> 0.084952756
B83: Total Equity | C83: ='BS Input'!C45/'BS Input'!C$70 -> 0.2528076 | D83: ='BS Input'!D45/'BS Input'!D$70 -> 0.23832599 | E83: ='BS Input'!E45/'BS Input'!E$70 -> 0.23747253 | F83: ='BS Input'!F45/'BS Input'!F$70 -> 0.29836609 | G83: ='BS Input'!G45/'BS Input'!G$70 -> 0.35490869
B84: Non-current liabilities
B85: Financial liabilities
B86: • Borrowings | C86: ='BS Input'!C48/'BS Input'!C$70 -> 0.31220439 | D86: ='BS Input'!D48/'BS Input'!D$70 -> 0.33935811 | E86: ='BS Input'!E48/'BS Input'!E$70 -> 0.29460847 | F86: ='BS Input'!F48/'BS Input'!F$70 -> 0.20387223 | G86: ='BS Input'!G48/'BS Input'!G$70 -> 0.18126344
B87: • Lease liabilities | C87: ='BS Input'!C49/'BS Input'!C$70 -> 0.079900235 | D87: ='BS Input'!D49/'BS Input'!D$70 -> 0.11380592 | E87: ='BS Input'!E49/'BS Input'!E$70 -> 0.12131235 | F87: ='BS Input'!F49/'BS Input'!F$70 -> 0.1082317 | G87: ='BS Input'!G49/'BS Input'!G$70 -> 0.11681502
B88: • Derivative instruments | C88: ='BS Input'!C50/'BS Input'!C$70 -> 4.7847416e-05 | D88: ='BS Input'!D50/'BS Input'!D$70 -> 0.00078879044 | E88: ='BS Input'!E50/'BS Input'!E$70 -> 0.00065012339 | F88: ='BS Input'!F50/'BS Input'!F$70 -> 0 | G88: ='BS Input'!G50/'BS Input'!G$70 -> 0
B89: • Other financial liabilities | C89: ='BS Input'!C51/'BS Input'!C$70 -> 0.024780562 | D89: ='BS Input'!D51/'BS Input'!D$70 -> 0.021787677 | E89: ='BS Input'!E51/'BS Input'!E$70 -> 0.019129375 | F89: ='BS Input'!F51/'BS Input'!F$70 -> 0.0075126312 | G89: ='BS Input'!G51/'BS Input'!G$70 -> 0.0047668068
B90: Deferred revenue | C90: ='BS Input'!C52/'BS Input'!C$70 -> 0.0083205007 | D90: ='BS Input'!D52/'BS Input'!D$70 -> 0.0069186527 | E90: ='BS Input'!E52/'BS Input'!E$70 -> 0.0076797794 | F90: ='BS Input'!F52/'BS Input'!F$70 -> 0.0068405344 | G90: ='BS Input'!G52/'BS Input'!G$70 -> 0.0072778925
B91: Provisions | C91: ='BS Input'!C53/'BS Input'!C$70 -> 0.0012756561 | D91: ='BS Input'!D53/'BS Input'!D$70 -> 0.0010621691 | E91: ='BS Input'!E53/'BS Input'!E$70 -> 0.0012244365 | F91: ='BS Input'!F53/'BS Input'!F$70 -> 0.0059094751 | G91: ='BS Input'!G53/'BS Input'!G$70 -> 0.0063730686
B92: Deferred tax liabilities (net) | C92: ='BS Input'!C54/'BS Input'!C$70 -> 0.0067338364 | D92: ='BS Input'!D54/'BS Input'!D$70 -> 0.0046485573 | E92: ='BS Input'!E54/'BS Input'!E$70 -> 0.0056504496 | F92: ='BS Input'!F54/'BS Input'!F$70 -> 0.018187442 | G92: ='BS Input'!G54/'BS Input'!G$70 -> 0.012277244
B93: Other non-current liabilities | C93: ='BS Input'!C55/'BS Input'!C$70 -> 0.00037480476 | D93: ='BS Input'!D55/'BS Input'!D$70 -> 0.0002303904 | E93: ='BS Input'!E55/'BS Input'!E$70 -> 0.0003306856 | F93: ='BS Input'!F55/'BS Input'!F$70 -> 0.00027490452 | G93: ='BS Input'!G55/'BS Input'!G$70 -> 0.00027112119
B94: Total non-current liabilities | C94: ='BS Input'!C56/'BS Input'!C$70 -> 0.43363783 | D94: ='BS Input'!D56/'BS Input'!D$70 -> 0.48860027 | E94: ='BS Input'!E56/'BS Input'!E$70 -> 0.45058567 | F94: ='BS Input'!F56/'BS Input'!F$70 -> 0.35082891 | G94: ='BS Input'!G56/'BS Input'!G$70 -> 0.3290446
B95: Current liabilities
B96: Financial liabilities
B97: • Borrowings | C97: ='BS Input'!C59/'BS Input'!C$70 -> 0.053290747 | D97: ='BS Input'!D59/'BS Input'!D$70 -> 0.031292345 | E97: ='BS Input'!E59/'BS Input'!E$70 -> 0.047137095 | F97: ='BS Input'!F59/'BS Input'!F$70 -> 0.084470927 | G97: ='BS Input'!G59/'BS Input'!G$70 -> 0.039095241
B98: • Lease liabilities | C98: ='BS Input'!C60/'BS Input'!C$70 -> 0.021193656 | D98: ='BS Input'!D60/'BS Input'!D$70 -> 0.021597141 | E98: ='BS Input'!E60/'BS Input'!E$70 -> 0.021930304 | F98: ='BS Input'!F60/'BS Input'!F$70 -> 0.018780023 | G98: ='BS Input'!G60/'BS Input'!G$70 -> 0.016735802
B99: • Derivative instruments | C99: ='BS Input'!C61/'BS Input'!C$70 -> 0.00027361023 | D99: ='BS Input'!D61/'BS Input'!D$70 -> 0.00025009337 | E99: ='BS Input'!E61/'BS Input'!E$70 -> 0.0027460402 | F99: ='BS Input'!F61/'BS Input'!F$70 -> 0.00037347354 | G99: ='BS Input'!G61/'BS Input'!G$70 -> 0.00034736837
B100: • Trade payables | C100: ='BS Input'!C62/'BS Input'!C$70 -> 0.080499428 | D100: ='BS Input'!D62/'BS Input'!D$70 -> 0.073650145 | E100: ='BS Input'!E62/'BS Input'!E$70 -> 0.079032733 | F100: ='BS Input'!F62/'BS Input'!F$70 -> 0.074176978 | G100: ='BS Input'!G62/'BS Input'!G$70 -> 0.081526885
B101: • Other financial liabilities | C101: ='BS Input'!C63/'BS Input'!C$70 -> 0.053461238 | D101: ='BS Input'!D63/'BS Input'!D$70 -> 0.054172193 | E101: ='BS Input'!E63/'BS Input'!E$70 -> 0.057016496 | F101: ='BS Input'!F63/'BS Input'!F$70 -> 0.064745264 | G101: ='BS Input'!G63/'BS Input'!G$70 -> 0.074012101
B102: Deferred revenue | C102: ='BS Input'!C64/'BS Input'!C$70 -> 0.020879348 | D102: ='BS Input'!D64/'BS Input'!D$70 -> 0.019030157 | E102: ='BS Input'!E64/'BS Input'!E$70 -> 0.019630127 | F102: ='BS Input'!F64/'BS Input'!F$70 -> 0.019000102 | G102: ='BS Input'!G64/'BS Input'!G$70 -> 0.019829156
B103: Provisions | C103: ='BS Input'!C65/'BS Input'!C$70 -> 0.06694486 | D103: ='BS Input'!D65/'BS Input'!D$70 -> 0.057607003 | E103: ='BS Input'!E65/'BS Input'!E$70 -> 0.063726039 | F103: ='BS Input'!F65/'BS Input'!F$70 -> 0.07029157 | G103: ='BS Input'!G65/'BS Input'!G$70 -> 0.064806115
B104: Current tax liabilities (net) | C104: ='BS Input'!C66/'BS Input'!C$70 -> 0.0056990673 | D104: ='BS Input'!D66/'BS Input'!D$70 -> 0.0040238836 | E104: ='BS Input'!E66/'BS Input'!E$70 -> 0.0074305279 | F104: ='BS Input'!F66/'BS Input'!F$70 -> 0.0038951288 | G104: ='BS Input'!G66/'BS Input'!G$70 -> 0.005686844
B105: Other current liabilities | C105: ='BS Input'!C67/'BS Input'!C$70 -> 0.011312614 | D105: ='BS Input'!D67/'BS Input'!D$70 -> 0.011450783 | E105: ='BS Input'!E67/'BS Input'!E$70 -> 0.013292436 | F105: ='BS Input'!F67/'BS Input'!F$70 -> 0.015071534 | G105: ='BS Input'!G67/'BS Input'!G$70 -> 0.014007204
B106: Total current liabilities | C106: ='BS Input'!C68/'BS Input'!C$70 -> 0.31355457 | D106: ='BS Input'!D68/'BS Input'!D$70 -> 0.27307374 | E106: ='BS Input'!E68/'BS Input'!E$70 -> 0.3119418 | F106: ='BS Input'!F68/'BS Input'!F$70 -> 0.350805 | G106: ='BS Input'!G68/'BS Input'!G$70 -> 0.31604672
B107: Total liabilities | C107: ='BS Input'!C69/'BS Input'!C$70 -> 0.7471924 | D107: ='BS Input'!D69/'BS Input'!D$70 -> 0.76167401 | E107: ='BS Input'!E69/'BS Input'!E$70 -> 0.76252747 | F107: ='BS Input'!F69/'BS Input'!F$70 -> 0.70163391 | G107: ='BS Input'!G69/'BS Input'!G$70 -> 0.64509131
B108: Total equity and liabilities | C108: ='BS Input'!C70/'BS Input'!C$70 -> 1 | D108: ='BS Input'!D70/'BS Input'!D$70 -> 1 | E108: ='BS Input'!E70/'BS Input'!E$70 -> 1 | F108: ='BS Input'!F70/'BS Input'!F$70 -> 1 | G108: ='BS Input'!G70/'BS Input'!G$70 -> 1

Sheet Revenue Buildup
A1: Bharti Airtel Ltd
P5: (INR in millions)
B6: Revenue Buildup
B7: Particulars | C7: =FAS!C7 -> 2022 | D7: =FAS!D7 -> 2023 | E7: =FAS!E7 -> 2024 | F7: =FAS!F7 -> 2025 | G7: =FAS!G7 -> 2026 | H7: =FAS!H7 -> 2027 | I7: =FAS!I7 -> 2028 | J7: =FAS!J7 -> 2029 | ... Q7: =FAS!Q7 -> 2036
C8: Audited | D8: Audited | E8: Audited | F8: Audited | G8: Audited | H8: Estimated | I8: Projected | J8: Projected | K8: Projected | L8: Projected | M8: Projected | N8: Projected | O8: Projected | P8: Projected | Q8: Projected
B10: Sale of Service | C10: =C76 -> 1165469 | D10: =D76 -> 1391448 | E10: =E76 -> 1499824 | F10: =F76 -> 1729852 | G10: =G76 -> 2109728 | H10: =H76 -> 2507801.6 | I10: =I76 -> 2823455.7 | J10: =J76 -> 3149592.4 | ... Q10: =Q76 -> 5195687.7
B11: Other Operating Revenues | C11: 5343 | D11: 9366 | E11: 14354 | F11: 15737 | G11: 28173 | H11: =H12*H10 -> 33488.816 | I11: =I12*I10 -> 37704.016 | J11: =J12*J10 -> 42059.198 | K11: =K12*K10 -> 46482.213 | L11: =L12*L10 -> 50890.149 | M11: =M12*M10 -> 55191.54 | N11: =N12*N10 -> 59289.291 | O11: =O12*O10 -> 63084.215 | ... Q11: =Q12*Q10 -> 69382.456
B12: (% on total Revenue) | C12: =C11/C10 -> 0.0045844205 | D12: =D11/D10 -> 0.0067311175 | E12: =E11/E10 -> 0.0095704563 | F12: =F11/F10 -> 0.0090973101 | G12: =G11/G10 -> 0.013353854 | H12: =G12 -> 0.013353854 | I12: =H12 -> 0.013353854 | J12: =I12 -> 0.013353854 | K12: =J12 -> 0.013353854 | L12: =K12 -> 0.013353854 | M12: =L12 -> 0.013353854 | N12: =M12 -> 0.013353854 | O12: =N12 -> 0.013353854 | ... Q12: =P12 -> 0.013353854
B14: Revenue from Operations | C14: =C10+C11 -> 1170812 | D14: =D10+D11 -> 1400814 | E14: =E10+E11 -> 1514178 | F14: =F10+F11 -> 1745589 | G14: =G10+G11 -> 2137901 | H14: =H10+H11 -> 2541290.4 | I14: =I10+I11 -> 2861159.8 | J14: =J10+J11 -> 3191651.6 | ... Q14: =Q10+Q11 -> 5265070.2
B15: Y-O-Y Growth | D15: =D14/C14-1 -> 0.19644657 | E15: =E14/D14-1 -> 0.080927232 | F15: =F14/E14-1 -> 0.15282946 | G15: =G14/F14-1 -> 0.22474477 | H15: =H14/G14-1 -> 0.18868477 | I15: =I14/H14-1 -> 0.12586889 | J15: =J14/I14-1 -> 0.11550975 | K15: =K14/J14-1 -> 0.10516165 | ... Q15: =Q14/P14-1 -> 0.043674675
B17: Share of Profit/(Loss) of Associates | C17: ='P&L Input'!C33 -> -24232 | D17: ='P&L Input'!D33 -> -7521 | E17: ='P&L Input'!E33 -> -27094 | F17: ='P&L Input'!F33 -> -37030 | G17: ='P&L Input'!G33 -> -3645 | H17: =H10*H18 -> -33803.03 | I17: =I10*I18 -> -38057.78 | J17: =J10*J18 -> -42453.824 | K17: =K10*K18 -> -46918.339 | L17: =L10*L18 -> -51367.633 | M17: =M10*M18 -> -55709.382 | N17: =N10*N18 -> -59845.582 | O17: =O10*O18 -> -63676.112 | ... Q17: =Q10*Q18 -> -70033.447
C18: =C17/C10 -> -0.02079163 | D18: =D17/D10 -> -0.0054051607 | E18: =E17/E10 -> -0.018064786 | F18: =F17/F10 -> -0.021406456 | G18: =G17/G10 -> -0.0017277109 | H18: =AVERAGE(C18:G18) -> -0.013479149 | I18: =H18 -> -0.013479149 | J18: =I18 -> -0.013479149 | K18: =J18 -> -0.013479149 | L18: =K18 -> -0.013479149 | M18: =L18 -> -0.013479149 | N18: =M18 -> -0.013479149 | O18: =N18 -> -0.013479149 | P18: =O18 -> -0.013479149 | Q18: =P18 -> -0.013479149
B20: ='P&L Input'!B37 -> Exceptional items | C20: ='P&L Input'!C37 -> -16986 | D20: ='P&L Input'!D37 -> 6698 | E20: ='P&L Input'!E37 -> 75723 | F20: ='P&L Input'!F37 -> -72868 | G20: ='P&L Input'!G37 -> 34175 | H20: =H10*H21 -> 7424.1759 | I20: =I10*I21 -> 18260.408 | J20: =J10*J21 -> 21411.363 | K20: =K10*K21 -> -6752.1412 | L20: =L10*L21 -> 23234.969 | M20: =M10*M21 -> 16848.714 | N20: =N10*N21 -> 19090.813 | O20: =O10*O21 -> 18264.853 | ... Q20: =Q10*Q21 -> 22465.982
C21: =C20/C10 -> -0.01457439 | D21: =D20/D10 -> 0.0048136905 | E21: =E20/E10 -> 0.050487924 | F21: =F20/F10 -> -0.042123835 | G21: =G20/G10 -> 0.016198771 | H21: =AVERAGE(C21:G21) -> 0.002960432 | I21: =AVERAGE(D21:H21) -> 0.0064673964 | J21: =AVERAGE(E21:I21) -> 0.0067981376 | K21: =AVERAGE(F21:J21) -> -0.0019398196 | L21: =AVERAGE(G21:K21) -> 0.0060969834 | M21: =AVERAGE(H21:L21) -> 0.004076626 | N21: =AVERAGE(I21:M21) -> 0.0042998648 | O21: =AVERAGE(J21:N21) -> 0.0038663584 | ... Q21: =AVERAGE(L21:P21) -> 0.004323967
B25: Revenue by Service Line | C25: 2022 | D25: =C25+1 -> 2023 | E25: =D25+1 -> 2024 | F25: =E25+1 -> 2025 | G25: =F25+1 -> 2026 | H25: =G25+1 -> 2027 | I25: =H25+1 -> 2028 | J25: =I25+1 -> 2029 | K25: =J25+1 -> 2030 | ... Q25: =P25+1 -> 2036
B26: Mobile Services India | C26: 629149 | D26: 759246 | E26: 850488 | F26: 1002500 | G26: 1129954 | H26: =G26*(1+H27) -> 1308720.7 | I26: =H26*(1+I27) -> 1500064.9 | J26: =I26*(1+J27) -> 1701384.1 | K26: =J26*(1+K27) -> 1909305.3 | L26: =K26*(1+L27) -> 2119724.2 | M26: =L26*(1+M27) -> 2327896 | N26: =M26*(1+N27) -> 2528577 | O26: =N26*(1+O27) -> 2716215.3 | ... Q26: =P26*(1+Q27) -> 3030039.5
D27: =IFERROR(D26/C26-1,"") -> 0.2067825 | E27: =IFERROR(E26/D26-1,"") -> 0.12017449 | F27: =IFERROR(F26/E26-1,"") -> 0.17873503 | G27: =IFERROR(G26/F26-1,"") -> 0.12713616 | H27: =CHOOSE(Assumptions!$D$18,H28,H29,H30) -> 0.15820704 | I27: =CHOOSE(Assumptions!$D$18,I28,I29,I30) -> 0.14620704 | J27: =CHOOSE(Assumptions!$D$18,J28,J29,J30) -> 0.13420704 | K27: =CHOOSE(Assumptions!$D$18,K28,K29,K30) -> 0.12220704 | L27: =CHOOSE(Assumptions!$D$18,L28,L29,L30) -> 0.11020704 | M27: =CHOOSE(Assumptions!$D$18,M28,M29,M30) -> 0.098207044 | N27: =CHOOSE(Assumptions!$D$18,N28,N29,N30) -> 0.086207044 | O27: =CHOOSE(Assumptions!$D$18,O28,O29,O30) -> 0.074207044 | ... Q27: =CHOOSE(Assumptions!$D$18,Q28,Q29,Q30) -> 0.050207044
H28: =H29+0.05 -> 0.20820704 | I28: =I29+0.05 -> 0.19620704 | J28: =J29+0.05 -> 0.18420704 | K28: =K29+0.05 -> 0.17220704 | L28: =L29+0.05 -> 0.16020704 | M28: =M29+0.05 -> 0.14820704 | N28: =N29+0.05 -> 0.13620704 | O28: =O29+0.05 -> 0.12420704 | ... Q28: =Q29+0.05 -> 0.10020704
H29: =AVERAGE(D27:G27) -> 0.15820704 | I29: =H29-0.012 -> 0.14620704 | J29: =I29-0.012 -> 0.13420704 | K29: =J29-0.012 -> 0.12220704 | L29: =K29-0.012 -> 0.11020704 | M29: =L29-0.012 -> 0.098207044 | N29: =M29-0.012 -> 0.086207044 | O29: =N29-0.012 -> 0.074207044 | P29: =O29-0.012 -> 0.062207044 | Q29: =P29-0.012 -> 0.050207044
H30: =H29-0.05 -> 0.10820704 | I30: =I29-0.05 -> 0.096207044 | J30: =J29-0.05 -> 0.084207044 | K30: =K29-0.05 -> 0.072207044 | L30: =L29-0.05 -> 0.060207044 | M30: =M29-0.05 -> 0.048207044 | N30: =N29-0.05 -> 0.036207044 | O30: =O29-0.05 -> 0.024207044 | ... Q30: =Q29-0.05 -> 0.00020704393
B32: Mobile Services Africa | C32: 350612 | D32: 422664 | E32: 411841 | F32: 418795 | G32: 568064 | H32: =G32*(1+H33) -> 646628.25 | I32: =H32*(1+I33) -> 728298.53 | J32: =I32*(1+J33) -> 811544.34 | K32: =J32*(1+K33) -> 894566.75 | L32: =K32*(1+L33) -> 975347.7 | M32: =L32*(1+M33) -> 1051719.1 | N32: =M32*(1+N33) -> 1121450 | O32: =N32*(1+O33) -> 1182346.7 | ... Q32: =P32*(1+Q33) -> 1269704.7
D33: =IFERROR(D32/C32-1,"") -> 0.20550352 | E33: =IFERROR(E32/D32-1,"") -> -0.025606628 | F33: =IFERROR(F32/E32-1,"") -> 0.016885157 | G33: =IFERROR(G32/F32-1,"") -> 0.35642498 | H33: =CHOOSE(Assumptions!$D$18,H34,H35,H36) -> 0.13830176 | I33: =CHOOSE(Assumptions!$D$18,I34,I35,I36) -> 0.12630176 | J33: =CHOOSE(Assumptions!$D$18,J34,J35,J36) -> 0.11430176 | K33: =CHOOSE(Assumptions!$D$18,K34,K35,K36) -> 0.10230176 | L33: =CHOOSE(Assumptions!$D$18,L34,L35,L36) -> 0.090301757 | M33: =CHOOSE(Assumptions!$D$18,M34,M35,M36) -> 0.078301757 | N33: =CHOOSE(Assumptions!$D$18,N34,N35,N36) -> 0.066301757 | O33: =CHOOSE(Assumptions!$D$18,O34,O35,O36) -> 0.054301757 | ... Q33: =CHOOSE(Assumptions!$D$18,Q34,Q35,Q36) -> 0.030301757
H34: =H35+0.05 -> 0.18830176 | I34: =I35+0.05 -> 0.17630176 | J34: =J35+0.05 -> 0.16430176 | K34: =K35+0.05 -> 0.15230176 | L34: =L35+0.05 -> 0.14030176 | M34: =M35+0.05 -> 0.12830176 | N34: =N35+0.05 -> 0.11630176 | O34: =O35+0.05 -> 0.10430176 | ... Q34: =Q35+0.05 -> 0.080301757
H35: =AVERAGE(D33:G33) -> 0.13830176 | I35: =H35-0.012 -> 0.12630176 | J35: =I35-0.012 -> 0.11430176 | K35: =J35-0.012 -> 0.10230176 | L35: =K35-0.012 -> 0.090301757 | M35: =L35-0.012 -> 0.078301757 | N35: =M35-0.012 -> 0.066301757 | O35: =N35-0.012 -> 0.054301757 | P35: =O35-0.012 -> 0.042301757 | Q35: =P35-0.012 -> 0.030301757
H36: =H35-0.05 -> 0.088301757 | I36: =I35-0.05 -> 0.076301757 | J36: =J35-0.05 -> 0.064301757 | K36: =K35-0.05 -> 0.052301757 | L36: =L35-0.05 -> 0.040301757 | M36: =M35-0.05 -> 0.028301757 | N36: =N35-0.05 -> 0.016301757 | O36: =O35-0.05 -> 0.0043017574 | ... Q36: =Q35-0.05 -> -0.019698243
B38: Mobile Services South Asia | C38: 3869 | D38: 2944 | E38: 3773 | F38: 941 | G38: 0 | H38: 0 | I38: 0 | J38: 0 | K38: 0 | L38: 0 | M38: 0 | N38: 0 | O38: 0 | P38: 0 | Q38: 0
D39: =IFERROR(D38/C38-1,"") -> -0.23907987 | E39: =IFERROR(E38/D38-1,"") -> 0.28158967 | F39: =IFERROR(F38/E38-1,"") -> -0.75059634 | G39: =IFERROR(G38/F38-1,"") -> -1
B44: Airtel Business | C44: 160702 | D44: 185931 | E44: 208209 | F44: 220935 | G44: 211766 | H44: =G44*(1+H45) -> 227459.53 | I44: =H44*(1+I45) -> 241586.55 | J44: =I44*(1+J45) -> 253691.94 | K44: =J44*(1+K45) -> 263359.6 | L44: =K44*(1+L45) -> 270235.36 | M44: =L44*(1+M45) -> 274047.8 | N44: =M44*(1+N45) -> 274625.46 | O44: =N44*(1+O45) -> 271908.83 | ... Q44: =P44*(1+Q45) -> 256942.34
D45: =IFERROR(D44/C44-1,"") -> 0.15699245 | E45: =IFERROR(E44/D44-1,"") -> 0.11981864 | F45: =IFERROR(F44/E44-1,"") -> 0.061121277 | G45: =IFERROR(G44/F44-1,"") -> -0.041500894 | H45: =CHOOSE(Assumptions!$D$18,H46,H47,H48) -> 0.074107868 | I45: =CHOOSE(Assumptions!$D$18,I46,I47,I48) -> 0.062107868 | J45: =CHOOSE(Assumptions!$D$18,J46,J47,J48) -> 0.050107868 | K45: =CHOOSE(Assumptions!$D$18,K46,K47,K48) -> 0.038107868 | L45: =CHOOSE(Assumptions!$D$18,L46,L47,L48) -> 0.026107868 | M45: =CHOOSE(Assumptions!$D$18,M46,M47,M48) -> 0.014107868 | N45: =CHOOSE(Assumptions!$D$18,N46,N47,N48) -> 0.0021078678 | O45: =CHOOSE(Assumptions!$D$18,O46,O47,O48) -> -0.0098921322 | ... Q45: =CHOOSE(Assumptions!$D$18,Q46,Q47,Q48) -> -0.033892132
H46: =H47+0.05 -> 0.12410787 | I46: =I47+0.05 -> 0.11210787 | J46: =J47+0.05 -> 0.10010787 | K46: =K47+0.05 -> 0.088107868 | L46: =L47+0.05 -> 0.076107868 | M46: =M47+0.05 -> 0.064107868 | N46: =N47+0.05 -> 0.052107868 | O46: =O47+0.05 -> 0.040107868 | ... Q46: =Q47+0.05 -> 0.016107868
H47: =AVERAGE(D45:G45) -> 0.074107868 | I47: =H47-0.012 -> 0.062107868 | J47: =I47-0.012 -> 0.050107868 | K47: =J47-0.012 -> 0.038107868 | L47: =K47-0.012 -> 0.026107868 | M47: =L47-0.012 -> 0.014107868 | N47: =M47-0.012 -> 0.0021078678 | O47: =N47-0.012 -> -0.0098921322 | P47: =O47-0.012 -> -0.021892132 | Q47: =P47-0.012 -> -0.033892132
H48: =H47-0.05 -> 0.024107868 | I48: =I47-0.05 -> 0.012107868 | J48: =J47-0.05 -> 0.00010786782 | K48: =K47-0.05 -> -0.011892132 | L48: =L47-0.05 -> -0.023892132 | M48: =M47-0.05 -> -0.035892132 | N48: =N47-0.05 -> -0.047892132 | O48: =O47-0.05 -> -0.059892132 | ... Q48: =Q47-0.05 -> -0.083892132
B50: Passive Infrastructure Services | C50: 0 | D50: 0 | E50: 0 | F50: 112920 | G50: 326944 | H50: =G50*(1+H51) -> 353099.52 | I50: =H50*(1+I51) -> 377110.29 | J50: =I50*(1+J51) -> 398228.46 | K50: =J50*(1+K51) -> 415750.52 | L50: =K50*(1+L51) -> 429054.53 | M50: =L50*(1+M51) -> 437635.62 | N50: =M50*(1+N51) -> 441136.71 | O50: =N50*(1+O51) -> 439372.16 | ... Q50: =P50*(1+Q51) -> 420236.62
D51: =IFERROR(D50/C50-1,"") | E51: =IFERROR(E50/D50-1,"") | F51: =IFERROR(F50/E50-1,"") | G51: =IFERROR(G50/F50-1,"") -> 1.8953595 | H51: =CHOOSE(Assumptions!$D$18,H52,H53,H54) -> 0.08 | I51: =CHOOSE(Assumptions!$D$18,I52,I53,I54) -> 0.068 | J51: =CHOOSE(Assumptions!$D$18,J52,J53,J54) -> 0.056 | K51: =CHOOSE(Assumptions!$D$18,K52,K53,K54) -> 0.044 | L51: =CHOOSE(Assumptions!$D$18,L52,L53,L54) -> 0.032 | M51: =CHOOSE(Assumptions!$D$18,M52,M53,M54) -> 0.02 | N51: =CHOOSE(Assumptions!$D$18,N52,N53,N54) -> 0.008 | O51: =CHOOSE(Assumptions!$D$18,O52,O53,O54) -> -0.004 | ... Q51: =CHOOSE(Assumptions!$D$18,Q52,Q53,Q54) -> -0.028
H52: =H53+0.05 -> 0.13 | I52: =I53+0.05 -> 0.118 | J52: =J53+0.05 -> 0.106 | K52: =K53+0.05 -> 0.094 | L52: =L53+0.05 -> 0.082 | M52: =M53+0.05 -> 0.07 | N52: =N53+0.05 -> 0.058 | O52: =O53+0.05 -> 0.046 | ... Q52: =Q53+0.05 -> 0.022
H53: 0.08 | I53: =H53-0.012 -> 0.068 | J53: =I53-0.012 -> 0.056 | K53: =J53-0.012 -> 0.044 | L53: =K53-0.012 -> 0.032 | M53: =L53-0.012 -> 0.02 | N53: =M53-0.012 -> 0.008 | O53: =N53-0.012 -> -0.004 | P53: =O53-0.012 -> -0.016 | Q53: =P53-0.012 -> -0.028
H54: =H53-0.05 -> 0.03 | I54: =I53-0.05 -> 0.018 | J54: =J53-0.05 -> 0.006 | K54: =K53-0.05 -> -0.006 | L54: =L53-0.05 -> -0.018 | M54: =M53-0.05 -> -0.03 | N54: =N53-0.05 -> -0.042 | O54: =O53-0.05 -> -0.054 | ... Q54: =Q53-0.05 -> -0.078
B56: Homes Services | C56: 30390 | D56: 40472 | E56: 49701 | F56: 59044 | G56: 77747 | H56: =G56*(1+H57) -> 98438.12 | I56: =H56*(1+I57) -> 123454.59 | J56: =I56*(1+J57) -> 153347.15 | K56: =J56*(1+K57) -> 188637.54 | L56: =K56*(1+L57) -> 229785.8 | M56: =L56*(1+M57) -> 277152.46 | N56: =M56*(1+N57) -> 330957.17 | O56: =N56*(1+O57) -> 391235.73 | ... Q56: =P56*(1+Q57) -> 530191.69
D57: =IFERROR(D56/C56-1,"") -> 0.33175387 | E57: =IFERROR(E56/D56-1,"") -> 0.2280342 | F57: =IFERROR(F56/E56-1,"") -> 0.18798415 | G57: =IFERROR(G56/F56-1,"") -> 0.31676377 | H57: =CHOOSE(Assumptions!$D$18,H58,H59,H60) -> 0.26613399 | I57: =CHOOSE(Assumptions!$D$18,I58,I59,I60) -> 0.25413399 | J57: =CHOOSE(Assumptions!$D$18,J58,J59,J60) -> 0.24213399 | K57: =CHOOSE(Assumptions!$D$18,K58,K59,K60) -> 0.23013399 | L57: =CHOOSE(Assumptions!$D$18,L58,L59,L60) -> 0.21813399 | M57: =CHOOSE(Assumptions!$D$18,M58,M59,M60) -> 0.20613399 | N57: =CHOOSE(Assumptions!$D$18,N58,N59,N60) -> 0.19413399 | O57: =CHOOSE(Assumptions!$D$18,O58,O59,O60) -> 0.18213399 | ... Q57: =CHOOSE(Assumptions!$D$18,Q58,Q59,Q60) -> 0.15813399
H58: =H59+0.05 -> 0.31613399 | I58: =I59+0.05 -> 0.30413399 | J58: =J59+0.05 -> 0.29213399 | K58: =K59+0.05 -> 0.28013399 | L58: =L59+0.05 -> 0.26813399 | M58: =M59+0.05 -> 0.25613399 | N58: =N59+0.05 -> 0.24413399 | O58: =O59+0.05 -> 0.23213399 | ... Q58: =Q59+0.05 -> 0.20813399
H59: =AVERAGE(D57:G57) -> 0.26613399 | I59: =H59-0.012 -> 0.25413399 | J59: =I59-0.012 -> 0.24213399 | K59: =J59-0.012 -> 0.23013399 | L59: =K59-0.012 -> 0.21813399 | M59: =L59-0.012 -> 0.20613399 | N59: =M59-0.012 -> 0.19413399 | O59: =N59-0.012 -> 0.18213399 | P59: =O59-0.012 -> 0.17013399 | Q59: =P59-0.012 -> 0.15813399
H60: =H59-0.05 -> 0.21613399 | I60: =I59-0.05 -> 0.20413399 | J60: =J59-0.05 -> 0.19213399 | K60: =K59-0.05 -> 0.18013399 | L60: =L59-0.05 -> 0.16813399 | M60: =M59-0.05 -> 0.15613399 | N60: =N59-0.05 -> 0.14413399 | O60: =O59-0.05 -> 0.13213399 | ... Q60: =Q59-0.05 -> 0.10813399
B62: Digital TV Services | C62: 31538 | D62: 29450 | E62: 30448 | F62: 30608 | G62: 30179 | H62: =G62*(1+H63) -> 29869.069 | I62: =H62*(1+I63) -> 29203.893 | J62: =I62*(1+J63) -> 28203.083 | K62: =J62*(1+K63) -> 26898.133 | L62: =K62*(1+L63) -> 25330.786 | M62: =L62*(1+M63) -> 23550.798 | N62: =M62*(1+N63) -> 21613.28 | O62: =N62*(1+O63) -> 19575.801 | ... Q62: =P62*(1+Q63) -> 15426.299
D63: =IFERROR(D62/C62-1,"") -> -0.066205847 | E63: =IFERROR(E62/D62-1,"") -> 0.033887946 | F63: =IFERROR(F62/E62-1,"") -> 0.0052548607 | G63: =IFERROR(G62/F62-1,"") -> -0.014015944 | H63: =CHOOSE(Assumptions!$D$18,H64,H65,H66) -> -0.010269746 | I63: =CHOOSE(Assumptions!$D$18,I64,I65,I66) -> -0.022269746 | J63: =CHOOSE(Assumptions!$D$18,J64,J65,J66) -> -0.034269746 | K63: =CHOOSE(Assumptions!$D$18,K64,K65,K66) -> -0.046269746 | L63: =CHOOSE(Assumptions!$D$18,L64,L65,L66) -> -0.058269746 | M63: =CHOOSE(Assumptions!$D$18,M64,M65,M66) -> -0.070269746 | N63: =CHOOSE(Assumptions!$D$18,N64,N65,N66) -> -0.082269746 | O63: =CHOOSE(Assumptions!$D$18,O64,O65,O66) -> -0.094269746 | ... Q63: =CHOOSE(Assumptions!$D$18,Q64,Q65,Q66) -> -0.11826975
H64: =H65+0.05 -> 0.039730254 | I64: =I65+0.05 -> 0.027730254 | J64: =J65+0.05 -> 0.015730254 | K64: =K65+0.05 -> 0.003730254 | L64: =L65+0.05 -> -0.008269746 | M64: =M65+0.05 -> -0.020269746 | N64: =N65+0.05 -> -0.032269746 | O64: =O65+0.05 -> -0.044269746 | ... Q64: =Q65+0.05 -> -0.068269746
H65: =AVERAGE(D63:G63) -> -0.010269746 | I65: =H65-0.012 -> -0.022269746 | J65: =I65-0.012 -> -0.034269746 | K65: =J65-0.012 -> -0.046269746 | L65: =K65-0.012 -> -0.058269746 | M65: =L65-0.012 -> -0.070269746 | N65: =M65-0.012 -> -0.082269746 | O65: =N65-0.012 -> -0.094269746 | P65: =O65-0.012 -> -0.10626975 | Q65: =P65-0.012 -> -0.11826975
H66: =H65-0.05 -> -0.060269746 | I66: =I65-0.05 -> -0.072269746 | J66: =J65-0.05 -> -0.084269746 | K66: =K65-0.05 -> -0.096269746 | L66: =L65-0.05 -> -0.10826975 | M66: =M65-0.05 -> -0.12026975 | N66: =N65-0.05 -> -0.13226975 | O66: =O65-0.05 -> -0.14426975 | ... Q66: =Q65-0.05 -> -0.16826975
B68: Others | C68: 355 | D68: 855 | E68: 1875 | F68: 3478 | G68: 3883 | H68: =G68*(1+H69) -> 4271.3 | I68: =H68*(1+I69) -> 4647.1744 | J68: =I68*(1+J69) -> 5000.3597 | K68: =J68*(1+K69) -> 5320.3827 | L68: =K68*(1+L69) -> 5597.0426 | M68: =L68*(1+M69) -> 5820.9243 | N68: =M68*(1+N69) -> 5983.9102 | O68: =N68*(1+O69) -> 6079.6527 | ... Q68: =P68*(1+Q69) -> 6055.1396
D69: =IFERROR(D68/C68-1,"") -> 1.4084507 | E69: =IFERROR(E68/D68-1,"") -> 1.1929825 | F69: =IFERROR(F68/E68-1,"") -> 0.85493333 | G69: =IFERROR(G68/F68-1,"") -> 0.11644623 | H69: =CHOOSE(Assumptions!$D$18,H70,H71,H72) -> 0.1 | I69: =CHOOSE(Assumptions!$D$18,I70,I71,I72) -> 0.088 | J69: =CHOOSE(Assumptions!$D$18,J70,J71,J72) -> 0.076 | K69: =CHOOSE(Assumptions!$D$18,K70,K71,K72) -> 0.064 | L69: =CHOOSE(Assumptions!$D$18,L70,L71,L72) -> 0.052 | M69: =CHOOSE(Assumptions!$D$18,M70,M71,M72) -> 0.04 | N69: =CHOOSE(Assumptions!$D$18,N70,N71,N72) -> 0.028 | O69: =CHOOSE(Assumptions!$D$18,O70,O71,O72) -> 0.016 | ... Q69: =CHOOSE(Assumptions!$D$18,Q70,Q71,Q72) -> -0.008
H70: =H71+0.05 -> 0.15 | I70: =I71+0.05 -> 0.138 | J70: =J71+0.05 -> 0.126 | K70: =K71+0.05 -> 0.114 | L70: =L71+0.05 -> 0.102 | M70: =M71+0.05 -> 0.09 | N70: =N71+0.05 -> 0.078 | O70: =O71+0.05 -> 0.066 | ... Q70: =Q71+0.05 -> 0.042
H71: 0.1 | I71: =H71-0.012 -> 0.088 | J71: =I71-0.012 -> 0.076 | K71: =J71-0.012 -> 0.064 | L71: =K71-0.012 -> 0.052 | M71: =L71-0.012 -> 0.04 | N71: =M71-0.012 -> 0.028 | O71: =N71-0.012 -> 0.016 | P71: =O71-0.012 -> 0.004 | Q71: =P71-0.012 -> -0.008
H72: =H71-0.05 -> 0.05 | I72: =I71-0.05 -> 0.038 | J72: =J71-0.05 -> 0.026 | K72: =K71-0.05 -> 0.014 | L72: =L71-0.05 -> 0.002 | M72: =M71-0.05 -> -0.01 | N72: =N71-0.05 -> -0.022 | O72: =O71-0.05 -> -0.034 | ... Q72: =Q71-0.05 -> -0.058
B74: Total segment revenue | C74: =C26+C32+C38+C44+C50+C56+C62+C68 -> 1206615 | D74: =D26+D32+D38+D44+D50+D56+D62+D68 -> 1441562 | E74: =E26+E32+E38+E44+E50+E56+E62+E68 -> 1556335 | F74: =F26+F32+F38+F44+F50+F56+F62+F68 -> 1849221 | G74: =G26+G32+G38+G44+G50+G56+G62+G68 -> 2348537 | H74: =H26+H32+H38+H44+H50+H56+H62+H68 -> 2668486.5 | I74: =I26+I32+I38+I44+I50+I56+I62+I68 -> 3004365.9 | J74: =J26+J32+J38+J44+J50+J56+J62+J68 -> 3351399.5 | ... Q74: =Q26+Q32+Q38+Q44+Q50+Q56+Q62+Q68 -> 5528596.3
B75: Less: Inter-segment eliminations | C75: 41146 | D75: 50114 | E75: 56511 | F75: 119369 | G75: 238809 | H75: =AVERAGE(C75:G75)/AVERAGE(C74:G74)*H74 -> 160684.92 | I75: =H75/H74*I74 -> 180910.15 | J75: =I75/I74*J74 -> 201807.04 | K75: =J75/J74*K74 -> 223029.4 | L75: =K75/K74*L74 -> 244179.41 | M75: =L75/L74*M74 -> 264818.2 | N75: =M75/M74*N74 -> 284479.89 | O75: =N75/N74*O74 -> 302688.57 | P75: =O75/O74*P74 -> 318977.35 | Q75: =P75/P74*Q74 -> 332908.58
B76: Total revenue | C76: =C74-C75 -> 1165469 | D76: =D74-D75 -> 1391448 | E76: =E74-E75 -> 1499824 | F76: =F74-F75 -> 1729852 | G76: =G74-G75 -> 2109728 | H76: =H74-H75 -> 2507801.6 | I76: =I74-I75 -> 2823455.7 | J76: =J74-J75 -> 3149592.4 | ... Q76: =Q74-Q75 -> 5195687.7

Sheet Cost Builup
A1: Bharti Airtel Ltd
B7: Cost Build-up
B8: Particulars | C8: =FAS!C7 -> 2022 | D8: =FAS!D7 -> 2023 | E8: =FAS!E7 -> 2024 | F8: =FAS!F7 -> 2025 | G8: =FAS!G7 -> 2026 | H8: =FAS!H7 -> 2027 | I8: =FAS!I7 -> 2028 | J8: =FAS!J7 -> 2029 | ... Q8: =FAS!Q7 -> 2036
C9: Audited | D9: Audited | E9: Audited | F9: Audited | G9: Audited | H9: Estimated | I9: Projected | J9: Projected | K9: Projected | L9: Projected | M9: Projected | N9: Projected | O9: Projected | P9: Projected | Q9: Projected
B11: Revenue from Operations | C11: ='Revenue Buildup'!C14 -> 1170812 | D11: ='Revenue Buildup'!D14 -> 1400814 | E11: ='Revenue Buildup'!E14 -> 1514178 | F11: ='Revenue Buildup'!F14 -> 1745589 | G11: ='Revenue Buildup'!G14 -> 2137901 | H11: ='Revenue Buildup'!H14 -> 2541290.4 | I11: ='Revenue Buildup'!I14 -> 2861159.8 | J11: ='Revenue Buildup'!J14 -> 3191651.6 | ... Q11: ='Revenue Buildup'!Q14 -> 5265070.2
B13: ='P&L Input'!B17 -> Network operating expenses | C13: ='P&L Input'!C17 -> 250205 | D13: ='P&L Input'!D17 -> 285433 | E13: ='P&L Input'!E17 -> 300188 | F13: ='P&L Input'!F17 -> 335043 | G13: ='P&L Input'!G17 -> 397500 | H13: =H11*H14 -> 504996.47 | I13: =I11*I14 -> 568559.82 | J13: =J11*J14 -> 634234.02 | K13: =K11*K14 -> 700931.12 | L13: =L11*L14 -> 767400.83 | M13: =M11*M14 -> 832263.9 | N13: =N11*N14 -> 894056.17 | O13: =O11*O14 -> 951281.93 | ... Q13: =Q11*Q14 -> 1046256.6
C14: =C13/C11 -> 0.21370211 | D14: =D13/D11 -> 0.20376224 | E14: =E13/E11 -> 0.19825146 | F14: =F13/F11 -> 0.19193693 | G14: =G13/G11 -> 0.18593003 | H14: =AVERAGE(C14:G14) -> 0.19871656 | I14: =H14 -> 0.19871656 | J14: =I14 -> 0.19871656 | K14: =J14 -> 0.19871656 | L14: =K14 -> 0.19871656 | M14: =L14 -> 0.19871656 | N14: =M14 -> 0.19871656 | O14: =N14 -> 0.19871656 | P14: =O14 -> 0.19871656 | Q14: =P14 -> 0.19871656
B16: ='P&L Input'!B18 -> Access charges | C16: ='P&L Input'!C18 -> 67611 | D16: ='P&L Input'!D18 -> 76207 | E16: ='P&L Input'!E18 -> 75185 | F16: ='P&L Input'!F18 -> 71713 | G16: ='P&L Input'!G18 -> 55416 | H16: =H17*H11 -> 116292.6 | I16: =I17*I11 -> 130930.22 | J16: =J17*J11 -> 146053.94 | K16: =K17*K11 -> 161413.21 | L16: =L17*L11 -> 176720.13 | M16: =M17*M11 -> 191657.05 | N16: =N17*N11 -> 205886.82 | O16: =O17*O11 -> 219065 | ... Q16: =Q17*Q11 -> 240936.15
C17: =C16/C11 -> 0.057747102 | D17: =D16/D11 -> 0.054401941 | E17: =E16/E11 -> 0.049654004 | F17: =F16/F11 -> 0.041082408 | G17: =G16/G11 -> 0.025920751 | H17: =AVERAGE(C17:G17) -> 0.045761241 | I17: =H17 -> 0.045761241 | J17: =I17 -> 0.045761241 | K17: =J17 -> 0.045761241 | L17: =K17 -> 0.045761241 | M17: =L17 -> 0.045761241 | N17: =M17 -> 0.045761241 | O17: =N17 -> 0.045761241 | P17: =O17 -> 0.045761241 | Q17: =P17 -> 0.045761241
B19: ='P&L Input'!B19 -> License fee / Spectrum charges | C19: ='P&L Input'!C19 -> 110636 | D19: ='P&L Input'!D19 -> 117517 | E19: ='P&L Input'!E19 -> 120358 | F19: ='P&L Input'!F19 -> 138290 | G19: ='P&L Input'!G19 -> 153729 | H19: =H11*H20 -> 207879.3 | I19: =I11*I20 -> 234044.84 | J19: =J11*J20 -> 261079.3 | K19: =K11*K20 -> 288534.83 | L19: =L11*L20 -> 315896.76 | M19: =M11*M20 -> 342597.32 | N19: =N11*N20 -> 368033.81 | O19: =O11*O20 -> 391590.51 | ... Q19: =Q11*Q20 -> 430686.37
C20: =C19/C11 -> 0.094495103 | D20: =D19/D11 -> 0.083891937 | E20: =E19/E11 -> 0.079487352 | F20: =F19/F11 -> 0.079222543 | G20: =G19/G11 -> 0.07190651 | H20: =AVERAGE(C20:G20) -> 0.081800689 | I20: =H20 -> 0.081800689 | J20: =I20 -> 0.081800689 | K20: =J20 -> 0.081800689 | L20: =K20 -> 0.081800689 | M20: =L20 -> 0.081800689 | N20: =M20 -> 0.081800689 | O20: =N20 -> 0.081800689 | P20: =O20 -> 0.081800689 | Q20: =P20 -> 0.081800689
B22: ='P&L Input'!B20 -> Employee benefits expense | C22: ='P&L Input'!C20 -> 44333 | D22: ='P&L Input'!D20 -> 48308 | E22: ='P&L Input'!E20 -> 53231 | F22: ='P&L Input'!F20 -> 63089 | G22: ='P&L Input'!G20 -> 75813 | H22: =H11*H23 -> 91033.726 | I22: =I11*I23 -> 102492.04 | J22: =J11*J23 -> 114330.87 | K22: =K11*K23 -> 126354.09 | L22: =L11*L23 -> 138336.33 | M22: =M11*M23 -> 150028.94 | N22: =N11*N23 -> 161167.99 | O22: =O11*O23 -> 171483.85 | ... Q22: =Q11*Q23 -> 188604.56
C23: =C22/C11 -> 0.037865174 | D23: =D22/D11 -> 0.034485663 | E23: =E22/E11 -> 0.035155048 | F23: =F22/F11 -> 0.036141956 | G23: =G22/G11 -> 0.035461418 | H23: =AVERAGE(C23:G23) -> 0.035821852 | I23: =H23 -> 0.035821852 | J23: =I23 -> 0.035821852 | K23: =J23 -> 0.035821852 | L23: =K23 -> 0.035821852 | M23: =L23 -> 0.035821852 | N23: =M23 -> 0.035821852 | O23: =N23 -> 0.035821852 | P23: =O23 -> 0.035821852 | Q23: =P23 -> 0.035821852
B25: ='P&L Input'!B21 -> Sales and marketing expenses | C25: ='P&L Input'!C21 -> 53035 | D25: ='P&L Input'!D21 -> 72454 | E25: ='P&L Input'!E21 -> 107882 | F25: ='P&L Input'!F21 -> 114601 | G25: ='P&L Input'!G21 -> 131073 | H25: =H11*H26 -> 150052.66 | I25: =I11*I26 -> 168939.62 | J25: =J11*J26 -> 188453.8 | K25: =K11*K26 -> 208271.91 | L25: =L11*L26 -> 228022.46 | M25: =M11*M26 -> 247295.61 | N25: =N11*N26 -> 265656.33 | O25: =O11*O26 -> 282660.16 | ... Q25: =Q11*Q26 -> 310880.57
C26: =C25/C11 -> 0.045297623 | D26: =D25/D11 -> 0.051722784 | E26: =E25/E11 -> 0.071247898 | F26: =F25/F11 -> 0.065651766 | G26: =G25/G11 -> 0.0613092 | H26: =AVERAGE(C26:G26) -> 0.059045854 | I26: =H26 -> 0.059045854 | J26: =I26 -> 0.059045854 | K26: =J26 -> 0.059045854 | L26: =K26 -> 0.059045854 | M26: =L26 -> 0.059045854 | N26: =M26 -> 0.059045854 | O26: =N26 -> 0.059045854 | P26: =O26 -> 0.059045854 | Q26: =P26 -> 0.059045854
B28: ='P&L Input'!B22 -> Other expenses | C28: ='P&L Input'!C22 -> 64310 | D28: ='P&L Input'!D22 -> 78794 | E28: ='P&L Input'!E22 -> 60062 | F28: ='P&L Input'!F22 -> 75524 | G28: ='P&L Input'!G22 -> 99452 | H28: =H11*H29 -> 122300.6 | I28: =I11*I29 -> 137694.44 | J28: =J11*J29 -> 153599.49 | K28: =K11*K29 -> 169752.27 | L28: =L11*L29 -> 185849.98 | M28: =M11*M29 -> 201558.59 | N28: =N11*N29 -> 216523.51 | O28: =O11*O29 -> 230382.51 | ... Q28: =Q11*Q29 -> 253383.58
C29: =C28/C11 -> 0.054927691 | D29: =D28/D11 -> 0.056248724 | E29: =E28/E11 -> 0.039666406 | F29: =F28/F11 -> 0.043265626 | G29: =G28/G11 -> 0.046518524 | H29: =AVERAGE(C29:G29) -> 0.048125394 | I29: =H29 -> 0.048125394 | J29: =I29 -> 0.048125394 | K29: =J29 -> 0.048125394 | L29: =K29 -> 0.048125394 | M29: =L29 -> 0.048125394 | N29: =M29 -> 0.048125394 | O29: =N29 -> 0.048125394 | P29: =O29 -> 0.048125394 | Q29: =P29 -> 0.048125394
B31: ='P&L Input'!B32 -> Finance Costs | C31: ='P&L Input'!C32 -> 166162 | D31: ='P&L Input'!D32 -> 192999 | E31: ='P&L Input'!E32 -> 226477 | F31: ='P&L Input'!F32 -> 217539 | G31: ='P&L Input'!G32 -> 215553 | H31: =H32*H11 -> 332763.81 | I31: =I32*I11 -> 374648.42 | J31: =J32*J11 -> 417923.97 | K31: =K32*K11 -> 461873.55 | L31: =L32*L11 -> 505673.29 | M31: =M32*M11 -> 548414.34 | N31: =N32*N11 -> 589131.92 | O31: =O32*O11 -> 626840.42 | ... Q31: =Q32*Q11 -> 689423.31
C32: =C31/C11 -> 0.14192031 | D32: =D31/D11 -> 0.13777632 | E32: =E31/E11 -> 0.14957092 | F32: =F31/F11 -> 0.12462212 | G32: =G31/G11 -> 0.10082459 | H32: =AVERAGE(C32:G32) -> 0.13094285 | I32: =H32 -> 0.13094285 | J32: =I32 -> 0.13094285 | K32: =J32 -> 0.13094285 | L32: =K32 -> 0.13094285 | M32: =L32 -> 0.13094285 | N32: =M32 -> 0.13094285 | O32: =N32 -> 0.13094285 | P32: =O32 -> 0.13094285 | Q32: =P32 -> 0.13094285
B34: Effective Tax rate | C34: ='P&L Input'!C41/'P&L Input'!C39 -> 0.33468449 | D34: ='P&L Input'!D41/'P&L Input'!D39 -> 0.25803861 | E34: ='P&L Input'!E41/'P&L Input'!E39 -> 0.32502563 | F34: ='P&L Input'!F41/'P&L Input'!F39 -> 0.02388635 | G34: ='P&L Input'!G41/'P&L Input'!G39 -> 0.25125574 | H34: =G34+0.5% -> 0.25625574 | I34: =H34 -> 0.25625574 | J34: =I34+0.5% -> 0.26125574 | K34: =J34 -> 0.26125574 | L34: =K34+0.5% -> 0.26625574 | M34: =L34 -> 0.26625574 | N34: =M34+0.5% -> 0.27125574 | O34: =N34 -> 0.27125574 | P34: =O34+0.5% -> 0.27625574 | Q34: =P34 -> 0.27625574

Sheet FAS
A1: Bharti Airtel Ltd
Q5: (INR in millions)
B6: Fixed Assets Schedule
B7: Particulars | C7: 2022 | D7: =C7+1 -> 2023 | E7: =D7+1 -> 2024 | F7: =E7+1 -> 2025 | G7: =F7+1 -> 2026 | H7: =G7+1 -> 2027 | I7: =H7+1 -> 2028 | J7: =I7+1 -> 2029 | K7: =J7+1 -> 2030 | ... Q7: =P7+1 -> 2036
C8: Audited | D8: Audited | E8: Audited | F8: Audited | G8: Audited | H8: Estimated | I8: Projected | J8: Projected | K8: Projected | L8: Projected | M8: Projected | N8: Projected | O8: Projected | P8: Projected | Q8: Projected
B9: PPE Assets
B10: Leasehold Improvements
B11: Opening Gross Block | C11: 10357 | D11: =C15 -> 10512 | E11: =D15 -> 10880 | F11: =E15 -> 10729 | G11: =F15 -> 11075 | H11: =G15 -> 11075 | I11: =H15 -> 11559.4 | J11: =I15 -> 12043.8 | K11: =J15 -> 12528.2 | ... Q11: =P15 -> 17410.952
B12: Additions | C12: 202 | D12: 335 | E12: 264 | F12: =167+11 -> 178 | H12: =F12*1.4 -> 249.2 | I12: =H12 -> 249.2 | J12: =I12 -> 249.2 | K12: =J12*1.4 -> 348.88 | L12: =K12 -> 348.88 | M12: =L12 -> 348.88 | N12: =M12*1.4 -> 488.432 | O12: =N12 -> 488.432 | P12: =O12 -> 488.432 | Q12: =P12*1.4 -> 683.8048
B13: Disposals / Adjustments | C13: -49 | D13: 8 | E13: -9 | F13: =84-23-11 -> 50 | H13: =F13*1.4 -> 70 | I13: =H13 -> 70 | J13: =I13 -> 70 | K13: =J13*1.4 -> 98 | L13: =K13 -> 98 | M13: =L13 -> 98 | N13: =M13*1.4 -> 137.2 | O13: =N13 -> 137.2 | P13: =O13 -> 137.2 | Q13: =P13*1.4 -> 192.08
B14: Exchange Differences | C14: 2 | D14: 25 | E14: -406 | F14: 118 | H14: =F14*1.4 -> 165.2 | I14: =H14 -> 165.2 | J14: =I14 -> 165.2 | K14: =J14*1.4 -> 231.28 | L14: =K14 -> 231.28 | M14: =L14 -> 231.28 | N14: =M14*1.4 -> 323.792 | O14: =N14 -> 323.792 | P14: =O14 -> 323.792 | Q14: =P14*1.4 -> 453.3088
B15: Closing Gross Block | C15: =SUM(C11:C14) -> 10512 | D15: =SUM(D11:D14) -> 10880 | E15: =SUM(E11:E14) -> 10729 | F15: =SUM(F11:F14) -> 11075 | G15: =SUM(G11:G14) -> 11075 | H15: =SUM(H11:H14) -> 11559.4 | I15: =SUM(I11:I14) -> 12043.8 | J15: =SUM(J11:J14) -> 12528.2 | ... Q15: =SUM(Q11:Q14) -> 18740.146
B17: Opening Accumulated Depreciation | C17: 8464 | D17: =C21 -> 8761 | E17: =D21 -> 9139 | F17: =E21 -> 9097 | G17: =F21 -> 9273 | H17: =G21 -> 9273 | I17: =H21 -> 10076.6 | J17: =I21 -> 10880.2 | K17: =J21 -> 11683.8 | ... Q17: =P21 -> 19784.088
B18: Depreciation | C18: 361 | D18: 345 | E18: 398 | H18: =E18*1.4 -> 557.2 | I18: =H18 -> 557.2 | J18: =I18 -> 557.2 | K18: =J18*1.4 -> 780.08 | L18: =K18 -> 780.08 | M18: =L18 -> 780.08 | N18: =M18*1.4 -> 1092.112 | O18: =N18 -> 1092.112 | P18: =O18 -> 1092.112 | Q18: =P18*1.4 -> 1528.9568
B19: Disposals / Adjustments | C19: -45 | D19: -2 | E19: -29 | F19: =83-27-10 -> 46 | H19: =F19*1.4 -> 64.4 | I19: =H19 -> 64.4 | J19: =I19 -> 64.4 | K19: =J19*1.4 -> 90.16 | L19: =K19 -> 90.16 | M19: =L19 -> 90.16 | N19: =M19*1.4 -> 126.224 | O19: =N19 -> 126.224 | P19: =O19 -> 126.224 | Q19: =P19*1.4 -> 176.7136
B20: Exchange Differences | C20: -19 | D20: 35 | E20: -411 | F20: 130 | H20: =F20*1.4 -> 182 | I20: =H20 -> 182 | J20: =I20 -> 182 | K20: =J20*1.4 -> 254.8 | L20: =K20 -> 254.8 | M20: =L20 -> 254.8 | N20: =M20*1.4 -> 356.72 | O20: =N20 -> 356.72 | P20: =O20 -> 356.72 | Q20: =P20*1.4 -> 499.408
B21: Closing Accumulated Depreciation | C21: =SUM(C17:C20) -> 8761 | D21: =SUM(D17:D20) -> 9139 | E21: =SUM(E17:E20) -> 9097 | F21: =SUM(F17:F20) -> 9273 | G21: =SUM(G17:G20) -> 9273 | H21: =SUM(H17:H20) -> 10076.6 | I21: =SUM(I17:I20) -> 10880.2 | J21: =SUM(J17:J20) -> 11683.8 | ... Q21: =SUM(Q17:Q20) -> 21989.166
B23: Net Block | C23: =+C15-C21 -> 1751 | D23: =+D15-D21 -> 1741 | E23: =+E15-E21 -> 1632 | F23: =+F15-F21 -> 1802 | G23: =+G15-G21 -> 1802 | H23: =+H15-H21 -> 1482.8 | I23: =+I15-I21 -> 1163.6 | J23: =+J15-J21 -> 844.4 | ... Q23: =+Q15-Q21 -> -3249.0208
B25: Buildings
B26: Opening Gross Block | C26: 10731 | D26: =+C30 -> 13767 | E26: =+D30 -> 18152 | F26: =+E30 -> 17608 | G26: =+F30 -> 24796 | H26: =+G30 -> 24796 | I26: =+H30 -> 34859.2 | J26: =+I30 -> 44922.4 | K26: =+J30 -> 54985.6 | ... Q26: =+P30 -> 156422.66
B27: Additions | C27: 2897 | D27: 4455 | E27: 370 | F27: 5625 | H27: =F27*1.4 -> 7875 | I27: =H27 -> 7875 | J27: =I27 -> 7875 | K27: =J27*1.4 -> 11025 | L27: =K27 -> 11025 | M27: =L27 -> 11025 | N27: =M27*1.4 -> 15435 | O27: =N27 -> 15435 | P27: =O27 -> 15435 | Q27: =P27*1.4 -> 21609
B28: Disposals / Adjustments | C28: -11 | E28: -252 | F28: =1074-28 -> 1046 | H28: =F28*1.4 -> 1464.4 | I28: =H28 -> 1464.4 | J28: =I28 -> 1464.4 | K28: =J28*1.4 -> 2050.16 | L28: =K28 -> 2050.16 | M28: =L28 -> 2050.16 | N28: =M28*1.4 -> 2870.224 | O28: =N28 -> 2870.224 | P28: =O28 -> 2870.224 | Q28: =P28*1.4 -> 4018.3136
B29: Exchange Differences | C29: 150 | D29: -70 | E29: -662 | F29: 517 | H29: =F29*1.4 -> 723.8 | I29: =H29 -> 723.8 | J29: =I29 -> 723.8 | K29: =J29*1.4 -> 1013.32 | L29: =K29 -> 1013.32 | M29: =L29 -> 1013.32 | N29: =M29*1.4 -> 1418.648 | O29: =N29 -> 1418.648 | P29: =O29 -> 1418.648 | Q29: =P29*1.4 -> 1986.1072
B30: Closing Gross Block | C30: =SUM(C26:C29) -> 13767 | D30: =SUM(D26:D29) -> 18152 | E30: =SUM(E26:E29) -> 17608 | F30: =SUM(F26:F29) -> 24796 | G30: =SUM(G26:G29) -> 24796 | H30: =SUM(H26:H29) -> 34859.2 | I30: =SUM(I26:I29) -> 44922.4 | J30: =SUM(J26:J29) -> 54985.6 | ... Q30: =SUM(Q26:Q29) -> 184036.08
B32: Opening Accumulated Depreciation | C32: 4799 | D32: =+C36 -> 5413 | E32: =+D36 -> 6177 | F32: =+E36 -> 6437 | G32: =+F36 -> 8484 | H32: =+G36 -> 8484 | I32: =+H36 -> 11349.8 | J32: =+I36 -> 14215.6 | K32: =+J36 -> 17081.4 | ... Q32: =+P36 -> 45968.664
B33: Depreciation | C33: 568 | D33: 866 | E33: 859 | F33: 1069 | H33: =F33*1.4 -> 1496.6 | I33: =H33 -> 1496.6 | J33: =I33 -> 1496.6 | K33: =J33*1.4 -> 2095.24 | L33: =K33 -> 2095.24 | M33: =L33 -> 2095.24 | N33: =M33*1.4 -> 2933.336 | O33: =N33 -> 2933.336 | P33: =O33 -> 2933.336 | Q33: =P33*1.4 -> 4106.6704
B34: Disposals / Adjustments | C34: -2 | D34: -5 | E34: -165 | F34: =655-17+4 -> 642 | H34: =F34*1.4 -> 898.8 | I34: =H34 -> 898.8 | J34: =I34 -> 898.8 | K34: =J34*1.4 -> 1258.32 | L34: =K34 -> 1258.32 | M34: =L34 -> 1258.32 | N34: =M34*1.4 -> 1761.648 | O34: =N34 -> 1761.648 | P34: =O34 -> 1761.648 | Q34: =P34*1.4 -> 2466.3072
B35: Exchange Differences | C35: 48 | D35: -97 | E35: -434 | F35: 336 | H35: =F35*1.4 -> 470.4 | I35: =H35 -> 470.4 | J35: =I35 -> 470.4 | K35: =J35*1.4 -> 658.56 | L35: =K35 -> 658.56 | M35: =L35 -> 658.56 | N35: =M35*1.4 -> 921.984 | O35: =N35 -> 921.984 | P35: =O35 -> 921.984 | Q35: =P35*1.4 -> 1290.7776
B36: Closing Accumulated Depreciation | C36: =SUM(C32:C35) -> 5413 | D36: =SUM(D32:D35) -> 6177 | E36: =SUM(E32:E35) -> 6437 | F36: =SUM(F32:F35) -> 8484 | G36: =SUM(G32:G35) -> 8484 | H36: =SUM(H32:H35) -> 11349.8 | I36: =SUM(I32:I35) -> 14215.6 | J36: =SUM(J32:J35) -> 17081.4 | ... Q36: =SUM(Q32:Q35) -> 53832.419
B38: Net Block | C38: =+C30-C36 -> 8354 | D38: =+D30-D36 -> 11975 | E38: =+E30-E36 -> 11171 | F38: =+F30-F36 -> 16312 | G38: =+G30-G36 -> 16312 | H38: =+H30-H36 -> 23509.4 | I38: =+I30-I36 -> 30706.8 | J38: =+J30-J36 -> 37904.2 | ... Q38: =+Q30-Q36 -> 130203.66
B40: Land
B41: Opening Gross Block | C41: 5843 | D41: =+C45 -> 5798 | E41: =+D45 -> 8238 | F41: =+E45 -> 9415 | G41: =+F45 -> 10112 | H41: =+G45 -> 10112 | I41: =+H45 -> 11087.8 | J41: =+I45 -> 12063.6 | K41: =+J45 -> 13039.4 | ... Q41: =+P45 -> 22875.464
B42: Additions | C42: 145 | D42: 2355 | E42: 1350 | F42: =652+4 -> 656 | H42: =F42*1.4 -> 918.4 | I42: =H42 -> 918.4 | J42: =I42 -> 918.4 | K42: =J42*1.4 -> 1285.76 | L42: =K42 -> 1285.76 | M42: =L42 -> 1285.76 | N42: =M42*1.4 -> 1800.064 | O42: =N42 -> 1800.064 | P42: =O42 -> 1800.064 | Q42: =P42*1.4 -> 2520.0896
B43: Disposals / Adjustments | C43: -185 | D43: 0 | E43: -44 | F43: =25-6 -> 19 | H43: =F43*1.4 -> 26.6 | I43: =H43 -> 26.6 | J43: =I43 -> 26.6 | K43: =J43*1.4 -> 37.24 | L43: =K43 -> 37.24 | M43: =L43 -> 37.24 | N43: =M43*1.4 -> 52.136 | O43: =N43 -> 52.136 | P43: =O43 -> 52.136 | Q43: =P43*1.4 -> 72.9904
B44: Exchange Differences | C44: -5 | D44: 85 | E44: -129 | F44: 22 | H44: =F44*1.4 -> 30.8 | I44: =H44 -> 30.8 | J44: =I44 -> 30.8 | K44: =J44*1.4 -> 43.12 | L44: =K44 -> 43.12 | M44: =L44 -> 43.12 | N44: =M44*1.4 -> 60.368 | O44: =N44 -> 60.368 | P44: =O44 -> 60.368 | Q44: =P44*1.4 -> 84.5152
B45: Closing Gross Block | C45: =SUM(C41:C44) -> 5798 | D45: =SUM(D41:D44) -> 8238 | E45: =SUM(E41:E44) -> 9415 | F45: =SUM(F41:F44) -> 10112 | G45: =SUM(G41:G44) -> 10112 | H45: =SUM(H41:H44) -> 11087.8 | I45: =SUM(I41:I44) -> 12063.6 | J45: =SUM(J41:J44) -> 13039.4 | ... Q45: =SUM(Q41:Q44) -> 25553.059
B47: Net Block | C47: =+C45 -> 5798 | D47: =+D45 -> 8238 | E47: =+E45 -> 9415 | F47: =+F45 -> 10112 | G47: =+G45 -> 10112 | H47: =+H45 -> 11087.8 | I47: =+I45 -> 12063.6 | J47: =+J45 -> 13039.4 | ... Q47: =+Q45 -> 25553.059
B49: Plant & Equipment
B50: Opening Gross Block | C50: 1926716 | D50: =+C54 -> 2105395 | E50: =+D54 -> 2284891 | F50: =+E54 -> 2431350 | G50: =+F54 -> 2950094 | H50: =+G54 -> 3087684 | I50: =+H54 -> 3813925.6 | J50: =+I54 -> 4540167.2 | K50: =+J54 -> 5266408.8 | ... Q50: =+P54 -> 12586924
B51: Additions | C51: 231788 | D51: 231784 | E51: =381615+1 -> 381616 | F51: =336681+271296 -> 607977 | G51: 137590 | H51: =F51*1.4 -> 851167.8 | I51: =H51 -> 851167.8 | J51: =I51 -> 851167.8 | K51: =J51*1.4 -> 1191634.9 | L51: =K51 -> 1191634.9 | M51: =L51 -> 1191634.9 | N51: =M51*1.4 -> 1668288.9 | O51: =N51 -> 1668288.9 | P51: =O51 -> 1668288.9 | Q51: =P51*1.4 -> 2335604.4
B52: Disposals / Adjustments | C52: -51121 | D52: -43150 | E52: -124658 | F52: =17021-100738-10615 -> -94332 | H52: =F52*1.4 -> -132064.8 | I52: =H52 -> -132064.8 | J52: =I52 -> -132064.8 | K52: =J52*1.4 -> -184890.72 | L52: =K52 -> -184890.72 | M52: =L52 -> -184890.72 | N52: =M52*1.4 -> -258847.01 | O52: =N52 -> -258847.01 | P52: =O52 -> -258847.01 | Q52: =P52*1.4 -> -362385.81
B53: Exchange Differences | C53: -1988 | D53: -9138 | E53: -110499 | F53: 5099 | H53: =F53*1.4 -> 7138.6 | I53: =H53 -> 7138.6 | J53: =I53 -> 7138.6 | K53: =J53*1.4 -> 9994.04 | L53: =K53 -> 9994.04 | M53: =L53 -> 9994.04 | N53: =M53*1.4 -> 13991.656 | O53: =N53 -> 13991.656 | P53: =O53 -> 13991.656 | Q53: =P53*1.4 -> 19588.318
B54: Closing Gross Block | C54: =SUM(C50:C53) -> 2105395 | D54: =SUM(D50:D53) -> 2284891 | E54: =SUM(E50:E53) -> 2431350 | F54: =SUM(F50:F53) -> 2950094 | G54: =SUM(G50:G53) -> 3087684 | H54: =SUM(H50:H53) -> 3813925.6 | I54: =SUM(I50:I53) -> 4540167.2 | J54: =SUM(J50:J53) -> 5266408.8 | ... Q54: =SUM(Q50:Q53) -> 14579731
B56: Opening Accumulated Depreciation | C56: 1094375 | D56: =+C60 -> 1230809 | E56: =+D60 -> 1376394 | F56: =+E60 -> 1407191 | G56: =+F60 -> 1569071 | H56: =+G60 -> 1569071 | I56: =+H60 -> 1795703 | J56: =+I60 -> 2022335 | K56: =+J60 -> 2248967 | ... Q56: =+P60 -> 4533417.6
B57: Depreciation | C57: 182766 | D57: 196737 | E57: 211925 | F57: 248439 | H57: =F57*1.4 -> 347814.6 | I57: =H57 -> 347814.6 | J57: =I57 -> 347814.6 | K57: =J57*1.4 -> 486940.44 | L57: =K57 -> 486940.44 | M57: =L57 -> 486940.44 | N57: =M57*1.4 -> 681716.62 | O57: =N57 -> 681716.62 | P57: =O57 -> 681716.62 | Q57: =P57*1.4 -> 954403.26
B58: Disposals / Adjustments | C58: -42402 | D58: -41394 | E58: -122056 | F58: =14599+-96395-9126 -> -90922 | H58: =F58*1.4 -> -127290.8 | I58: =H58 -> -127290.8 | J58: =I58 -> -127290.8 | K58: =J58*1.4 -> -178207.12 | L58: =K58 -> -178207.12 | M58: =L58 -> -178207.12 | N58: =M58*1.4 -> -249489.97 | O58: =N58 -> -249489.97 | P58: =O58 -> -249489.97 | Q58: =P58*1.4 -> -349285.96
B59: Exchange Differences | C59: -3930 | D59: -9758 | E59: -59072 | F59: 4363 | H59: =F59*1.4 -> 6108.2 | I59: =H59 -> 6108.2 | J59: =I59 -> 6108.2 | K59: =J59*1.4 -> 8551.48 | L59: =K59 -> 8551.48 | M59: =L59 -> 8551.48 | N59: =M59*1.4 -> 11972.072 | O59: =N59 -> 11972.072 | P59: =O59 -> 11972.072 | Q59: =P59*1.4 -> 16760.901
B60: Closing Accumulated Depreciation | C60: =SUM(C56:C59) -> 1230809 | D60: =SUM(D56:D59) -> 1376394 | E60: =SUM(E56:E59) -> 1407191 | F60: =SUM(F56:F59) -> 1569071 | G60: =SUM(G56:G59) -> 1569071 | H60: =SUM(H56:H59) -> 1795703 | I60: =SUM(I56:I59) -> 2022335 | J60: =SUM(J56:J59) -> 2248967 | ... Q60: =SUM(Q56:Q59) -> 5155295.8
B62: Net Block | C62: =+C54-C60 -> 874586 | D62: =+D54-D60 -> 908497 | E62: =+E54-E60 -> 1024159 | F62: =+F54-F60 -> 1381023 | G62: =+G54-G60 -> 1518613 | H62: =+H54-H60 -> 2018222.6 | I62: =+I54-I60 -> 2517832.2 | J62: =+J54-J60 -> 3017441.8 | ... Q62: =+Q54-Q60 -> 9424435.3
B64: Furniture & Fixtures
B65: Opening Gross Block | C65: 4653 | D65: =+C69 -> 6701 | E65: =+D69 -> 7754 | F65: =+E69 -> 7133 | G65: =+F69 -> 8228 | H65: =+G69 -> 8228 | I65: =+H69 -> 9761 | J65: =+I69 -> 11294 | K65: =+J69 -> 12827 | ... Q65: =+P69 -> 28279.64
B66: Additions | C66: 2134 | D66: 1451 | E66: 912 | F66: =586+8 -> 594 | H66: =F66*1.4 -> 831.6 | I66: =H66 -> 831.6 | J66: =I66 -> 831.6 | K66: =J66*1.4 -> 1164.24 | L66: =K66 -> 1164.24 | M66: =L66 -> 1164.24 | N66: =M66*1.4 -> 1629.936 | O66: =N66 -> 1629.936 | P66: =O66 -> 1629.936 | Q66: =P66*1.4 -> 2281.9104
B67: Disposals / Adjustments | C67: -151 | D67: -272 | E67: -498 | F67: =335+-48-10 -> 277 | H67: =F67*1.4 -> 387.8 | I67: =H67 -> 387.8 | J67: =I67 -> 387.8 | K67: =J67*1.4 -> 542.92 | L67: =K67 -> 542.92 | M67: =L67 -> 542.92 | N67: =M67*1.4 -> 760.088 | O67: =N67 -> 760.088 | P67: =O67 -> 760.088 | Q67: =P67*1.4 -> 1064.1232
B68: +/- Exchange Differences | C68: 65 | D68: -126 | E68: -1035 | F68: 224 | H68: =F68*1.4 -> 313.6 | I68: =H68 -> 313.6 | J68: =I68 -> 313.6 | K68: =J68*1.4 -> 439.04 | L68: =K68 -> 439.04 | M68: =L68 -> 439.04 | N68: =M68*1.4 -> 614.656 | O68: =N68 -> 614.656 | P68: =O68 -> 614.656 | Q68: =P68*1.4 -> 860.5184
B69: Closing Gross Block | C69: =SUM(C65:C68) -> 6701 | D69: =SUM(D65:D68) -> 7754 | E69: =SUM(E65:E68) -> 7133 | F69: =SUM(F65:F68) -> 8228 | G69: =SUM(G65:G68) -> 8228 | H69: =SUM(H65:H68) -> 9761 | I69: =SUM(I65:I68) -> 11294 | J69: =SUM(J65:J68) -> 12827 | ... Q69: =SUM(Q65:Q68) -> 32486.192
B71: Opening Accumulated Depreciation | C71: 3417 | D71: =+C75 -> 4058 | E71: =+D75 -> 4829 | F71: =+E75 -> 4828 | G71: =+F75 -> 6358 | H71: =+G75 -> 6358 | I71: =+H75 -> 8500 | J71: =+I75 -> 10642 | K71: =+J75 -> 12784 | ... Q71: =+P75 -> 34375.36
B72: Depreciation | C72: 764 | D72: 1069 | E72: 1099 | F72: 1145 | H72: =F72*1.4 -> 1603 | I72: =H72 -> 1603 | J72: =I72 -> 1603 | K72: =J72*1.4 -> 2244.2 | L72: =K72 -> 2244.2 | M72: =L72 -> 2244.2 | N72: =M72*1.4 -> 3141.88 | O72: =N72 -> 3141.88 | P72: =O72 -> 3141.88 | Q72: =P72*1.4 -> 4398.632
B73: Disposals / Adjustments | C73: -164 | D73: -230 | E73: -461 | F73: =267-80-10 -> 177 | H73: =F73*1.4 -> 247.8 | I73: =H73 -> 247.8 | J73: =I73 -> 247.8 | K73: =J73*1.4 -> 346.92 | L73: =K73 -> 346.92 | M73: =L73 -> 346.92 | N73: =M73*1.4 -> 485.688 | O73: =N73 -> 485.688 | P73: =O73 -> 485.688 | Q73: =P73*1.4 -> 679.9632
B74: +/- Exchange Differences | C74: 41 | D74: -68 | E74: -639 | F74: 208 | H74: =F74*1.4 -> 291.2 | I74: =H74 -> 291.2 | J74: =I74 -> 291.2 | K74: =J74*1.4 -> 407.68 | L74: =K74 -> 407.68 | M74: =L74 -> 407.68 | N74: =M74*1.4 -> 570.752 | O74: =N74 -> 570.752 | P74: =O74 -> 570.752 | Q74: =P74*1.4 -> 799.0528
B75: Closing Accumulated Depreciation | C75: =SUM(C71:C74) -> 4058 | D75: =SUM(D71:D74) -> 4829 | E75: =SUM(E71:E74) -> 4828 | F75: =SUM(F71:F74) -> 6358 | G75: =SUM(G71:G74) -> 6358 | H75: =SUM(H71:H74) -> 8500 | I75: =SUM(I71:I74) -> 10642 | J75: =SUM(J71:J74) -> 12784 | ... Q75: =SUM(Q71:Q74) -> 40253.008
B77: Net Block | C77: =+C69-C75 -> 2643 | D77: =+D69-D75 -> 2925 | E77: =+E69-E75 -> 2305 | F77: =+F69-F75 -> 1870 | G77: =+G69-G75 -> 1870 | H77: =+H69-H75 -> 1261 | I77: =+I69-I75 -> 652 | J77: =+J69-J75 -> 43 | ... Q77: =+Q69-Q75 -> -7766.816
B79: Vehicles
B80: Opening Gross Block | C80: 2047 | D80: =+C84 -> 1892 | E80: =+D84 -> 1982 | F80: =+E84 -> 1996 | G80: =+F84 -> 2629 | H80: =+G84 -> 2629 | I80: =+H84 -> 3515.2 | J80: =+I84 -> 4401.4 | K80: =+J84 -> 5287.6 | ... Q80: =+P84 -> 14220.496
B81: Additions | C81: 57 | D81: 36 | F81: =190+402 -> 592 | H81: =F81*1.4 -> 828.8 | I81: =H81 -> 828.8 | J81: =I81 -> 828.8 | K81: =J81*1.4 -> 1160.32 | L81: =K81 -> 1160.32 | M81: =L81 -> 1160.32 | N81: =M81*1.4 -> 1624.448 | O81: =N81 -> 1624.448 | P81: =O81 -> 1624.448 | Q81: =P81*1.4 -> 2274.2272
B82: Disposals / Adjustments | C82: -231 | D82: -41 | F82: =65-49 -> 16 | H82: =F82*1.4 -> 22.4 | I82: =H82 -> 22.4 | J82: =I82 -> 22.4 | K82: =J82*1.4 -> 31.36 | L82: =K82 -> 31.36 | M82: =L82 -> 31.36 | N82: =M82*1.4 -> 43.904 | O82: =N82 -> 43.904 | P82: =O82 -> 43.904 | Q82: =P82*1.4 -> 61.4656
B83: Exchange Differences | C83: 19 | D83: 95 | E83: 14 | F83: 25 | H83: =F83*1.4 -> 35 | I83: =H83 -> 35 | J83: =I83 -> 35 | K83: =J83*1.4 -> 49 | L83: =K83 -> 49 | M83: =L83 -> 49 | N83: =M83*1.4 -> 68.6 | O83: =N83 -> 68.6 | P83: =O83 -> 68.6 | Q83: =P83*1.4 -> 96.04
B84: Closing Gross Block | C84: =SUM(C80:C83) -> 1892 | D84: =SUM(D80:D83) -> 1982 | E84: =SUM(E80:E83) -> 1996 | F84: =SUM(F80:F83) -> 2629 | G84: =SUM(G80:G83) -> 2629 | H84: =SUM(H80:H83) -> 3515.2 | I84: =SUM(I80:I83) -> 4401.4 | J84: =SUM(J80:J83) -> 5287.6 | ... Q84: =SUM(Q80:Q83) -> 16652.229
B86: Opening Accumulated Depreciation | C86: 1916 | D86: =+C90 -> 1734 | E86: =+D90 -> 1774 | F86: =+E90 -> 1887 | G86: =+F90 -> 2079 | H86: =+G90 -> 2079 | I86: =+H90 -> 2347.8 | J86: =+I90 -> 2616.6 | K86: =+J90 -> 2885.4 | ... Q86: =+P90 -> 5594.904
B87: Depreciation | C87: 24 | D87: 24 | E87: 23 | F87: 57 | H87: =F87*1.4 -> 79.8 | I87: =H87 -> 79.8 | J87: =I87 -> 79.8 | K87: =J87*1.4 -> 111.72 | L87: =K87 -> 111.72 | M87: =L87 -> 111.72 | N87: =M87*1.4 -> 156.408 | O87: =N87 -> 156.408 | P87: =O87 -> 156.408 | Q87: =P87*1.4 -> 218.9712
B88: Disposals / Adjustments | C88: -231 | D88: -40 | E88: 100 | F88: =65+-37+0 -> 28 | H88: =F88*1.4 -> 39.2 | I88: =H88 -> 39.2 | J88: =I88 -> 39.2 | K88: =J88*1.4 -> 54.88 | L88: =K88 -> 54.88 | M88: =L88 -> 54.88 | N88: =M88*1.4 -> 76.832 | O88: =N88 -> 76.832 | P88: =O88 -> 76.832 | Q88: =P88*1.4 -> 107.5648
B89: Exchange Differences | C89: 25 | D89: 56 | E89: -10 | F89: 107 | H89: =F89*1.4 -> 149.8 | I89: =H89 -> 149.8 | J89: =I89 -> 149.8 | K89: =J89*1.4 -> 209.72 | L89: =K89 -> 209.72 | M89: =L89 -> 209.72 | N89: =M89*1.4 -> 293.608 | O89: =N89 -> 293.608 | P89: =O89 -> 293.608 | Q89: =P89*1.4 -> 411.0512
B90: Closing Accumulated Depreciation | C90: =SUM(C86:C89) -> 1734 | D90: =SUM(D86:D89) -> 1774 | E90: =SUM(E86:E89) -> 1887 | F90: =SUM(F86:F89) -> 2079 | G90: =SUM(G86:G89) -> 2079 | H90: =SUM(H86:H89) -> 2347.8 | I90: =SUM(I86:I89) -> 2616.6 | J90: =SUM(J86:J89) -> 2885.4 | ... Q90: =SUM(Q86:Q89) -> 6332.4912
B92: Net Block | C92: =+C84-C90 -> 158 | D92: =+D84-D90 -> 208 | E92: =+E84-E90 -> 109 | F92: =+F84-F90 -> 550 | G92: =+G84-G90 -> 550 | H92: =+H84-H90 -> 1167.4 | I92: =+I84-I90 -> 1784.8 | J92: =+J84-J90 -> 2402.2 | ... Q92: =+Q84-Q90 -> 10319.738
B94: Office Equipment
B95: Opening Gross Block | C95: 9449 | D95: =+C99 -> 10707 | E95: =+D99 -> 11905 | F95: =+E99 -> 12181 | G95: =+F99 -> 14818 | H95: =+G99 -> 14818 | I95: =+H99 -> 18509.8 | J95: =+I99 -> 22201.6 | K95: =+J99 -> 25893.4 | ... Q95: =+P99 -> 63106.744
B96: Additions | C96: 1491 | D96: 1721 | E96: 1959 | F96: =2780+69 -> 2849 | H96: =F96*1.4 -> 3988.6 | I96: =H96 -> 3988.6 | J96: =I96 -> 3988.6 | K96: =J96*1.4 -> 5584.04 | L96: =K96 -> 5584.04 | M96: =L96 -> 5584.04 | N96: =M96*1.4 -> 7817.656 | O96: =N96 -> 7817.656 | P96: =O96 -> 7817.656 | Q96: =P96*1.4 -> 10944.718
B97: Disposals / Adjustments | C97: -354 | D97: -308 | E97: -242 | F97: =321-858-14 -> -551 | H97: =F97*1.4 -> -771.4 | I97: =H97 -> -771.4 | J97: =I97 -> -771.4 | K97: =J97*1.4 -> -1079.96 | L97: =K97 -> -1079.96 | M97: =L97 -> -1079.96 | N97: =M97*1.4 -> -1511.944 | O97: =N97 -> -1511.944 | P97: =O97 -> -1511.944 | Q97: =P97*1.4 -> -2116.7216
B98: Exchange Differences | C98: 121 | D98: -215 | E98: -1441 | F98: 339 | H98: =F98*1.4 -> 474.6 | I98: =H98 -> 474.6 | J98: =I98 -> 474.6 | K98: =J98*1.4 -> 664.44 | L98: =K98 -> 664.44 | M98: =L98 -> 664.44 | N98: =M98*1.4 -> 930.216 | O98: =N98 -> 930.216 | P98: =O98 -> 930.216 | Q98: =P98*1.4 -> 1302.3024
B99: Closing Gross Block | C99: =SUM(C95:C98) -> 10707 | D99: =SUM(D95:D98) -> 11905 | E99: =SUM(E95:E98) -> 12181 | F99: =SUM(F95:F98) -> 14818 | G99: =SUM(G95:G98) -> 14818 | H99: =SUM(H95:H98) -> 18509.8 | I99: =SUM(I95:I98) -> 22201.6 | J99: =SUM(J95:J98) -> 25893.4 | ... Q99: =SUM(Q95:Q98) -> 73237.043
B101: Opening Accumulated Depreciation | C101: 7317 | D101: =+C105 -> 8025 | E101: =+D105 -> 8959 | F101: =+E105 -> 9623 | G101: =+F105 -> 11244 | H101: =+G105 -> 11244 | I101: =+H105 -> 13513.4 | J101: =+I105 -> 15782.8 | K101: =+J105 -> 18052.2 | ... Q101: =+P105 -> 40927.752
B102: Depreciation | C102: 986 | D102: 1366 | E102: 1694 | F102: 1992 | H102: =F102*1.4 -> 2788.8 | I102: =H102 -> 2788.8 | J102: =I102 -> 2788.8 | K102: =J102*1.4 -> 3904.32 | L102: =K102 -> 3904.32 | M102: =L102 -> 3904.32 | N102: =M102*1.4 -> 5466.048 | O102: =N102 -> 5466.048 | P102: =O102 -> 5466.048 | Q102: =P102*1.4 -> 7652.4672
B103: Disposals / Adjustments | C103: -272 | D103: -206 | E103: 46 | F103: =310-910-13 -> -613 | H103: =F103*1.4 -> -858.2 | I103: =H103 -> -858.2 | J103: =I103 -> -858.2 | K103: =J103*1.4 -> -1201.48 | L103: =K103 -> -1201.48 | M103: =L103 -> -1201.48 | N103: =M103*1.4 -> -1682.072 | O103: =N103 -> -1682.072 | P103: =O103 -> -1682.072 | Q103: =P103*1.4 -> -2354.9008
B104: Exchange Differences | C104: -6 | D104: -226 | E104: -1076 | F104: 242 | H104: =F104*1.4 -> 338.8 | I104: =H104 -> 338.8 | J104: =I104 -> 338.8 | K104: =J104*1.4 -> 474.32 | L104: =K104 -> 474.32 | M104: =L104 -> 474.32 | N104: =M104*1.4 -> 664.048 | O104: =N104 -> 664.048 | P104: =O104 -> 664.048 | Q104: =P104*1.4 -> 929.6672
B105: Closing Accumulated Depreciation | C105: =SUM(C101:C104) -> 8025 | D105: =SUM(D101:D104) -> 8959 | E105: =SUM(E101:E104) -> 9623 | F105: =SUM(F101:F104) -> 11244 | G105: =SUM(G101:G104) -> 11244 | H105: =SUM(H101:H104) -> 13513.4 | I105: =SUM(I101:I104) -> 15782.8 | J105: =SUM(J101:J104) -> 18052.2 | ... Q105: =SUM(Q101:Q104) -> 47154.986
B107: Net Block | C107: =+C99-C105 -> 2682 | D107: =+D99-D105 -> 2946 | E107: =+E99-E105 -> 2558 | F107: =+F99-F105 -> 3574 | G107: =+G99-G105 -> 3574 | H107: =+H99-H105 -> 4996.4 | I107: =+I99-I105 -> 6418.8 | J107: =+J99-J105 -> 7841.2 | ... Q107: =+Q99-Q105 -> 26082.058
B109: Computer & Servers
B110: Opening Gross Block | C110: 91616 | D110: =+C114 -> 99043 | E110: =+D114 -> 107398 | F110: =+E114 -> 103722 | G110: =+F114 -> 117968 | H110: =+G114 -> 117968 | I110: =+H114 -> 137912.4 | J110: =+I114 -> 157856.8 | K110: =+J114 -> 177801.2 | ... Q110: =+P114 -> 378840.75
B111: Additions | C111: 7240 | D111: 8569 | E111: =9+7910 -> 7919 | F111: =229+10281 -> 10510 | H111: =F111*1.4 -> 14714 | I111: =H111 -> 14714 | J111: =I111 -> 14714 | K111: =J111*1.4 -> 20599.6 | L111: =K111 -> 20599.6 | M111: =L111 -> 20599.6 | N111: =M111*1.4 -> 28839.44 | O111: =N111 -> 28839.44 | P111: =O111 -> 28839.44 | Q111: =P111*1.4 -> 40375.216
B112: Disposals / Adjustments | C112: -131 | D112: -450 | E112: -486 | F112: =3869-660-1771 -> 1438 | H112: =F112*1.4 -> 2013.2 | I112: =H112 -> 2013.2 | J112: =I112 -> 2013.2 | K112: =J112*1.4 -> 2818.48 | L112: =K112 -> 2818.48 | M112: =L112 -> 2818.48 | N112: =M112*1.4 -> 3945.872 | O112: =N112 -> 3945.872 | P112: =O112 -> 3945.872 | Q112: =P112*1.4 -> 5524.2208
B113: Exchange Differences | C113: 318 | D113: 236 | E113: -11109 | F113: 2298 | H113: =F113*1.4 -> 3217.2 | I113: =H113 -> 3217.2 | J113: =I113 -> 3217.2 | K113: =J113*1.4 -> 4504.08 | L113: =K113 -> 4504.08 | M113: =L113 -> 4504.08 | N113: =M113*1.4 -> 6305.712 | O113: =N113 -> 6305.712 | P113: =O113 -> 6305.712 | Q113: =P113*1.4 -> 8827.9968
B114: Closing Gross Block | C114: =SUM(C110:C113) -> 99043 | D114: =SUM(D110:D113) -> 107398 | E114: =SUM(E110:E113) -> 103722 | F114: =SUM(F110:F113) -> 117968 | G114: =SUM(G110:G113) -> 117968 | H114: =SUM(H110:H113) -> 137912.4 | I114: =SUM(I110:I113) -> 157856.8 | J114: =SUM(J110:J113) -> 177801.2 | ... Q114: =SUM(Q110:Q113) -> 433568.19
B116: Opening Accumulated Depreciation | C116: 83078 | D116: =+C120 -> 89290 | E116: =+D120 -> 95630 | F116: =+E120 -> 92675 | G116: =+F120 -> 103792 | H116: =+G120 -> 103792 | I116: =+H120 -> 119355.8 | J116: =+I120 -> 134919.6 | K116: =+J120 -> 150483.4 | ... Q116: =+P120 -> 307366.5
B117: Depreciation | C117: 6177 | D117: 6415 | E117: 7041 | F117: 7450 | H117: =F117*1.4 -> 10430 | I117: =H117 -> 10430 | J117: =I117 -> 10430 | K117: =J117*1.4 -> 14602 | L117: =K117 -> 14602 | M117: =L117 -> 14602 | N117: =M117*1.4 -> 20442.8 | O117: =N117 -> 20442.8 | P117: =O117 -> 20442.8 | Q117: =P117*1.4 -> 28619.92
B118: Disposals / Adjustments | C118: -265 | D118: -464 | E118: -102 | F118: =-650+3829-1667 -> 1512 | H118: =F118*1.4 -> 2116.8 | I118: =H118 -> 2116.8 | J118: =I118 -> 2116.8 | K118: =J118*1.4 -> 2963.52 | L118: =K118 -> 2963.52 | M118: =L118 -> 2963.52 | N118: =M118*1.4 -> 4148.928 | O118: =N118 -> 4148.928 | P118: =O118 -> 4148.928 | Q118: =P118*1.4 -> 5808.4992
B119: Exchange Differences | C119: 300 | D119: 389 | E119: -9894 | F119: 2155 | H119: =F119*1.4 -> 3017 | I119: =H119 -> 3017 | J119: =I119 -> 3017 | K119: =J119*1.4 -> 4223.8 | L119: =K119 -> 4223.8 | M119: =L119 -> 4223.8 | N119: =M119*1.4 -> 5913.32 | O119: =N119 -> 5913.32 | P119: =O119 -> 5913.32 | Q119: =P119*1.4 -> 8278.648
B120: Closing Accumulated Depreciation | C120: =SUM(C116:C119) -> 89290 | D120: =SUM(D116:D119) -> 95630 | E120: =SUM(E116:E119) -> 92675 | F120: =SUM(F116:F119) -> 103792 | G120: =SUM(G116:G119) -> 103792 | H120: =SUM(H116:H119) -> 119355.8 | I120: =SUM(I116:I119) -> 134919.6 | J120: =SUM(J116:J119) -> 150483.4 | ... Q120: =SUM(Q116:Q119) -> 350073.57
B122: Net Block | C122: =+C114-C120 -> 9753 | D122: =+D114-D120 -> 11768 | E122: =+E114-E120 -> 11047 | F122: =+F114-F120 -> 14176 | G122: =+G114-G120 -> 14176 | H122: =+H114-H120 -> 18556.6 | I122: =+I114-I120 -> 22937.2 | J122: =+J114-J120 -> 27317.8 | ... Q122: =+Q114-Q120 -> 83494.614
B124: Aircraft
B125: Opening Gross Block | C125: 0 | D125: =+C129 -> 0 | E125: =+D129 -> 3960 | F125: =+E129 -> 3960 | G125: =+F129 -> 4118 | H125: =+G129 -> 4277 | I125: =+H129 -> 4498.2 | J125: =+I129 -> 4719.4 | K125: =+J129 -> 4940.6 | ... Q125: =+P129 -> 7170.296
B126: Additions | D126: 3960 | E126: - | F126: - | G126: - | H126: - | I126: - | J126: - | K126: - | L126: - | M126: - | N126: - | O126: - | P126: - | Q126: -
...

Sheet BS items
A1: Bharti Airtel Ltd
R6: (INR in millions)
B7: Balance Sheet Items
B8: Particulars | D8: =FAS!C7 -> 2022 | E8: =FAS!D7 -> 2023 | F8: =FAS!E7 -> 2024 | G8: =FAS!F7 -> 2025 | H8: =FAS!G7 -> 2026 | I8: =FAS!H7 -> 2027 | J8: =FAS!I7 -> 2028 | K8: =FAS!J7 -> 2029 | ... R8: =FAS!Q7 -> 2036
D9: Audited | E9: Audited | F9: Audited | G9: Audited | H9: Audited | I9: Estimated | J9: Projected | K9: Projected | L9: Projected | M9: Projected | N9: Projected | O9: Projected | P9: Projected | Q9: Projected | R9: Projected
B10: ASSETS
B12: Non-Current Assets
C13: ='BS Input'!B16 -> Investment in Joint Ventures & Associates | D13: ='BS Input'!C16 -> 284268 | E13: ='BS Input'!D16 -> 281838 | F13: ='BS Input'!E16 -> 312404 | G13: ='BS Input'!F16 -> 36416 | H13: ='BS Input'!G16 -> 40622 | I13: ='Revenue Buildup'!H$14*I14 -> 353269.21 | J13: ='Revenue Buildup'!I$14*J14 -> 397734.81 | K13: ='Revenue Buildup'!J$14*K14 -> 443677.06 | L13: ='Revenue Buildup'!K$14*L14 -> 490334.88 | M13: ='Revenue Buildup'!L$14*M14 -> 536833.62 | N13: ='Revenue Buildup'!M$14*N14 -> 582208.44 | O13: ='Revenue Buildup'!N$14*O14 -> 625435.1 | P13: ='Revenue Buildup'!O$14*P14 -> 665467.26 | ... R13: ='Revenue Buildup'!Q$14*R14 -> 731906.59
D14: =D13/'P&L Input'!C$11 -> 0.24390868 | E14: =E13/'P&L Input'!D$11 -> 0.20255015 | F14: =F13/'P&L Input'!E$11 -> 0.20829377 | G14: =G13/'P&L Input'!F$11 -> 0.021051512 | H14: =H13/'P&L Input'!G$11 -> 0.019254615 | I14: =AVERAGE(D14:H14) -> 0.13901174 | J14: =I14 -> 0.13901174 | K14: =J14 -> 0.13901174 | L14: =K14 -> 0.13901174 | M14: =L14 -> 0.13901174 | N14: =M14 -> 0.13901174 | O14: =N14 -> 0.13901174 | P14: =O14 -> 0.13901174 | Q14: =P14 -> 0.13901174 | R14: =Q14 -> 0.13901174
C15: ='BS Input'!B18 -> Investments | D15: ='BS Input'!C18 -> 609 | E15: ='BS Input'!D18 -> 656 | F15: ='BS Input'!E18 -> 924 | G15: ='BS Input'!F18 -> 5435 | H15: ='BS Input'!G18 -> 11385 | I15: ='Revenue Buildup'!H$14*I16 -> 5157.9948 | J15: ='Revenue Buildup'!I$14*J16 -> 5807.2259 | K15: ='Revenue Buildup'!J$14*K16 -> 6478.0171 | L15: ='Revenue Buildup'!K$14*L16 -> 7159.2562 | M15: ='Revenue Buildup'!L$14*M16 -> 7838.1727 | N15: ='Revenue Buildup'!M$14*N16 -> 8500.679 | O15: ='Revenue Buildup'!N$14*O16 -> 9131.8205 | P15: ='Revenue Buildup'!O$14*P16 -> 9716.32 | ... R15: ='Revenue Buildup'!Q$14*R16 -> 10686.384
D16: =D15/'P&L Input'!C$11 -> 0.00052253642 | E16: =E15/'P&L Input'!D$11 -> 0.00047145132 | F16: =F15/'P&L Input'!E$11 -> 0.00061607229 | G16: =G15/'P&L Input'!F$11 -> 0.0031418873 | H16: =H15/'P&L Input'!G$11 -> 0.0053964303 | I16: =AVERAGE(D16:H16) -> 0.0020296755 | J16: =I16 -> 0.0020296755 | K16: =J16 -> 0.0020296755 | L16: =K16 -> 0.0020296755 | M16: =L16 -> 0.0020296755 | N16: =M16 -> 0.0020296755 | O16: =N16 -> 0.0020296755 | P16: =O16 -> 0.0020296755 | Q16: =P16 -> 0.0020296755 | R16: =Q16 -> 0.0020296755
C17: Other financial assets | D17: ='BS Input'!C22 -> 22515 | E17: ='BS Input'!D22 -> 25963 | F17: ='BS Input'!E22 -> 26557 | G17: ='BS Input'!F22 -> 37471 | H17: ='BS Input'!G22 -> 35700 | I17: ='Revenue Buildup'!H$14*I18 -> 47912.03 | J17: ='Revenue Buildup'!I$14*J18 -> 53942.664 | K17: ='Revenue Buildup'!J$14*K18 -> 60173.568 | L17: ='Revenue Buildup'!K$14*L18 -> 66501.52 | M17: ='Revenue Buildup'!L$14*M18 -> 72807.899 | N17: ='Revenue Buildup'!M$14*N18 -> 78961.845 | O17: ='Revenue Buildup'!N$14*O18 -> 84824.447 | P17: ='Revenue Buildup'!O$14*P18 -> 90253.797 | ... R17: ='Revenue Buildup'!Q$14*R18 -> 99264.612
D18: =D17/'P&L Input'!C$11 -> 0.019318403 | E18: =E17/'P&L Input'!D$11 -> 0.01865898 | F18: =F17/'P&L Input'!E$11 -> 0.017706744 | G18: =G17/'P&L Input'!F$11 -> 0.021661391 | H18: =H17/'P&L Input'!G$11 -> 0.016921613 | I18: =AVERAGE(D18:H18) -> 0.018853426 | J18: =I18 -> 0.018853426 | K18: =J18 -> 0.018853426 | L18: =K18 -> 0.018853426 | M18: =L18 -> 0.018853426 | N18: =M18 -> 0.018853426 | O18: =N18 -> 0.018853426 | P18: =O18 -> 0.018853426 | Q18: =P18 -> 0.018853426 | R18: =Q18 -> 0.018853426
C19: Income tax assets (net) | D19: ='BS Input'!C23 -> 17479 | E19: ='BS Input'!D23 -> 20399 | F19: ='BS Input'!E23 -> 14135 | G19: ='BS Input'!F23 -> 24978 | H19: ='BS Input'!G23 -> 20181 | I19: ='Revenue Buildup'!H14*I20 -> 32064.567 | J19: ='Revenue Buildup'!I14*J20 -> 36100.498 | K19: ='Revenue Buildup'!J14*K20 -> 40270.458 | L19: ='Revenue Buildup'!K14*L20 -> 44505.366 | M19: ='Revenue Buildup'!L14*M20 -> 48725.836 | N19: ='Revenue Buildup'!M14*N20 -> 52844.293 | O19: ='Revenue Buildup'!N14*O20 -> 56767.771 | P19: ='Revenue Buildup'!O14*P20 -> 60401.299 | ... R19: ='Revenue Buildup'!Q14*R20 -> 66431.682
D20: =D19/'P&L Input'!C$11 -> 0.014997396 | E20: =E19/'P&L Input'!D$11 -> 0.014660268 | F20: =F19/'P&L Input'!E$11 -> 0.0094244391 | G20: =G19/'P&L Input'!F$11 -> 0.014439386 | H20: =H19/'P&L Input'!G$11 -> 0.0095656881 | I20: =AVERAGE(D20:H20) -> 0.012617435 | J20: =I20 -> 0.012617435 | K20: =J20 -> 0.012617435 | L20: =K20 -> 0.012617435 | M20: =L20 -> 0.012617435 | N20: =M20 -> 0.012617435 | O20: =N20 -> 0.012617435 | P20: =O20 -> 0.012617435 | Q20: =P20 -> 0.012617435 | R20: =Q20 -> 0.012617435
C21: Deferred Tax Assets(net) | D21: ='BS Input'!C24 -> 199250 | E21: ='BS Input'!D24 -> 189519 | F21: ='BS Input'!E24 -> 192428 | G21: ='BS Input'!F24 -> 249111 | H21: ='BS Input'!G24 -> 191413 | I21: ='Revenue Buildup'!H$14*I22 -> 340634.66 | J21: ='Revenue Buildup'!I$14*J22 -> 383509.97 | K21: ='Revenue Buildup'!J$14*K22 -> 427809.11 | L21: ='Revenue Buildup'!K$14*L22 -> 472798.22 | M21: ='Revenue Buildup'!L$14*M22 -> 517633.96 | N21: ='Revenue Buildup'!M$14*N22 -> 561385.97 | O21: ='Revenue Buildup'!N$14*O22 -> 603066.64 | P21: ='Revenue Buildup'!O$14*P22 -> 641667.06 | ... R21: ='Revenue Buildup'!Q$14*R22 -> 705730.22
D22: =D21/'P&L Input'!C$11 -> 0.17096122 | E22: =E21/'P&L Input'!D$11 -> 0.13620272 | F22: =F21/'P&L Input'!E$11 -> 0.12830039 | G22: =G21/'P&L Input'!F$11 -> 0.14400712 | H22: =H21/'P&L Input'!G$11 -> 0.090728757 | I22: =AVERAGE(D22:H22) -> 0.13404004 | J22: =I22 -> 0.13404004 | K22: =J22 -> 0.13404004 | L22: =K22 -> 0.13404004 | M22: =L22 -> 0.13404004 | N22: =M22 -> 0.13404004 | O22: =N22 -> 0.13404004 | P22: =O22 -> 0.13404004 | Q22: =P22 -> 0.13404004 | R22: =Q22 -> 0.13404004
C23: Other non-current assets | D23: ='BS Input'!C25 -> 91562 | E23: ='BS Input'!D25 -> 103898 | F23: ='BS Input'!E25 -> 112159 | G23: ='BS Input'!F25 -> 116638 | H23: ='BS Input'!G25 -> 124770 | I23: ='Revenue Buildup'!H$14*I24 -> 239429.28 | J23: ='Revenue Buildup'!I$14*J24 -> 269565.98 | K23: ='Revenue Buildup'!J$14*K24 -> 300703.48 | L23: ='Revenue Buildup'!K$14*L24 -> 332325.95 | M23: ='Revenue Buildup'!L$14*M24 -> 363840.62 | N23: ='Revenue Buildup'!M$14*N24 -> 394593.55 | O23: ='Revenue Buildup'!N$14*O24 -> 423890.54 | P23: ='Revenue Buildup'!O$14*P24 -> 451022.46 | ... R23: ='Revenue Buildup'!Q$14*R24 -> 496051.92
D24: =D23/'P&L Input'!$C$11 -> 0.078562364 | E24: =E23/'P&L Input'!$C$11 -> 0.089146944 | F24: =F23/'P&L Input'!$C$11 -> 0.096235078 | G24: =G23/'P&L Input'!$C$11 -> 0.10007817 | H24: =H23/'P&L Input'!$C$11 -> 0.10705561 | I24: =AVERAGE(D24:H24) -> 0.094215633 | J24: =I24 -> 0.094215633 | K24: =J24 -> 0.094215633 | L24: =K24 -> 0.094215633 | M24: =L24 -> 0.094215633 | N24: =M24 -> 0.094215633 | O24: =N24 -> 0.094215633 | P24: =O24 -> 0.094215633 | Q24: =P24 -> 0.094215633 | R24: =Q24 -> 0.094215633
B25: Current Assets
C26: Investments | D26: ='BS Input'!C28 -> 3750 | E26: ='BS Input'!D28 -> 2576 | F26: ='BS Input'!E28 -> 3639 | G26: ='BS Input'!F28 -> 4517 | H26: ='BS Input'!G28 -> 6009 | I26: ='Revenue Buildup'!H$14*I27 -> 8936.0731 | J26: ='Revenue Buildup'!I$14*J27 -> 10060.847 | K26: ='Revenue Buildup'!J$14*K27 -> 11222.973 | L26: ='Revenue Buildup'!K$14*L27 -> 12403.199 | M26: ='Revenue Buildup'!L$14*M27 -> 13579.402 | N26: ='Revenue Buildup'!M$14*N27 -> 14727.174 | O26: ='Revenue Buildup'!N$14*O27 -> 15820.608 | P26: ='Revenue Buildup'!O$14*P27 -> 16833.236 | ... R26: ='Revenue Buildup'!Q$14*R27 -> 18513.843
D27: =D26/'P&L Input'!$C$11 -> 0.0032175888 | E27: =E26/'P&L Input'!$C$11 -> 0.002210269 | F27: =F26/'P&L Input'!$C$11 -> 0.0031223482 | G27: =G26/'P&L Input'!$C$11 -> 0.003875693 | H27: =H26/'P&L Input'!$C$11 -> 0.0051558643 | I27: =AVERAGE(D27:H27) -> 0.0035163526 | J27: =I27 -> 0.0035163526 | K27: =J27 -> 0.0035163526 | L27: =K27 -> 0.0035163526 | M27: =L27 -> 0.0035163526 | N27: =M27 -> 0.0035163526 | O27: =N27 -> 0.0035163526 | P27: =O27 -> 0.0035163526 | Q27: =P27 -> 0.0035163526 | R27: =Q27 -> 0.0035163526
C28: Other financial assets | D28: ='BS Input'!C34 -> 214697 | E28: ='BS Input'!D34 -> 220865 | F28: ='BS Input'!E34 -> 249544 | G28: ='BS Input'!F34 -> 267662 | H28: ='BS Input'!G34 -> 244264 | I28: ='Revenue Buildup'!H$14*I29 -> 396359.28 | J28: ='Revenue Buildup'!I$14*J29 -> 446248.59 | K28: ='Revenue Buildup'!J$14*K29 -> 497794.65 | L28: ='Revenue Buildup'!K$14*L29 -> 550143.56 | M28: ='Revenue Buildup'!L$14*M29 -> 602314 | N28: ='Revenue Buildup'!M$14*N29 -> 653223.43 | O28: ='Revenue Buildup'!N$14*O29 -> 701722.66 | P28: ='Revenue Buildup'!O$14*P29 -> 746637.75 | ... R28: ='Revenue Buildup'!Q$14*R29 -> 821181.03
D29: =D28/'P&L Input'!C$11 -> 0.18421511 | E29: =E28/'P&L Input'!D$11 -> 0.15873033 | F29: =F28/'P&L Input'!E$11 -> 0.16638219 | G29: =G28/'P&L Input'!F$11 -> 0.15473116 | H29: =H28/'P&L Input'!G$11 -> 0.11577985 | I29: =AVERAGE(D29:H29) -> 0.15596773 | J29: =I29 -> 0.15596773 | K29: =J29 -> 0.15596773 | L29: =K29 -> 0.15596773 | M29: =L29 -> 0.15596773 | N29: =M29 -> 0.15596773 | O29: =N29 -> 0.15596773 | P29: =O29 -> 0.15596773 | Q29: =P29 -> 0.15596773 | R29: =Q29 -> 0.15596773
C30: Other current assets | D30: ='BS Input'!C35 -> 117152 | E30: ='BS Input'!D35 -> 129243 | F30: ='BS Input'!E35 -> 115039 | G30: ='BS Input'!F35 -> 144608 | H30: ='BS Input'!G35 -> 125718 | I30: ='Revenue Buildup'!H$14*I31 -> 210057.95 | J30: ='Revenue Buildup'!I$14*J31 -> 236497.71 | K30: ='Revenue Buildup'!J$14*K31 -> 263815.5 | L30: ='Revenue Buildup'!K$14*L31 -> 291558.77 | M30: ='Revenue Buildup'!L$14*M31 -> 319207.47 | N30: ='Revenue Buildup'!M$14*N31 -> 346187.86 | O30: ='Revenue Buildup'!N$14*O31 -> 371890.92 | P30: ='Revenue Buildup'!O$14*P31 -> 395694.51 | ... R30: ='Revenue Buildup'!Q$14*R31 -> 435200.1
D31: =D30/'P&L Input'!C$11 -> 0.10051919 | E31: =E30/'P&L Input'!D$11 -> 0.092883816 | F31: =F30/'P&L Input'!E$11 -> 0.076701666 | G31: =G30/'P&L Input'!F$11 -> 0.083595591 | H31: =H30/'P&L Input'!G$11 -> 0.059589672 | I31: =AVERAGE(D31:H31) -> 0.082657987 | J31: =I31 -> 0.082657987 | K31: =J31 -> 0.082657987 | L31: =K31 -> 0.082657987 | M31: =L31 -> 0.082657987 | N31: =M31 -> 0.082657987 | O31: =N31 -> 0.082657987 | P31: =O31 -> 0.082657987 | Q31: =P31 -> 0.082657987 | R31: =Q31 -> 0.082657987
B33: LIABILITIES
B35: Non-current liabilities
C36: Borrowings | D36: ='BS Input'!C48 -> 1135350 | E36: ='BS Input'!D48 -> 1515686 | F36: ='BS Input'!E48 -> 1309626 | G36: ='BS Input'!F48 -> 1048638 | H36: ='BS Input'!G48 -> 1000849 | I36: ='Revenue Buildup'!H$14*I37 -> 1205581 | J36: ='Revenue Buildup'!I$14*J37 -> 1357326.1 | K36: ='Revenue Buildup'!J$14*K37 -> 1514110.5 | L36: ='Revenue Buildup'!K$14*L37 -> 1673336.9 | M36: ='Revenue Buildup'!L$14*M37 -> 1832020.4 | N36: ='Revenue Buildup'!M$14*N37 -> 1986868.4 | O36: ='Revenue Buildup'!N$14*O37 -> 2134385.4 | P36: ='Revenue Buildup'!O$14*P37 -> 2271000.8 | ... R36: ='Revenue Buildup'!Q$14*R37 -> 2497734.4
D37: =D36/'P&L Input'!C$11 -> 0.97415718 | E37: =E36/'P&L Input'!D$11 -> 1.0892868 | F37: =F36/'P&L Input'!E$11 -> 0.87318645 | G37: =G36/'P&L Input'!F$11 -> 0.60620099 | H37: =H36/'P&L Input'!G$11 -> 0.47439717 | I37: =MIN(D37:H37) -> 0.47439717 | J37: =I37 -> 0.47439717 | K37: =J37 -> 0.47439717 | L37: =K37 -> 0.47439717 | M37: =L37 -> 0.47439717 | N37: =M37 -> 0.47439717 | O37: =N37 -> 0.47439717 | P37: =O37 -> 0.47439717 | Q37: =P37 -> 0.47439717 | R37: =Q37 -> 0.47439717
C38: Lease liabilities | D38: ='BS Input'!C49 -> 290562 | E38: ='BS Input'!D49 -> 508295 | F38: ='BS Input'!E49 -> 539271 | G38: ='BS Input'!F49 -> 556701 | H38: ='BS Input'!G49 -> 644996 | I38: ='Revenue Buildup'!H$14*I39 -> 814081.69 | J38: ='Revenue Buildup'!I$14*J39 -> 916549.25 | K38: ='Revenue Buildup'!J$14*K39 -> 1022419.6 | L38: ='Revenue Buildup'!K$14*L39 -> 1129939 | M38: ='Revenue Buildup'!L$14*M39 -> 1237091.8 | N38: ='Revenue Buildup'!M$14*N39 -> 1341654.5 | O38: ='Revenue Buildup'!N$14*O39 -> 1441267 | P38: ='Revenue Buildup'!O$14*P39 -> 1533518.1 | ... R38: ='Revenue Buildup'!Q$14*R39 -> 1686622.4
D39: =D38/'P&L Input'!C$11 -> 0.24930908 | E39: =E38/'P&L Input'!D$11 -> 0.36529931 | F39: =F38/'P&L Input'!E$11 -> 0.35955619 | G39: =G38/'P&L Input'!F$11 -> 0.32182002 | H39: =H38/'P&L Input'!G$11 -> 0.30572472 | I39: =AVERAGE(D39:H39) -> 0.32034186 | J39: =I39 -> 0.32034186 | K39: =J39 -> 0.32034186 | L39: =K39 -> 0.32034186 | M39: =L39 -> 0.32034186 | N39: =M39 -> 0.32034186 | O39: =N39 -> 0.32034186 | P39: =O39 -> 0.32034186 | Q39: =P39 -> 0.32034186 | R39: =Q39 -> 0.32034186
C40: Other Financial liabilities | D40: ='BS Input'!C51 -> 90116 | E40: ='BS Input'!D51 -> 97311 | F40: ='BS Input'!E51 -> 85036 | G40: ='BS Input'!F51 -> 38642 | H40: ='BS Input'!G51 -> 26320 | I40: ='Revenue Buildup'!H$14*I41 -> 121355.72 | J40: ='Revenue Buildup'!I$14*J41 -> 136630.63 | K40: ='Revenue Buildup'!J$14*K41 -> 152412.8 | L40: ='Revenue Buildup'!K$14*L41 -> 168440.78 | M40: ='Revenue Buildup'!L$14*M41 -> 184414.12 | N40: ='Revenue Buildup'!M$14*N41 -> 200001.37 | O40: ='Revenue Buildup'!N$14*O41 -> 214850.67 | P40: ='Revenue Buildup'!O$14*P41 -> 228602.59 | ... R40: ='Revenue Buildup'!Q$14*R41 -> 251425.96
D41: =D40/'P&L Input'!C$11 -> 0.077321662 | E41: =E40/'P&L Input'!D$11 -> 0.06993506 | F41: =F40/'P&L Input'!E$11 -> 0.056697319 | G41: =G40/'P&L Input'!F$11 -> 0.022338327 | H41: =H40/'P&L Input'!G$11 -> 0.012475542 | I41: =AVERAGE(D41:H41) -> 0.047753582 | J41: =I41 -> 0.047753582 | K41: =J41 -> 0.047753582 | L41: =K41 -> 0.047753582 | M41: =L41 -> 0.047753582 | N41: =M41 -> 0.047753582 | O41: =N41 -> 0.047753582 | P41: =O41 -> 0.047753582 | Q41: =P41 -> 0.047753582 | R41: =Q41 -> 0.047753582
C42: Provisions | D42: ='BS Input'!C53 -> 4639 | E42: ='BS Input'!D53 -> 4744 | F42: ='BS Input'!E53 -> 5443 | G42: ='BS Input'!F53 -> 30396 | H42: ='BS Input'!G53 -> 35189 | I42: ='Revenue Buildup'!H$14*I43 -> 16409.583 | J42: ='Revenue Buildup'!I$14*J43 -> 18475.039 | K42: ='Revenue Buildup'!J$14*K43 -> 20609.086 | L42: ='Revenue Buildup'!K$14*L43 -> 22776.371 | M42: ='Revenue Buildup'!L$14*M43 -> 24936.268 | N42: ='Revenue Buildup'!M$14*N43 -> 27043.958 | O42: ='Revenue Buildup'!N$14*O43 -> 29051.864 | P42: ='Revenue Buildup'!O$14*P43 -> 30911.383 | ... R42: ='Revenue Buildup'!Q$14*R43 -> 33997.534
D43: =D42/'P&L Input'!C$11 -> 0.0039803719 | E43: =E42/'P&L Input'!D$11 -> 0.003409398 | F43: =F42/'P&L Input'!E$11 -> 0.0036290925 | G43: =G42/'P&L Input'!F$11 -> 0.017571445 | H43: =H42/'P&L Input'!G$11 -> 0.016679401 | I43: =AVEDEV(D43:H43) -> 0.0064571852 | J43: =I43 -> 0.0064571852 | K43: =J43 -> 0.0064571852 | L43: =K43 -> 0.0064571852 | M43: =L43 -> 0.0064571852 | N43: =M43 -> 0.0064571852 | O43: =N43 -> 0.0064571852 | P43: =O43 -> 0.0064571852 | Q43: =P43 -> 0.0064571852 | R43: =Q43 -> 0.0064571852
C44: Deferred Tax Liability(net) | D44: ='BS Input'!C54 -> 24488 | E44: ='BS Input'!D54 -> 20762 | F44: ='BS Input'!E54 -> 25118 | G44: ='BS Input'!F54 -> 93549 | H44: ='BS Input'!G54 -> 67789 | I44: ='Revenue Buildup'!H$14*I45 -> 70592.244 | J44: ='Revenue Buildup'!I$14*J45 -> 79477.612 | K44: ='Revenue Buildup'!J$14*K45 -> 88658.051 | L44: ='Revenue Buildup'!K$14*L45 -> 97981.479 | M44: ='Revenue Buildup'!L$14*M45 -> 107273.12 | N44: ='Revenue Buildup'!M$14*N45 -> 116340.17 | O44: ='Revenue Buildup'!N$14*O45 -> 124977.97 | P44: ='Revenue Buildup'!O$14*P45 -> 132977.42 | ... R44: ='Revenue Buildup'!Q$14*R45 -> 146253.7
D45: =D44/'P&L Input'!C$11 -> 0.021011284 | E45: =E44/'P&L Input'!D$11 -> 0.014921147 | F45: =F44/'P&L Input'!E$11 -> 0.016747298 | G45: =G44/'P&L Input'!F$11 -> 0.054079193 | H45: =H44/'P&L Input'!G$11 -> 0.03213163 | I45: =AVERAGE(D45:H45) -> 0.02777811 | J45: =I45 -> 0.02777811 | K45: =J45 -> 0.02777811 | L45: =K45 -> 0.02777811 | M45: =L45 -> 0.02777811 | N45: =M45 -> 0.02777811 | O45: =N45 -> 0.02777811 | P45: =O45 -> 0.02777811 | Q45: =P45 -> 0.02777811 | R45: =Q45 -> 0.02777811
C46: ='BS Input'!B55 -> Other non-current liabilities | D46: ='BS Input'!C55 -> 1363 | E46: ='BS Input'!D55 -> 1029 | F46: ='BS Input'!E55 -> 1470 | G46: ='BS Input'!F55 -> 1414 | H46: ='BS Input'!G55 -> 1497 | I46: ='Revenue Buildup'!H$14*I47 -> 2244.5184 | J46: ='Revenue Buildup'!I$14*J47 -> 2527.0334 | K46: ='Revenue Buildup'!J$14*K47 -> 2818.9304 | L46: ='Revenue Buildup'!K$14*L47 -> 3115.3738 | M46: ='Revenue Buildup'!L$14*M47 -> 3410.8066 | N46: ='Revenue Buildup'!M$14*N47 -> 3699.0984 | O46: ='Revenue Buildup'!N$14*O47 -> 3973.7416 | P46: ='Revenue Buildup'!O$14*P47 -> 4228.0885 | ... R46: ='Revenue Buildup'!Q$14*R47 -> 4650.2151
D47: =D46/'P&L Input'!C$11 -> 0.0011694863 | E47: =E46/'P&L Input'!D$11 -> 0.00073951739 | F47: =F46/'P&L Input'!E$11 -> 0.000980115 | G47: =G46/'P&L Input'!F$11 -> 0.00081741097 | H47: =H46/'P&L Input'!G$11 -> 0.00070957014 | I47: =AVERAGE(D47:H47) -> 0.00088321996 | J47: =I47 -> 0.00088321996 | K47: =J47 -> 0.00088321996 | L47: =K47 -> 0.00088321996 | M47: =L47 -> 0.00088321996 | N47: =M47 -> 0.00088321996 | O47: =N47 -> 0.00088321996 | P47: =O47 -> 0.00088321996 | Q47: =P47 -> 0.00088321996 | R47: =Q47 -> 0.00088321996
B49: Current Liabilities
C50: Borrowings | D50: ='BS Input'!C59 -> 193795 | E50: ='BS Input'!D59 -> 139762 | F50: ='BS Input'!E59 -> 209539 | G50: ='BS Input'!F59 -> 434485 | H50: ='BS Input'!G59 -> 215865 | I50: ='Revenue Buildup'!H$14*I51 -> 386236.03 | J50: ='Revenue Buildup'!I$14*J51 -> 434851.13 | K50: ='Revenue Buildup'!J$14*K51 -> 485080.68 | L50: ='Revenue Buildup'!K$14*L51 -> 536092.56 | M50: ='Revenue Buildup'!L$14*M51 -> 586930.54 | N50: ='Revenue Buildup'!M$14*N51 -> 636539.7 | O50: ='Revenue Buildup'!N$14*O51 -> 683800.24 | P50: ='Revenue Buildup'!O$14*P51 -> 727568.17 | ... R50: ='Revenue Buildup'!Q$14*R51 -> 800207.57
D51: =D50/'P&L Input'!C$11 -> 0.1662807 | E51: =E50/'P&L Input'!D$11 -> 0.10044357 | F51: =F50/'P&L Input'!E$11 -> 0.13970906 | G51: =G50/'P&L Input'!F$11 -> 0.25116889 | H51: =H50/'P&L Input'!G$11 -> 0.10231888 | I51: =AVERAGE(D51:H51) -> 0.15198422 | J51: =I51 -> 0.15198422 | K51: =J51 -> 0.15198422 | L51: =K51 -> 0.15198422 | M51: =L51 -> 0.15198422 | N51: =M51 -> 0.15198422 | O51: =N51 -> 0.15198422 | P51: =O51 -> 0.15198422 | Q51: =P51 -> 0.15198422 | R51: =Q51 -> 0.15198422
C52: Lease liabilities | D52: ='BS Input'!C60 -> 77072 | E52: ='BS Input'!D60 -> 96460 | F52: ='BS Input'!E60 -> 97487 | G52: ='BS Input'!F60 -> 96597 | H52: ='BS Input'!G60 -> 92407 | I52: ='Revenue Buildup'!H$14*I53 -> 152525.02 | J52: ='Revenue Buildup'!I$14*J53 -> 171723.18 | K52: ='Revenue Buildup'!J$14*K53 -> 191558.88 | L52: ='Revenue Buildup'!K$14*L53 -> 211703.53 | M52: ='Revenue Buildup'!L$14*M53 -> 231779.5 | N52: ='Revenue Buildup'!M$14*N53 -> 251370.21 | O52: ='Revenue Buildup'!N$14*O53 -> 270033.45 | P52: ='Revenue Buildup'!O$14*P53 -> 287317.45 | ... R52: ='Revenue Buildup'!Q$14*R53 -> 316002.83
D53: =D52/'P&L Input'!C$11 -> 0.066129601 | E53: =E52/'P&L Input'!D$11 -> 0.069323467 | F53: =F52/'P&L Input'!E$11 -> 0.06499896 | G53: =G52/'P&L Input'!F$11 -> 0.055841193 | H53: =H52/'P&L Input'!G$11 -> 0.043800433 | I53: =AVERAGE(D53:H53) -> 0.060018731 | J53: =I53 -> 0.060018731 | K53: =J53 -> 0.060018731 | L53: =K53 -> 0.060018731 | M53: =L53 -> 0.060018731 | N53: =M53 -> 0.060018731 | O53: =N53 -> 0.060018731 | P53: =O53 -> 0.060018731 | Q53: =P53 -> 0.060018731 | R53: =Q53 -> 0.060018731
C54: Other financial liabilities | D54: ='BS Input'!C63 -> 194415 | E54: ='BS Input'!D63 -> 241951 | F54: ='BS Input'!E63 -> 253456 | G54: ='BS Input'!F63 -> 333024 | H54: ='BS Input'!G63 -> 408659 | I54: ='Revenue Buildup'!H$14*I55 -> 455351.26 | J54: ='Revenue Buildup'!I$14*J55 -> 512665.82 | K54: ='Revenue Buildup'!J$14*K55 -> 571883.72 | L54: ='Revenue Buildup'!K$14*L55 -> 632023.96 | M54: ='Revenue Buildup'!L$14*M55 -> 691959.17 | N54: ='Revenue Buildup'!M$14*N55 -> 750445.67 | O54: ='Revenue Buildup'!N$14*O55 -> 806163.27 | P54: ='Revenue Buildup'!O$14*P55 -> 857763.28 | ... R54: ='Revenue Buildup'!Q$14*R55 -> 943401.18
D55: =D54/'P&L Input'!C$11 -> 0.16681267 | E55: =E54/'P&L Input'!D$11 -> 0.17388433 | F55: =F54/'P&L Input'!E$11 -> 0.16899049 | G55: =G54/'P&L Input'!F$11 -> 0.19251589 | H55: =H54/'P&L Input'!G$11 -> 0.19370222 | I55: =AVERAGE(D55:H55) -> 0.17918112 | J55: =I55 -> 0.17918112 | K55: =J55 -> 0.17918112 | L55: =K55 -> 0.17918112 | M55: =L55 -> 0.17918112 | N55: =M55 -> 0.17918112 | O55: =N55 -> 0.17918112 | P55: =O55 -> 0.17918112 | Q55: =P55 -> 0.17918112 | R55: =Q55 -> 0.17918112
C56: Other current liabilities | D56: ='BS Input'!C67 -> 41139 | E56: ='BS Input'!D67 -> 51143 | F56: ='BS Input'!E67 -> 59089 | G56: ='BS Input'!F67 -> 77522 | H56: ='BS Input'!G67 -> 77341 | I56: ='Revenue Buildup'!H$14*I57 -> 98055.297 | J56: ='Revenue Buildup'!I$14*J57 -> 110397.41 | K56: ='Revenue Buildup'!J$14*K57 -> 123149.39 | L56: ='Revenue Buildup'!K$14*L57 -> 136099.98 | M56: ='Revenue Buildup'!L$14*M57 -> 149006.42 | N56: ='Revenue Buildup'!M$14*N57 -> 161600.9 | O56: ='Revenue Buildup'!N$14*O57 -> 173599.12 | P56: ='Revenue Buildup'!O$14*P57 -> 184710.66 | ... R56: ='Revenue Buildup'!Q$14*R57 -> 203151.92
D57: =D56/'P&L Input'!C$11 -> 0.035298236 | E57: =E56/'P&L Input'!D$11 -> 0.036755236 | F57: =F56/'P&L Input'!E$11 -> 0.039397289 | G57: =G56/'P&L Input'!F$11 -> 0.044814238 | H57: =H56/'P&L Input'!G$11 -> 0.036659228 | I57: =AVERAGE(D57:H57) -> 0.038584846 | J57: =I57 -> 0.038584846 | K57: =J57 -> 0.038584846 | L57: =K57 -> 0.038584846 | M57: =L57 -> 0.038584846 | N57: =M57 -> 0.038584846 | O57: =N57 -> 0.038584846 | P57: =O57 -> 0.038584846 | Q57: =P57 -> 0.038584846 | R57: =Q57 -> 0.038584846
C58: Provisions | D58: ='BS Input'!C65 -> 243449 | E58: ='BS Input'!D65 -> 257292 | F58: ='BS Input'!E65 -> 283282 | G58: ='BS Input'!F65 -> 361552 | H58: ='BS Input'!G65 -> 357828 | I58: ='Revenue Buildup'!H$14*I59 -> 488582.1 | J58: ='Revenue Buildup'!I$14*J59 -> 550079.39 | K58: ='Revenue Buildup'!J$14*K59 -> 613618.92 | L58: ='Revenue Buildup'!K$14*L59 -> 678148.1 | M58: ='Revenue Buildup'!L$14*M59 -> 742457.29 | N58: ='Revenue Buildup'!M$14*N59 -> 805212.06 | O58: ='Revenue Buildup'!N$14*O59 -> 864995.84 | P58: ='Revenue Buildup'!O$14*P59 -> 920361.54 | ... R58: ='Revenue Buildup'!Q$14*R59 -> 1012249.2
D59: =D58/'P&L Input'!C$11 -> 0.20888501 | E59: =E58/'P&L Input'!D$11 -> 0.18490953 | F59: =F58/'P&L Input'!E$11 -> 0.18887683 | G59: =G58/'P&L Input'!F$11 -> 0.20900748 | H59: =H58/'P&L Input'!G$11 -> 0.16960859 | I59: =AVERAGE(D59:H59) -> 0.19225749 | J59: =I59 -> 0.19225749 | K59: =J59 -> 0.19225749 | L59: =K59 -> 0.19225749 | M59: =L59 -> 0.19225749 | N59: =M59 -> 0.19225749 | O59: =N59 -> 0.19225749 | P59: =O59 -> 0.19225749 | Q59: =P59 -> 0.19225749 | R59: =Q59 -> 0.19225749
C60: Current Tax Liabilities(net) | D60: ='BS Input'!C66 -> 20725 | E60: ='BS Input'!D66 -> 17972 | F60: ='BS Input'!E66 -> 33031 | G60: ='BS Input'!F66 -> 20035 | H60: ='BS Input'!G66 -> 31400 | I60: ='Revenue Buildup'!H$14*I61 -> 40247.525 | J60: ='Revenue Buildup'!I$14*J61 -> 44200.386 | K60: ='Revenue Buildup'!J$14*K61 -> 50922.453 | L60: ='Revenue Buildup'!K$14*L61 -> 51996.569 | M60: ='Revenue Buildup'!L$14*M61 -> 59367.545 | N60: ='Revenue Buildup'!M$14*N61 -> 64795.617 | O60: ='Revenue Buildup'!N$14*O61 -> 69276.709 | P60: ='Revenue Buildup'!O$14*P61 -> 73662.361 | ... R60: ='Revenue Buildup'!Q$14*R61 -> 80980.483
D61: =D60/'P&L Input'!C11 -> 0.017782541 | E61: =E60/'P&L Input'!D11 -> 0.012916041 | F61: =F60/'P&L Input'!E11 -> 0.022023251 | G61: =G60/'P&L Input'!F11 -> 0.011581916 | H61: =H60/'P&L Input'!G11 -> 0.014883435 | I61: =AVERAGEA(D61:H61) -> 0.015837437 | J61: =AVERAGEA(E61:I61) -> 0.015448416 | K61: =AVERAGEA(F61:J61) -> 0.015954891 | L61: =AVERAGEA(G61:K61) -> 0.014741219 | M61: =AVERAGEA(H61:L61) -> 0.01537308 | N61: =AVERAGEA(I61:M61) -> 0.015471008 | O61: =AVERAGEA(J61:N61) -> 0.015397723 | P61: =AVERAGEA(K61:O61) -> 0.015387584 | ... R61: =AVERAGEA(M61:Q61) -> 0.015380703

Sheet Working Capital
A1: Bharti Airtel Ltd
B7: Working Capital
B8: Particulars | C8: 2021-22 | D8: 2022-23 | E8: 2023-24 | F8: 2024-25 | G8: 2025-26 | H8: 2026-27 | I8: 2027-28 | J8: 2028-29 | K8: 2029-30 | L8: 2030-31 | M8: 2031-32 | N8: 2032-33 | O8: 2033-34 | P8: 2034-35 | Q8: 2035-36
C9: Audited | D9: Audited | E9: Audited | F9: Audited | G9: Audited | H9: Estimated | I9: Projected | J9: Projected | K9: Projected | L9: Projected | M9: Projected | N9: Projected | O9: Projected | P9: Projected | Q9: Projected
B11: Trade Receivables | C11: ='BS Input'!C31 -> 40562 | D11: ='BS Input'!D31 -> 39815 | E11: ='BS Input'!E31 -> 47277 | F11: ='BS Input'!F31 -> 74557 | G11: ='BS Input'!G31 -> 79776 | H11: =H12*'Revenue Buildup'!H14 -> 88597.888 | I11: =I12*'Revenue Buildup'!I14 -> 99749.606 | J11: =J12*'Revenue Buildup'!J14 -> 111271.66 | K11: =K12*'Revenue Buildup'!K14 -> 122973.17 | L11: =L12*'Revenue Buildup'!L14 -> 134634.79 | M11: =M12*'Revenue Buildup'!M14 -> 146014.53 | N11: =N12*'Revenue Buildup'!N14 -> 156855.53 | O11: =O12*'Revenue Buildup'!O14 -> 166895.37 | ... Q11: =Q12*'Revenue Buildup'!Q14 -> 183557.97
C12: =C11/'P&L Input'!C14 -> 0.034644332 | D12: =D11/'P&L Input'!D14 -> 0.02842276 | E12: =E11/'P&L Input'!E14 -> 0.031222881 | F12: =F11/'P&L Input'!F14 -> 0.042711658 | G12: =G11/'P&L Input'!G14 -> 0.037315105 | H12: =AVERAGE(C12:G12) -> 0.034863347 | I12: =H12 -> 0.034863347 | J12: =I12 -> 0.034863347 | K12: =J12 -> 0.034863347 | L12: =K12 -> 0.034863347 | M12: =L12 -> 0.034863347 | N12: =M12 -> 0.034863347 | O12: =N12 -> 0.034863347 | P12: =O12 -> 0.034863347 | Q12: =P12 -> 0.034863347
B13: ='BS Input'!B28 -> Inventories | C13: ='BS Input'!C28 -> 3750 | D13: ='BS Input'!D28 -> 2576 | E13: ='BS Input'!E28 -> 3639 | F13: ='BS Input'!F28 -> 4517 | G13: ='BS Input'!G28 -> 6009 | H13: ='Revenue Buildup'!H14*H14 -> 6527.8056 | I13: ='Revenue Buildup'!I14*I14 -> 7349.4533 | J13: ='Revenue Buildup'!J14*J14 -> 8198.3868 | K13: ='Revenue Buildup'!K14*K14 -> 9060.5427 | L13: ='Revenue Buildup'!L14*L14 -> 9919.7594 | M13: ='Revenue Buildup'!M14*M14 -> 10758.208 | N13: ='Revenue Buildup'!N14*N14 -> 11556.962 | O13: ='Revenue Buildup'!O14*O14 -> 12296.687 | ... Q13: ='Revenue Buildup'!Q14*Q14 -> 13524.371
C14: =C13/'P&L Input'!C14 -> 0.0032029053 | D14: =D13/'P&L Input'!D14 -> 0.0018389308 | E14: =E13/'P&L Input'!E14 -> 0.0024032842 | F14: =F13/'P&L Input'!F14 -> 0.0025876653 | G14: =G13/'P&L Input'!G14 -> 0.0028107008 | H14: =AVERAGE(C14:G14) -> 0.0025686973 | I14: =H14 -> 0.0025686973 | J14: =I14 -> 0.0025686973 | K14: =J14 -> 0.0025686973 | L14: =K14 -> 0.0025686973 | M14: =L14 -> 0.0025686973 | N14: =M14 -> 0.0025686973 | O14: =N14 -> 0.0025686973 | P14: =O14 -> 0.0025686973 | Q14: =P14 -> 0.0025686973
B15: Trade Payables | C15: ='BS Input'!C62 -> 292741 | D15: ='BS Input'!D62 -> 328946 | E15: ='BS Input'!E62 -> 351325 | F15: ='BS Input'!F62 -> 381537 | G15: ='BS Input'!G62 -> 450152 | H15: =H16*'Revenue Buildup'!H14 -> 582469.31 | I15: =I16*'Revenue Buildup'!I14 -> 655784.07 | J15: =J16*'Revenue Buildup'!J14 -> 731533.53 | K15: =K16*'Revenue Buildup'!K14 -> 808462.8 | L15: =L16*'Revenue Buildup'!L14 -> 885129.81 | M15: =M16*'Revenue Buildup'!M14 -> 959943.69 | N15: =N16*'Revenue Buildup'!N14 -> 1031215.7 | O15: =O16*'Revenue Buildup'!O14 -> 1097220.6 | ... Q15: =Q16*'Revenue Buildup'!Q14 -> 1206765.6
C16: =C15/'P&L Input'!C14 -> 0.25003246 | D16: =D15/'P&L Input'!D14 -> 0.23482489 | E16: =E15/'P&L Input'!E14 -> 0.23202358 | F16: =F15/'P&L Input'!F14 -> 0.21857207 | G16: =G15/'P&L Input'!G14 -> 0.21055793 | H16: =AVERAGE(C16:G16) -> 0.22920219 | I16: =H16 -> 0.22920219 | J16: =I16 -> 0.22920219 | K16: =J16 -> 0.22920219 | L16: =K16 -> 0.22920219 | M16: =L16 -> 0.22920219 | N16: =M16 -> 0.22920219 | O16: =N16 -> 0.22920219 | P16: =O16 -> 0.22920219 | Q16: =P16 -> 0.22920219
B18: Net Working Capital | C18: =C11+C13-C15 -> -248429 | D18: =D11+D13-D15 -> -286555 | E18: =E11+E13-E15 -> -300409 | F18: =F11+F13-F15 -> -302463 | G18: =G11+G13-G15 -> -364367 | H18: =H11+H13-H15 -> -487343.61 | I18: =I11+I13-I15 -> -548685.01 | J18: =J11+J13-J15 -> -612063.48 | ... Q18: =Q11+Q13-Q15 -> -1009683.3

Sheet Income Statement
A1: Bharti Airtel Ltd
Q6: (INR in millions)
B7: Income Statement
B8: Particulars | C8: =FAS!C7 -> 2022 | D8: =FAS!D7 -> 2023 | E8: =FAS!E7 -> 2024 | F8: =FAS!F7 -> 2025 | G8: =FAS!G7 -> 2026 | H8: =FAS!H7 -> 2027 | I8: =FAS!I7 -> 2028 | J8: =FAS!J7 -> 2029 | ... Q8: =FAS!Q7 -> 2036
C9: Audited | D9: Audited | E9: Audited | F9: Audited | G9: Audited | H9: Estimated | I9: Projected | J9: Projected | K9: Projected | L9: Projected | M9: Projected | N9: Projected | O9: Projected | P9: Projected | Q9: Projected
B10: ='P&L Input'!B11 -> Revenue from Sale of Service | C10: ='P&L Input'!C11 -> 1165469 | D10: ='P&L Input'!D11 -> 1391448 | E10: ='P&L Input'!E11 -> 1499824 | F10: ='P&L Input'!F11 -> 1729852 | G10: ='P&L Input'!G11 -> 2109728 | H10: ='Revenue Buildup'!H10 -> 2507801.6 | I10: ='Revenue Buildup'!I10 -> 2823455.7 | J10: ='Revenue Buildup'!J10 -> 3149592.4 | K10: ='Revenue Buildup'!K10 -> 3480808.8 | L10: ='Revenue Buildup'!L10 -> 3810896 | M10: ='Revenue Buildup'!M10 -> 4133004.5 | N10: ='Revenue Buildup'!N10 -> 4439863.6 | O10: ='Revenue Buildup'!O10 -> 4724045.5 | ... Q10: ='Revenue Buildup'!Q10 -> 5195687.7
B11: ='P&L Input'!B12 -> Other Operating Revenue | C11: ='P&L Input'!C12 -> 5343 | D11: ='P&L Input'!D12 -> 9366 | E11: ='P&L Input'!E12 -> 14354 | F11: ='P&L Input'!F12 -> 15737 | G11: ='P&L Input'!G12 -> 28173 | H11: ='Revenue Buildup'!H11 -> 33488.816 | I11: ='Revenue Buildup'!I11 -> 37704.016 | J11: ='Revenue Buildup'!J11 -> 42059.198 | K11: ='Revenue Buildup'!K11 -> 46482.213 | L11: ='Revenue Buildup'!L11 -> 50890.149 | M11: ='Revenue Buildup'!M11 -> 55191.54 | N11: ='Revenue Buildup'!N11 -> 59289.291 | O11: ='Revenue Buildup'!O11 -> 63084.215 | ... Q11: ='Revenue Buildup'!Q11 -> 69382.456
B13: ='P&L Input'!B14 -> Total Income | C13: =SUM(C10:C11) -> 1170812 | D13: =SUM(D10:D11) -> 1400814 | E13: =SUM(E10:E11) -> 1514178 | F13: =SUM(F10:F11) -> 1745589 | G13: =SUM(G10:G11) -> 2137901 | H13: =SUM(H10:H11) -> 2541290.4 | I13: =SUM(I10:I11) -> 2861159.8 | J13: =SUM(J10:J11) -> 3191651.6 | ... Q13: =SUM(Q10:Q11) -> 5265070.2
B15: ='P&L Input'!B16 -> Expenses
B16: ='P&L Input'!B17 -> Network operating expenses | C16: ='P&L Input'!C17 -> 250205 | D16: ='P&L Input'!D17 -> 285433 | E16: ='P&L Input'!E17 -> 300188 | F16: ='P&L Input'!F17 -> 335043 | G16: ='P&L Input'!G17 -> 397500 | H16: ='Cost Builup'!H13 -> 504996.47 | I16: ='Cost Builup'!I13 -> 568559.82 | J16: ='Cost Builup'!J13 -> 634234.02 | K16: ='Cost Builup'!K13 -> 700931.12 | L16: ='Cost Builup'!L13 -> 767400.83 | M16: ='Cost Builup'!M13 -> 832263.9 | N16: ='Cost Builup'!N13 -> 894056.17 | O16: ='Cost Builup'!O13 -> 951281.93 | ... Q16: ='Cost Builup'!Q13 -> 1046256.6
B17: ='P&L Input'!B18 -> Access charges | C17: ='P&L Input'!C18 -> 67611 | D17: ='P&L Input'!D18 -> 76207 | E17: ='P&L Input'!E18 -> 75185 | F17: ='P&L Input'!F18 -> 71713 | G17: ='P&L Input'!G18 -> 55416 | H17: ='Cost Builup'!H16 -> 116292.6 | I17: ='Cost Builup'!I16 -> 130930.22 | J17: ='Cost Builup'!J16 -> 146053.94 | K17: ='Cost Builup'!K16 -> 161413.21 | L17: ='Cost Builup'!L16 -> 176720.13 | M17: ='Cost Builup'!M16 -> 191657.05 | N17: ='Cost Builup'!N16 -> 205886.82 | O17: ='Cost Builup'!O16 -> 219065 | ... Q17: ='Cost Builup'!Q16 -> 240936.15
B18: ='P&L Input'!B19 -> License fee / Spectrum charges | C18: ='P&L Input'!C19 -> 110636 | D18: ='P&L Input'!D19 -> 117517 | E18: ='P&L Input'!E19 -> 120358 | F18: ='P&L Input'!F19 -> 138290 | G18: ='P&L Input'!G19 -> 153729 | H18: ='Cost Builup'!H19 -> 207879.3 | I18: ='Cost Builup'!I19 -> 234044.84 | J18: ='Cost Builup'!J19 -> 261079.3 | K18: ='Cost Builup'!K19 -> 288534.83 | L18: ='Cost Builup'!L19 -> 315896.76 | M18: ='Cost Builup'!M19 -> 342597.32 | N18: ='Cost Builup'!N19 -> 368033.81 | O18: ='Cost Builup'!O19 -> 391590.51 | ... Q18: ='Cost Builup'!Q19 -> 430686.37
B19: ='P&L Input'!B20 -> Employee benefits expense | C19: ='P&L Input'!C20 -> 44333 | D19: ='P&L Input'!D20 -> 48308 | E19: ='P&L Input'!E20 -> 53231 | F19: ='P&L Input'!F20 -> 63089 | G19: ='P&L Input'!G20 -> 75813 | H19: ='Cost Builup'!H22 -> 91033.726 | I19: ='Cost Builup'!I22 -> 102492.04 | J19: ='Cost Builup'!J22 -> 114330.87 | K19: ='Cost Builup'!K22 -> 126354.09 | L19: ='Cost Builup'!L22 -> 138336.33 | M19: ='Cost Builup'!M22 -> 150028.94 | N19: ='Cost Builup'!N22 -> 161167.99 | O19: ='Cost Builup'!O22 -> 171483.85 | ... Q19: ='Cost Builup'!Q22 -> 188604.56
B20: ='P&L Input'!B21 -> Sales and marketing expenses | C20: ='P&L Input'!C21 -> 53035 | D20: ='P&L Input'!D21 -> 72454 | E20: ='P&L Input'!E21 -> 107882 | F20: ='P&L Input'!F21 -> 114601 | G20: ='P&L Input'!G21 -> 131073 | H20: ='Cost Builup'!H25 -> 150052.66 | I20: ='Cost Builup'!I25 -> 168939.62 | J20: ='Cost Builup'!J25 -> 188453.8 | K20: ='Cost Builup'!K25 -> 208271.91 | L20: ='Cost Builup'!L25 -> 228022.46 | M20: ='Cost Builup'!M25 -> 247295.61 | N20: ='Cost Builup'!N25 -> 265656.33 | O20: ='Cost Builup'!O25 -> 282660.16 | ... Q20: ='Cost Builup'!Q25 -> 310880.57
B21: ='P&L Input'!B22 -> Other expenses | C21: ='P&L Input'!C22 -> 64310 | D21: ='P&L Input'!D22 -> 78794 | E21: ='P&L Input'!E22 -> 60062 | F21: ='P&L Input'!F22 -> 75524 | G21: ='P&L Input'!G22 -> 99452 | H21: ='Cost Builup'!H28 -> 122300.6 | I21: ='Cost Builup'!I28 -> 137694.44 | J21: ='Cost Builup'!J28 -> 153599.49 | K21: ='Cost Builup'!K28 -> 169752.27 | L21: ='Cost Builup'!L28 -> 185849.98 | M21: ='Cost Builup'!M28 -> 201558.59 | N21: ='Cost Builup'!N28 -> 216523.51 | O21: ='Cost Builup'!O28 -> 230382.51 | ... Q21: ='Cost Builup'!Q28 -> 253383.58
B23: ='P&L Input'!B24 -> Total Expenses | C23: =SUM(C16:C21) -> 590130 | D23: =SUM(D16:D21) -> 678713 | E23: =SUM(E16:E21) -> 716906 | F23: =SUM(F16:F21) -> 798260 | G23: =SUM(G16:G21) -> 912983 | H23: =SUM(H16:H21) -> 1192555.4 | I23: =SUM(I16:I21) -> 1342661 | J23: =SUM(J16:J21) -> 1497751.4 | ... Q23: =SUM(Q16:Q21) -> 2470747.8
B25: ='P&L Input'!B26 -> EBITDA | C25: =C13-C23 -> 580682 | D25: =D13-D23 -> 722101 | E25: =E13-E23 -> 797272 | F25: =F13-F23 -> 947329 | G25: =G13-G23 -> 1224918 | H25: =H13-H23 -> 1348735 | I25: =I13-I23 -> 1518498.8 | J25: =J13-J23 -> 1693900.2 | ... Q25: =Q13-Q23 -> 2794322.3
B27: ='P&L Input'!B28 -> Depreciation & Amortisation | C27: ='P&L Input'!C28 -> 330907 | D27: ='P&L Input'!D28 -> 364318 | E27: ='P&L Input'!E28 -> 395376 | F27: ='P&L Input'!F28 -> 455703 | G27: ='P&L Input'!G28 -> 527108 | H27: =FAS!H168 -> 537650.16 | I27: =FAS!I168 -> 548403.16 | J27: =FAS!J168 -> 559371.23 | K27: =FAS!K168 -> 570558.65 | L27: =FAS!L168 -> 581969.82 | M27: =FAS!M168 -> 593609.22 | N27: =FAS!N168 -> 605481.4 | O27: =FAS!O168 -> 617591.03 | ... Q27: =FAS!Q168 -> 642541.71
B29: ='P&L Input'!B30 -> EBIT | C29: =C25-C27 -> 249775 | D29: =D25-D27 -> 357783 | E29: =E25-E27 -> 401896 | F29: =F25-F27 -> 491626 | G29: =G25-G27 -> 697810 | H29: =H25-H27 -> 811084.84 | I29: =I25-I27 -> 970095.62 | J29: =J25-J27 -> 1134529 | ... Q29: =Q25-Q27 -> 2151780.6
B31: ='P&L Input'!B32 -> Finance Costs | C31: ='P&L Input'!C32 -> 166162 | D31: ='P&L Input'!D32 -> 192999 | E31: ='P&L Input'!E32 -> 226477 | F31: ='P&L Input'!F32 -> 217539 | G31: ='P&L Input'!G32 -> 215553 | H31: ='Cost Builup'!H31 -> 332763.81 | I31: ='Cost Builup'!I31 -> 374648.42 | J31: ='Cost Builup'!J31 -> 417923.97 | K31: ='Cost Builup'!K31 -> 461873.55 | L31: ='Cost Builup'!L31 -> 505673.29 | M31: ='Cost Builup'!M31 -> 548414.34 | N31: ='Cost Builup'!N31 -> 589131.92 | O31: ='Cost Builup'!O31 -> 626840.42 | ... Q31: ='Cost Builup'!Q31 -> 689423.31
B32: ='P&L Input'!B33 -> Share of Profit/(Loss) of Associates | C32: ='P&L Input'!C33 -> -24232 | D32: ='P&L Input'!D33 -> -7521 | E32: ='P&L Input'!E33 -> -27094 | F32: ='P&L Input'!F33 -> -37030 | G32: ='P&L Input'!G33 -> -3645 | H32: ='Revenue Buildup'!H17 -> -33803.03 | I32: ='Revenue Buildup'!I17 -> -38057.78 | J32: ='Revenue Buildup'!J17 -> -42453.824 | K32: ='Revenue Buildup'!K17 -> -46918.339 | L32: ='Revenue Buildup'!L17 -> -51367.633 | M32: ='Revenue Buildup'!M17 -> -55709.382 | N32: ='Revenue Buildup'!N17 -> -59845.582 | O32: ='Revenue Buildup'!O17 -> -63676.112 | ... Q32: ='Revenue Buildup'!Q17 -> -70033.447
B34: ='P&L Input'!B35 -> Profit before exceptional items | C34: =C29-C31-C32 -> 107845 | D34: =D29-D31-D32 -> 172305 | E34: =E29-E31-E32 -> 202513 | F34: =F29-F31-F32 -> 311117 | G34: =G29-G31-G32 -> 485902 | H34: =H29-H31-H32 -> 512124.06 | I34: =I29-I31-I32 -> 633504.98 | J34: =J29-J31-J32 -> 759058.83 | ... Q34: =Q29-Q31-Q32 -> 1532390.8
B36: ='P&L Input'!B37 -> Exceptional items | C36: ='P&L Input'!C37 -> -16986 | D36: ='P&L Input'!D37 -> 6698 | E36: ='P&L Input'!E37 -> 75723 | F36: ='P&L Input'!F37 -> -72868 | G36: ='P&L Input'!G37 -> 34175 | H36: ='Revenue Buildup'!H20 -> 7424.1759 | I36: ='Revenue Buildup'!I20 -> 18260.408 | J36: ='Revenue Buildup'!J20 -> 21411.363 | K36: ='Revenue Buildup'!K20 -> -6752.1412 | L36: ='Revenue Buildup'!L20 -> 23234.969 | M36: ='Revenue Buildup'!M20 -> 16848.714 | N36: ='Revenue Buildup'!N20 -> 19090.813 | O36: ='Revenue Buildup'!O20 -> 18264.853 | ... Q36: ='Revenue Buildup'!Q20 -> 22465.982
B38: ='P&L Input'!B39 -> Profit before Tax | C38: =C34-C36 -> 124831 | D38: =D34-D36 -> 165607 | E38: =E34-E36 -> 126790 | F38: =F34-F36 -> 383985 | G38: =G34-G36 -> 451727 | H38: =H34-H36 -> 504699.89 | I38: =I34-I36 -> 615244.57 | J38: =J34-J36 -> 737647.47 | ... Q38: =Q34-Q36 -> 1509924.8
B40: ='P&L Input'!B41 -> Taxes | C40: ='P&L Input'!C41 -> 41779 | D40: ='P&L Input'!D41 -> 42733 | E40: ='P&L Input'!E41 -> 41210 | F40: ='P&L Input'!F41 -> 9172 | G40: ='P&L Input'!G41 -> 113499 | H40: =H38*'Cost Builup'!H34 -> 129332.24 | I40: =I38*'Cost Builup'!I34 -> 157659.95 | J40: =J38*'Cost Builup'!J34 -> 192714.63 | K40: =K38*'Cost Builup'!K34 -> 233372.39 | L40: =L38*'Cost Builup'!L34 -> 263606.27 | M40: =M38*'Cost Builup'!M34 -> 298108.38 | N40: =N38*'Cost Builup'!N34 -> 334721.37 | O40: =O38*'Cost Builup'!O34 -> 363929.06 | ... Q40: =Q38*'Cost Builup'!Q34 -> 417125.39
B42: ='P&L Input'!B43 -> Net Profit | C42: =C38-C40 -> 83052 | D42: =D38-D40 -> 122874 | E42: =E38-E40 -> 85580 | F42: =F38-F40 -> 374813 | G42: =G38-G40 -> 338228 | H42: =H38-H40 -> 375367.65 | I42: =I38-I40 -> 457584.62 | J42: =J38-J40 -> 544932.84 | ... Q42: =Q38-Q40 -> 1092799.4
B45: Basic EPS | C45: =(C42*1000)/5549342 -> 14.966099 | D45: =(D42*1000)/5549342 -> 22.142085 | E45: =(E42*1000)/5549342 -> 15.421648 | F45: =(F42*1000)/5549342 -> 67.541882 | G45: =(G42*1000)/5549342 -> 60.949208 | H45: =(H42*1000)/5549342 -> 67.64183 | I45: =(I42*1000)/5549342 -> 82.457455 | J45: =(J42*1000)/5549342 -> 98.197739 | ... Q45: =(Q42*1000)/5549342 -> 196.92414
B47: Total Dividend Payout | C47: 51736 | D47: 58756 | E47: 79863 | F47: 70963 | G47: 70963 | H47: =G47*(1+H48) -> 85851.618 | I47: =H47*(1+I48) -> 103863.99 | J47: =I47*(1+J48) -> 125655.5 | K47: =J47*(1+K48) -> 152019.06 | L47: =K47*(1+L48) -> 183913.9 | M47: =L47*(1+M48) -> 222500.54 | N47: =M47*(1+N48) -> 269182.97 | O47: =N47*(1+O48) -> 325659.75 | ... Q47: =P47*(1+Q48) -> 476647.28
B48: (as % on Net Profit) | C48: =C47/C42 -> 0.62293503 | D48: =D47/D42 -> 0.4781809 | E48: =E47/E42 -> 0.93319701 | F48: =F47/F42 -> 0.18932908 | G48: =G47/G42 -> 0.20980818 | H48: =G48 -> 0.20980818 | I48: =H48 -> 0.20980818 | J48: =I48 -> 0.20980818 | K48: =J48 -> 0.20980818 | L48: =K48 -> 0.20980818 | M48: =L48 -> 0.20980818 | N48: =M48 -> 0.20980818 | O48: =N48 -> 0.20980818 | ... Q48: =P48 -> 0.20980818

Sheet Balance Sheet
A1: Bharti Airtel Ltd
Q6: (INR in millions)
B7: Income Statement
B8: Particulars | C8: =FAS!C7 -> 2022 | D8: =FAS!D7 -> 2023 | E8: =FAS!E7 -> 2024 | F8: =FAS!F7 -> 2025 | G8: =FAS!G7 -> 2026 | H8: =FAS!H7 -> 2027 | I8: =FAS!I7 -> 2028 | J8: =FAS!J7 -> 2029 | ... Q8: =FAS!Q7 -> 2036
C9: Audited | D9: Audited | E9: Audited | F9: Audited | G9: Audited | H9: Estimated | I9: Projected | J9: Projected | K9: Projected | L9: Projected | M9: Projected | N9: Projected | O9: Projected | P9: Projected | Q9: Projected
B10: ='BS Input'!B8 -> ASSETS
B11: ='BS Input'!B9 -> Non-current assets
B12: ='BS Input'!B10 -> Property, Plant & Equipment | C12: ='BS Input'!C10 -> 905725 | D12: ='BS Input'!D10 -> 952241 | E12: ='BS Input'!E10 -> 1066121 | F12: ='BS Input'!F10 -> 1432724 | G12: ='BS Input'!G10 -> 1570659 | H12: =FAS!H140 -> 2083882.2 | I12: =FAS!I140 -> 2597105.4 | J12: =FAS!J140 -> 3110328.6 | K12: =FAS!K140 -> 3828841.1 | L12: =FAS!L140 -> 4547353.6 | M12: =FAS!M140 -> 5265866 | N12: =FAS!N140 -> 6271783.5 | O12: =FAS!O140 -> 7277701 | ... Q12: =FAS!Q140 -> 9691902.9
B13: ='BS Input'!B11 -> Capital Work-in-Progress | C13: ='BS Input'!C11 -> 42386 | D13: ='BS Input'!D11 -> 110293 | E13: ='BS Input'!E11 -> 89077 | F13: ='BS Input'!F11 -> 105962 | G13: ='BS Input'!G11 -> 126131 | H13: =FAS!H173 -> 147067.25 | I13: =FAS!I173 -> 168003.5 | J13: =FAS!J173 -> 188939.75 | K13: =FAS!K173 -> 209876 | L13: =FAS!L173 -> 230812.25 | M13: =FAS!M173 -> 251748.5 | N13: =FAS!N173 -> 272684.75 | O13: =FAS!O173 -> 293621 | ... Q13: =FAS!Q173 -> 335493.5
B14: ='BS Input'!B12 -> Right-of-use Assets | C14: ='BS Input'!C12 -> 322286 | D14: ='BS Input'!D12 -> 546466 | E14: ='BS Input'!E12 -> 559367 | F14: ='BS Input'!F12 -> 602415 | G14: ='BS Input'!G12 -> 673244 | H14: =FAS!H149 -> 673244 | I14: =FAS!I149 -> 673244 | J14: =FAS!J149 -> 673244 | K14: =FAS!K149 -> 673244 | L14: =FAS!L149 -> 673244 | M14: =FAS!M149 -> 673244 | N14: =FAS!N149 -> 673244 | O14: =FAS!O149 -> 673244 | ... Q14: =FAS!Q149 -> 673244
B15: ='BS Input'!B13 -> Goodwill | C15: ='BS Input'!C13 -> 338313 | D15: ='BS Input'!D13 -> 337741 | E15: ='BS Input'!E13 -> 265017 | F15: ='BS Input'!F13 -> 516974 | G15: ='BS Input'!G13 -> 566859 | H15: =G15 -> 566859 | I15: =H15 -> 566859 | J15: =I15 -> 566859 | K15: =J15 -> 566859 | L15: =K15 -> 566859 | M15: =L15 -> 566859 | N15: =M15 -> 566859 | O15: =N15 -> 566859 | ... Q15: =P15 -> 566859
B16: ='BS Input'!B14 -> Other Intangible Assets | C16: ='BS Input'!C14 -> 874509 | D16: ='BS Input'!D14 -> 937490 | E16: ='BS Input'!E14 -> 1142526 | F16: ='BS Input'!F14 -> 1332569 | G16: ='BS Input'!G14 -> 1252604 | H16: =FAS!H157 -> 1252604 | I16: =FAS!I157 -> 1252604 | J16: =FAS!J157 -> 1252604 | K16: =FAS!K157 -> 1252604 | L16: =FAS!L157 -> 1252604 | M16: =FAS!M157 -> 1252604 | N16: =FAS!N157 -> 1252604 | O16: =FAS!O157 -> 1252604 | ... Q16: =FAS!Q157 -> 1252604
B17: ='BS Input'!B15 -> Intangible Assets Under Development | C17: ='BS Input'!C15 -> 17161 | D17: ='BS Input'!D15 -> 383961 | E17: ='BS Input'!E15 -> 79964 | F17: ='BS Input'!F15 -> 4027 | G17: ='BS Input'!G15 -> 3250 | H17: =FAS!H165 -> 3250 | I17: =FAS!I165 -> 3250 | J17: =FAS!J165 -> 3250 | K17: =FAS!K165 -> 3250 | L17: =FAS!L165 -> 3250 | M17: =FAS!M165 -> 3250 | N17: =FAS!N165 -> 3250 | O17: =FAS!O165 -> 3250 | ... Q17: =FAS!Q165 -> 3250
B18: ='BS Input'!B16 -> Investment in Joint Ventures & Associates | C18: ='BS Input'!C16 -> 284268 | D18: ='BS Input'!D16 -> 281838 | E18: ='BS Input'!E16 -> 312404 | F18: ='BS Input'!F16 -> 36416 | G18: ='BS Input'!G16 -> 40622 | H18: ='BS items'!I13 -> 353269.21 | I18: ='BS items'!J13 -> 397734.81 | J18: ='BS items'!K13 -> 443677.06 | K18: ='BS items'!L13 -> 490334.88 | L18: ='BS items'!M13 -> 536833.62 | M18: ='BS items'!N13 -> 582208.44 | N18: ='BS items'!O13 -> 625435.1 | O18: ='BS items'!P13 -> 665467.26 | ... Q18: ='BS items'!R13 -> 731906.59
B19: ='BS Input'!B17 -> Financial Assets
B20: ='BS Input'!B18 -> Investments | C20: ='BS Input'!C18 -> 609 | D20: ='BS Input'!D18 -> 656 | E20: ='BS Input'!E18 -> 924 | F20: ='BS Input'!F18 -> 5435 | G20: ='BS Input'!G18 -> 11385 | H20: ='BS items'!I15 -> 5157.9948 | I20: ='BS items'!J15 -> 5807.2259 | J20: ='BS items'!K15 -> 6478.0171 | K20: ='BS items'!L15 -> 7159.2562 | L20: ='BS items'!M15 -> 7838.1727 | M20: ='BS items'!N15 -> 8500.679 | N20: ='BS items'!O15 -> 9131.8205 | O20: ='BS items'!P15 -> 9716.32 | ... Q20: ='BS items'!R15 -> 10686.384
B21: ='BS Input'!B19 -> Derivative instruments | C21: ='BS Input'!C19 -> 218 | D21: ='BS Input'!D19 -> 854 | E21: ='BS Input'!E19 -> 65 | F21: ='BS Input'!F19 -> - | G21: ='BS Input'!G19 -> - | H21: =G21 -> - | I21: =H21 -> - | J21: =I21 -> - | K21: =J21 -> - | L21: =K21 -> - | M21: =L21 -> - | N21: =M21 -> - | O21: =N21 -> - | ... Q21: =P21 -> -
B22: ='BS Input'!B20 -> Trade Receivables | C22: ='BS Input'!C20 -> 0 | D22: ='BS Input'!D20 -> 0 | E22: ='BS Input'!E20 -> 1805 | F22: ='BS Input'!F20 -> 2131 | G22: ='BS Input'!G20 -> 2544 | H22: =G22 -> 2544 | I22: =H22 -> 2544 | J22: =I22 -> 2544 | K22: =J22 -> 2544 | L22: =K22 -> 2544 | M22: =L22 -> 2544 | N22: =M22 -> 2544 | O22: =N22 -> 2544 | ... Q22: =P22 -> 2544
B23: ='BS Input'!B21 -> Loans | C23: ='BS Input'!C21 -> – | D23: ='BS Input'!D21 -> – | E23: ='BS Input'!E21 -> - | F23: ='BS Input'!F21 -> 865 | G23: ='BS Input'!G21 -> – | H23: =G23 -> – | I23: =H23 -> – | J23: =I23 -> – | K23: =J23 -> – | L23: =K23 -> – | M23: =L23 -> – | N23: =M23 -> – | O23: =N23 -> – | ... Q23: =P23 -> –
B24: ='BS Input'!B22 -> Other Financial Assets | C24: ='BS Input'!C22 -> 22515 | D24: ='BS Input'!D22 -> 25963 | E24: ='BS Input'!E22 -> 26557 | F24: ='BS Input'!F22 -> 37471 | G24: ='BS Input'!G22 -> 35700 | H24: ='BS items'!I17 -> 47912.03 | I24: ='BS items'!J17 -> 53942.664 | J24: ='BS items'!K17 -> 60173.568 | K24: ='BS items'!L17 -> 66501.52 | L24: ='BS items'!M17 -> 72807.899 | M24: ='BS items'!N17 -> 78961.845 | N24: ='BS items'!O17 -> 84824.447 | O24: ='BS items'!P17 -> 90253.797 | ... Q24: ='BS items'!R17 -> 99264.612
B25: ='BS Input'!B23 -> Income Tax Assets (Net) | C25: ='BS Input'!C23 -> 17479 | D25: ='BS Input'!D23 -> 20399 | E25: ='BS Input'!E23 -> 14135 | F25: ='BS Input'!F23 -> 24978 | G25: ='BS Input'!G23 -> 20181 | H25: ='BS items'!I19 -> 32064.567 | I25: ='BS items'!J19 -> 36100.498 | J25: ='BS items'!K19 -> 40270.458 | K25: ='BS items'!L19 -> 44505.366 | L25: ='BS items'!M19 -> 48725.836 | M25: ='BS items'!N19 -> 52844.293 | N25: ='BS items'!O19 -> 56767.771 | O25: ='BS items'!P19 -> 60401.299 | ... Q25: ='BS items'!R19 -> 66431.682
B26: ='BS Input'!B24 -> Deferred Tax Assets (Net) | C26: ='BS Input'!C24 -> 199250 | D26: ='BS Input'!D24 -> 189519 | E26: ='BS Input'!E24 -> 192428 | F26: ='BS Input'!F24 -> 249111 | G26: ='BS Input'!G24 -> 191413 | H26: ='BS items'!I21 -> 340634.66 | I26: ='BS items'!J21 -> 383509.97 | J26: ='BS items'!K21 -> 427809.11 | K26: ='BS items'!L21 -> 472798.22 | L26: ='BS items'!M21 -> 517633.96 | M26: ='BS items'!N21 -> 561385.97 | N26: ='BS items'!O21 -> 603066.64 | O26: ='BS items'!P21 -> 641667.06 | ... Q26: ='BS items'!R21 -> 705730.22
B27: ='BS Input'!B25 -> Other Non-current Assets | C27: ='BS Input'!C25 -> 91562 | D27: ='BS Input'!D25 -> 103898 | E27: ='BS Input'!E25 -> 112159 | F27: ='BS Input'!F25 -> 116638 | G27: ='BS Input'!G25 -> 124770 | H27: ='BS items'!I23 -> 239429.28 | I27: ='BS items'!J23 -> 269565.98 | J27: ='BS items'!K23 -> 300703.48 | K27: ='BS items'!L23 -> 332325.95 | L27: ='BS items'!M23 -> 363840.62 | M27: ='BS items'!N23 -> 394593.55 | N27: ='BS items'!O23 -> 423890.54 | O27: ='BS items'!P23 -> 451022.46 | ... Q27: ='BS items'!R23 -> 496051.92
B28: ='BS Input'!B26 -> Total Non-current Assets | C28: =SUM(C12:C27) -> 3116281 | D28: =SUM(D12:D27) -> 3891319 | E28: =SUM(E12:E27) -> 3862549 | F28: =SUM(F12:F27) -> 4467716 | G28: =SUM(G12:G27) -> 4619362 | H28: =SUM(H12:H27) -> 5747918.2 | I28: =SUM(I12:I27) -> 6410271 | J28: =SUM(J12:J27) -> 7076881 | ... Q28: =SUM(Q12:Q27) -> 14635969
B29: ='BS Input'!B27 -> Current Assets
B30: ='BS Input'!B28 -> Inventories | C30: ='BS Input'!C28 -> 3750 | D30: ='BS Input'!D28 -> 2576 | E30: ='BS Input'!E28 -> 3639 | F30: ='BS Input'!F28 -> 4517 | G30: ='BS Input'!G28 -> 6009 | H30: ='Working Capital'!H13 -> 6527.8056 | I30: ='Working Capital'!I13 -> 7349.4533 | J30: ='Working Capital'!J13 -> 8198.3868 | K30: ='Working Capital'!K13 -> 9060.5427 | L30: ='Working Capital'!L13 -> 9919.7594 | M30: ='Working Capital'!M13 -> 10758.208 | N30: ='Working Capital'!N13 -> 11556.962 | O30: ='Working Capital'!O13 -> 12296.687 | ... Q30: ='Working Capital'!Q13 -> 13524.371
B31: ='BS Input'!B29 -> Investments | C31: ='BS Input'!C29 -> 8614 | D31: ='BS Input'!D29 -> 47045 | E31: ='BS Input'!E29 -> 2695 | F31: ='BS Input'!F29 -> 16532 | G31: ='BS Input'!G29 -> 137006 | H31: ='BS items'!I26 -> 8936.0731 | I31: ='BS items'!J26 -> 10060.847 | J31: ='BS items'!K26 -> 11222.973 | K31: ='BS items'!L26 -> 12403.199 | L31: ='BS items'!M26 -> 13579.402 | M31: ='BS items'!N26 -> 14727.174 | N31: ='BS items'!O26 -> 15820.608 | O31: ='BS items'!P26 -> 16833.236 | ... Q31: ='BS items'!R26 -> 18513.843
B32: ='BS Input'!B30 -> Derivative Instruments | C32: ='BS Input'!C30 -> 561 | D32: ='BS Input'!D30 -> 1283 | E32: ='BS Input'!E30 -> 1168 | F32: ='BS Input'!F30 -> 813 | G32: ='BS Input'!G30 -> 5040 | H32: =G32 -> 5040 | I32: =H32 -> 5040 | J32: =I32 -> 5040 | K32: =J32 -> 5040 | L32: =K32 -> 5040 | M32: =L32 -> 5040 | N32: =M32 -> 5040 | O32: =N32 -> 5040 | ... Q32: =P32 -> 5040
B33: ='BS Input'!B31 -> Trade Receivables | C33: ='BS Input'!C31 -> 40562 | D33: ='BS Input'!D31 -> 39815 | E33: ='BS Input'!E31 -> 47277 | F33: ='BS Input'!F31 -> 74557 | G33: ='BS Input'!G31 -> 79776 | H33: ='Working Capital'!H11 -> 88597.888 | I33: ='Working Capital'!I11 -> 99749.606 | J33: ='Working Capital'!J11 -> 111271.66 | K33: ='Working Capital'!K11 -> 122973.17 | L33: ='Working Capital'!L11 -> 134634.79 | M33: ='Working Capital'!M11 -> 146014.53 | N33: ='Working Capital'!N11 -> 156855.53 | O33: ='Working Capital'!O11 -> 166895.37 | ... Q33: ='Working Capital'!Q11 -> 183557.97
B34: ='BS Input'!B32 -> Cash & Cash Equivalents | C34: ='BS Input'!C32 -> 60959 | D34: ='BS Input'!D32 -> 71794 | E34: ='BS Input'!E32 -> 69155 | F34: ='BS Input'!F32 -> 61056 | G34: ='BS Input'!G32 -> 137222 | H34: ='Cash Flows'!H80 -> 204488.1 | I34: ='Cash Flows'!I80 -> 363384.45 | J34: ='Cash Flows'!J80 -> 601744.34 | K34: ='Cash Flows'!K80 -> 723167.21 | L34: ='Cash Flows'!L80 -> 884335.79 | M34: ='Cash Flows'!M80 -> 1091578.1 | N34: ='Cash Flows'!N80 -> 1025308.4 | O34: ='Cash Flows'!O80 -> 956840.06 | ... Q34: ='Cash Flows'!Q80 -> 271857.88
B35: ='BS Input'!B33 -> Other Bank Balances | C35: ='BS Input'!C33 -> 73984 | D35: ='BS Input'!D33 -> 62392 | E35: ='BS Input'!E33 -> 94244 | F35: ='BS Input'!F33 -> 106143 | G35: ='BS Input'!G33 -> 166546 | H35: =G35 -> 166546 | I35: =H35 -> 166546 | J35: =I35 -> 166546 | K35: =J35 -> 166546 | L35: =K35 -> 166546 | M35: =L35 -> 166546 | N35: =M35 -> 166546 | O35: =N35 -> 166546 | ... Q35: =P35 -> 166546
B36: ='BS Input'!B34 -> Other Financial Assets | C36: ='BS Input'!C34 -> 214697 | D36: ='BS Input'!D34 -> 220865 | E36: ='BS Input'!E34 -> 249544 | F36: ='BS Input'!F34 -> 267662 | G36: ='BS Input'!G34 -> 244264 | H36: ='BS items'!I28 -> 396359.28 | I36: ='BS items'!J28 -> 446248.59 | J36: ='BS items'!K28 -> 497794.65 | K36: ='BS items'!L28 -> 550143.56 | L36: ='BS items'!M28 -> 602314 | M36: ='BS items'!N28 -> 653223.43 | N36: ='BS items'!O28 -> 701722.66 | O36: ='BS items'!P28 -> 746637.75 | ... Q36: ='BS items'!R28 -> 821181.03
B37: ='BS Input'!B35 -> Other Current Assets | C37: ='BS Input'!C35 -> 117152 | D37: ='BS Input'!D35 -> 129243 | E37: ='BS Input'!E35 -> 115039 | F37: ='BS Input'!F35 -> 144608 | G37: ='BS Input'!G35 -> 125718 | H37: ='BS items'!I30 -> 210057.95 | I37: ='BS items'!J30 -> 236497.71 | J37: ='BS items'!K30 -> 263815.5 | K37: ='BS items'!L30 -> 291558.77 | L37: ='BS items'!M30 -> 319207.47 | M37: ='BS items'!N30 -> 346187.86 | N37: ='BS items'!O30 -> 371890.92 | O37: ='BS items'!P30 -> 395694.51 | ... Q37: ='BS items'!R30 -> 435200.1
B38: ='BS Input'!B36 -> Assets Held for Sale | C38: ='BS Input'!C36 -> – | D38: ='BS Input'!D36 -> – | E38: ='BS Input'!E36 -> – | F38: ='BS Input'!F36 -> – | G38: ='BS Input'!G36 -> 573 | H38: - | I38: - | J38: - | K38: - | L38: - | M38: - | N38: - | O38: - | P38: - | Q38: -
B39: ='BS Input'!B37 -> Total Current Assets | C39: =SUM(C30:C38) -> 520279 | D39: =SUM(D30:D38) -> 575013 | E39: =SUM(E30:E38) -> 582761 | F39: =SUM(F30:F38) -> 675888 | G39: =SUM(G30:G38) -> 902154 | H39: =SUM(H30:H38) -> 1086553.1 | I39: =SUM(I30:I38) -> 1334876.7 | J39: =SUM(J30:J38) -> 1665633.5 | ... Q39: =SUM(Q30:Q38) -> 1915421.2
B40: ='BS Input'!B38 -> TOTAL ASSETS | C40: =SUM(C28,C39) -> 3636560 | D40: =SUM(D28,D39) -> 4466332 | E40: =SUM(E28,E39) -> 4445310 | F40: =SUM(F28,F39) -> 5143604 | G40: =SUM(G28,G39) -> 5521516 | H40: =SUM(H28,H39) -> 6834471.3 | I40: =SUM(I28,I39) -> 7745147.7 | J40: =SUM(J28,J39) -> 8742514.6 | ... Q40: =SUM(Q28,Q39) -> 16551390
B42: ='BS Input'!B40 -> EQUITY & LIABILITIES
B43: ='BS Input'!B41 -> Share Capital | C43: ='BS Input'!C41 -> 27950 | D43: ='BS Input'!D41 -> 28366 | E43: ='BS Input'!E41 -> 28766 | F43: ='BS Input'!F41 -> 29001 | G43: ='BS Input'!G41 -> 30468 | H43: =G43 -> 30468 | I43: =H43 -> 30468 | J43: =I43 -> 30468 | K43: =J43 -> 30468 | L43: =K43 -> 30468 | M43: =L43 -> 30468 | N43: =M43 -> 30468 | O43: =N43 -> 30468 | ... Q43: =P43 -> 30468
B44: ='BS Input'!B42 -> Other Equity | C44: ='BS Input'!C42 -> 637593 | D44: ='BS Input'!D42 -> 747263 | E44: ='BS Input'!E42 -> 791422 | F44: ='BS Input'!F42 -> 1107718 | G44: ='BS Input'!G42 -> 1460098 | H44: =G44+'Income Statement'!H42-'Income Statement'!H47 -> 1749614 | I44: =H44+'Income Statement'!I42-'Income Statement'!I47 -> 2103334.7 | J44: =I44+'Income Statement'!J42-'Income Statement'!J47 -> 2522612 | K44: =J44+'Income Statement'!K42-'Income Statement'!K47 -> 3030492.4 | L44: =K44+'Income Statement'!L42-'Income Statement'!L47 -> 3573021.4 | M44: =L44+'Income Statement'!M42-'Income Statement'!M47 -> 4172044.2 | N44: =M44+'Income Statement'!N42-'Income Statement'!N47 -> 4802109.6 | O44: =N44+'Income Statement'!O42-'Income Statement'!O47 -> 5454166.4 | ... Q44: =P44+'Income Statement'!Q42-'Income Statement'!Q47 -> 6716821.1
B45: ='BS Input'!B43 -> Equity attributable to Owners | C45: =SUM(C43:C44) -> 665543 | D45: =SUM(D43:D44) -> 775629 | E45: =SUM(E43:E44) -> 820188 | F45: =SUM(F43:F44) -> 1136719 | G45: =SUM(G43:G44) -> 1490566 | H45: =SUM(H43:H44) -> 1780082 | I45: =SUM(I43:I44) -> 2133802.7 | J45: =SUM(J43:J44) -> 2553080 | ... Q45: =SUM(Q43:Q44) -> 6747289.1
B46: ='BS Input'!B44 -> Non-controlling Interests | C46: ='BS Input'!C44 -> 253807 | D46: ='BS Input'!D44 -> 288814 | E46: ='BS Input'!E44 -> 235451 | F46: ='BS Input'!F44 -> 397958 | G46: ='BS Input'!G44 -> 469068 | H46: =G46 -> 469068 | I46: =H46 -> 469068 | J46: =I46 -> 469068 | K46: =J46 -> 469068 | L46: =K46 -> 469068 | M46: =L46 -> 469068 | N46: =M46 -> 469068 | O46: =N46 -> 469068 | ... Q46: =P46 -> 469068
B47: ='BS Input'!B45 -> Total Equity | C47: =SUM(C45:C46) -> 919350 | D47: =SUM(D45:D46) -> 1064443 | E47: =SUM(E45:E46) -> 1055639 | F47: =SUM(F45:F46) -> 1534677 | G47: =SUM(G45:G46) -> 1959634 | H47: =SUM(H45:H46) -> 2249150 | I47: =SUM(I45:I46) -> 2602870.7 | J47: =SUM(J45:J46) -> 3022148 | ... Q47: =SUM(Q45:Q46) -> 7216357.1
B48: ='BS Input'!B46 -> Non-current liabilities
B49: ='BS Input'!B47 -> Financial liabilities
B50: ='BS Input'!B48 -> • Borrowings | C50: ='BS Input'!C48 -> 1135350 | D50: ='BS Input'!D48 -> 1515686 | E50: ='BS Input'!E48 -> 1309626 | F50: ='BS Input'!F48 -> 1048638 | G50: ='BS Input'!G48 -> 1000849 | H50: ='BS items'!I36 -> 1205581 | I50: ='BS items'!J36 -> 1357326.1 | J50: ='BS items'!K36 -> 1514110.5 | K50: ='BS items'!L36 -> 1673336.9 | L50: ='BS items'!M36 -> 1832020.4 | M50: ='BS items'!N36 -> 1986868.4 | N50: ='BS items'!O36 -> 2134385.4 | O50: ='BS items'!P36 -> 2271000.8 | ... Q50: ='BS items'!R36 -> 2497734.4
B51: ='BS Input'!B49 -> • Lease liabilities | C51: ='BS Input'!C49 -> 290562 | D51: ='BS Input'!D49 -> 508295 | E51: ='BS Input'!E49 -> 539271 | F51: ='BS Input'!F49 -> 556701 | G51: ='BS Input'!G49 -> 644996 | H51: ='BS items'!I38 -> 814081.69 | I51: ='BS items'!J38 -> 916549.25 | J51: ='BS items'!K38 -> 1022419.6 | K51: ='BS items'!L38 -> 1129939 | L51: ='BS items'!M38 -> 1237091.8 | M51: ='BS items'!N38 -> 1341654.5 | N51: ='BS items'!O38 -> 1441267 | O51: ='BS items'!P38 -> 1533518.1 | ... Q51: ='BS items'!R38 -> 1686622.4
B52: ='BS Input'!B50 -> • Derivative instruments | C52: ='BS Input'!C50 -> 174 | D52: ='BS Input'!D50 -> 3523 | E52: ='BS Input'!E50 -> 2890 | F52: ='BS Input'!F50 -> 0 | G52: ='BS Input'!G50 -> 0 | H52: =G52 -> 0 | I52: =H52 -> 0 | J52: =I52 -> 0 | K52: =J52 -> 0 | L52: =K52 -> 0 | M52: =L52 -> 0 | N52: =M52 -> 0 | O52: =N52 -> 0 | ... Q52: =P52 -> 0
B53: ='BS Input'!B51 -> • Other financial liabilities | C53: ='BS Input'!C51 -> 90116 | D53: ='BS Input'!D51 -> 97311 | E53: ='BS Input'!E51 -> 85036 | F53: ='BS Input'!F51 -> 38642 | G53: ='BS Input'!G51 -> 26320 | H53: ='BS items'!I40 -> 121355.72 | I53: ='BS items'!J40 -> 136630.63 | J53: ='BS items'!K40 -> 152412.8 | K53: ='BS items'!L40 -> 168440.78 | L53: ='BS items'!M40 -> 184414.12 | M53: ='BS items'!N40 -> 200001.37 | N53: ='BS items'!O40 -> 214850.67 | O53: ='BS items'!P40 -> 228602.59 | ... Q53: ='BS items'!R40 -> 251425.96
B54: ='BS Input'!B52 -> Deferred revenue | C54: ='BS Input'!C52 -> 30258 | D54: ='BS Input'!D52 -> 30901 | E54: ='BS Input'!E52 -> 34139 | F54: ='BS Input'!F52 -> 35185 | G54: ='BS Input'!G52 -> 40185 | H54: =G54 -> 40185 | I54: =H54 -> 40185 | J54: =I54 -> 40185 | K54: =J54 -> 40185 | L54: =K54 -> 40185 | M54: =L54 -> 40185 | N54: =M54 -> 40185 | O54: =N54 -> 40185 | ... Q54: =P54 -> 40185
B55: ='BS Input'!B53 -> Provisions | C55: ='BS Input'!C53 -> 4639 | D55: ='BS Input'!D53 -> 4744 | E55: ='BS Input'!E53 -> 5443 | F55: ='BS Input'!F53 -> 30396 | G55: ='BS Input'!G53 -> 35189 | H55: ='BS items'!I42 -> 16409.583 | I55: ='BS items'!J42 -> 18475.039 | J55: ='BS items'!K42 -> 20609.086 | K55: ='BS items'!L42 -> 22776.371 | L55: ='BS items'!M42 -> 24936.268 | M55: ='BS items'!N42 -> 27043.958 | N55: ='BS items'!O42 -> 29051.864 | O55: ='BS items'!P42 -> 30911.383 | ... Q55: ='BS items'!R42 -> 33997.534
B56: ='BS Input'!B54 -> Deferred tax liabilities (net) | C56: ='BS Input'!C54 -> 24488 | D56: ='BS Input'!D54 -> 20762 | E56: ='BS Input'!E54 -> 25118 | F56: ='BS Input'!F54 -> 93549 | G56: ='BS Input'!G54 -> 67789 | H56: ='BS items'!I44 -> 70592.244 | I56: ='BS items'!J44 -> 79477.612 | J56: ='BS items'!K44 -> 88658.051 | K56: ='BS items'!L44 -> 97981.479 | L56: ='BS items'!M44 -> 107273.12 | M56: ='BS items'!N44 -> 116340.17 | N56: ='BS items'!O44 -> 124977.97 | O56: ='BS items'!P44 -> 132977.42 | ... Q56: ='BS items'!R44 -> 146253.7
B57: ='BS Input'!B55 -> Other non-current liabilities | C57: ='BS Input'!C55 -> 1363 | D57: ='BS Input'!D55 -> 1029 | E57: ='BS Input'!E55 -> 1470 | F57: ='BS Input'!F55 -> 1414 | G57: ='BS Input'!G55 -> 1497 | H57: ='BS items'!I46 -> 2244.5184 | I57: ='BS items'!J46 -> 2527.0334 | J57: ='BS items'!K46 -> 2818.9304 | K57: ='BS items'!L46 -> 3115.3738 | L57: ='BS items'!M46 -> 3410.8066 | M57: ='BS items'!N46 -> 3699.0984 | N57: ='BS items'!O46 -> 3973.7416 | O57: ='BS items'!P46 -> 4228.0885 | ... Q57: ='BS items'!R46 -> 4650.2151
B58: ='BS Input'!B56 -> Total non-current liabilities | C58: =SUM(C50:C57) -> 1576950 | D58: =SUM(D50:D57) -> 2182251 | E58: =SUM(E50:E57) -> 2002993 | F58: =SUM(F50:F57) -> 1804525 | G58: =SUM(G50:G57) -> 1816825 | H58: =SUM(H50:H57) -> 2270449.7 | I58: =SUM(I50:I57) -> 2551170.7 | J58: =SUM(J50:J57) -> 2841214 | ... Q58: =SUM(Q50:Q57) -> 4660869.2
B59: ='BS Input'!B57 -> Current liabilities
B60: ='BS Input'!B58 -> Financial liabilities
B61: ='BS Input'!B59 -> • Borrowings | C61: ='BS Input'!C59 -> 193795 | D61: ='BS Input'!D59 -> 139762 | E61: ='BS Input'!E59 -> 209539 | F61: ='BS Input'!F59 -> 434485 | G61: ='BS Input'!G59 -> 215865 | H61: ='BS items'!I50 -> 386236.03 | I61: ='BS items'!J50 -> 434851.13 | J61: ='BS items'!K50 -> 485080.68 | K61: ='BS items'!L50 -> 536092.56 | L61: ='BS items'!M50 -> 586930.54 | M61: ='BS items'!N50 -> 636539.7 | N61: ='BS items'!O50 -> 683800.24 | O61: ='BS items'!P50 -> 727568.17 | ... Q61: ='BS items'!R50 -> 800207.57
B62: ='BS Input'!B60 -> • Lease liabilities | C62: ='BS Input'!C60 -> 77072 | D62: ='BS Input'!D60 -> 96460 | E62: ='BS Input'!E60 -> 97487 | F62: ='BS Input'!F60 -> 96597 | G62: ='BS Input'!G60 -> 92407 | H62: ='BS items'!I52 -> 152525.02 | I62: ='BS items'!J52 -> 171723.18 | J62: ='BS items'!K52 -> 191558.88 | K62: ='BS items'!L52 -> 211703.53 | L62: ='BS items'!M52 -> 231779.5 | M62: ='BS items'!N52 -> 251370.21 | N62: ='BS items'!O52 -> 270033.45 | O62: ='BS items'!P52 -> 287317.45 | ... Q62: ='BS items'!R52 -> 316002.83
B63: ='BS Input'!B61 -> • Derivative instruments | C63: ='BS Input'!C61 -> 995 | D63: ='BS Input'!D61 -> 1117 | E63: ='BS Input'!E61 -> 12207 | F63: ='BS Input'!F61 -> 1921 | G63: ='BS Input'!G61 -> 1918 | H63: =G63 -> 1918 | I63: =H63 -> 1918 | J63: =I63 -> 1918 | K63: =J63 -> 1918 | L63: =K63 -> 1918 | M63: =L63 -> 1918 | N63: =M63 -> 1918 | O63: =N63 -> 1918 | ... Q63: =P63 -> 1918
B64: ='BS Input'!B62 -> • Trade payables | C64: ='BS Input'!C62 -> 292741 | D64: ='BS Input'!D62 -> 328946 | E64: ='BS Input'!E62 -> 351325 | F64: ='BS Input'!F62 -> 381537 | G64: ='BS Input'!G62 -> 450152 | H64: ='Working Capital'!H15 -> 582469.31 | I64: ='Working Capital'!I15 -> 655784.07 | J64: ='Working Capital'!J15 -> 731533.53 | K64: ='Working Capital'!K15 -> 808462.8 | L64: ='Working Capital'!L15 -> 885129.81 | M64: ='Working Capital'!M15 -> 959943.69 | N64: ='Working Capital'!N15 -> 1031215.7 | O64: ='Working Capital'!O15 -> 1097220.6 | ... Q64: ='Working Capital'!Q15 -> 1206765.6
B65: ='BS Input'!B63 -> • Other financial liabilities | C65: ='BS Input'!C63 -> 194415 | D65: ='BS Input'!D63 -> 241951 | E65: ='BS Input'!E63 -> 253456 | F65: ='BS Input'!F63 -> 333024 | G65: ='BS Input'!G63 -> 408659 | H65: ='BS items'!I54 -> 455351.26 | I65: ='BS items'!J54 -> 512665.82 | J65: ='BS items'!K54 -> 571883.72 | K65: ='BS items'!L54 -> 632023.96 | L65: ='BS items'!M54 -> 691959.17 | M65: ='BS items'!N54 -> 750445.67 | N65: ='BS items'!O54 -> 806163.27 | O65: ='BS items'!P54 -> 857763.28 | ... Q65: ='BS items'!R54 -> 943401.18
B66: ='BS Input'!B64 -> Deferred revenue | C66: ='BS Input'!C64 -> 75929 | D66: ='BS Input'!D64 -> 84995 | E66: ='BS Input'!E64 -> 87262 | F66: ='BS Input'!F64 -> 97729 | G66: ='BS Input'!G64 -> 109487 | H66: =G66 -> 109487 | I66: =H66 -> 109487 | J66: =I66 -> 109487 | K66: =J66 -> 109487 | L66: =K66 -> 109487 | M66: =L66 -> 109487 | N66: =M66 -> 109487 | O66: =N66 -> 109487 | ... Q66: =P66 -> 109487
B67: ='BS Input'!B65 -> Provisions | C67: ='BS Input'!C65 -> 243449 | D67: ='BS Input'!D65 -> 257292 | E67: ='BS Input'!E65 -> 283282 | F67: ='BS Input'!F65 -> 361552 | G67: ='BS Input'!G65 -> 357828 | H67: ='BS items'!I58 -> 488582.1 | I67: ='BS items'!J58 -> 550079.39 | J67: ='BS items'!K58 -> 613618.92 | K67: ='BS items'!L58 -> 678148.1 | L67: ='BS items'!M58 -> 742457.29 | M67: ='BS items'!N58 -> 805212.06 | N67: ='BS items'!O58 -> 864995.84 | O67: ='BS items'!P58 -> 920361.54 | ... Q67: ='BS items'!R58 -> 1012249.2
B68: ='BS Input'!B66 -> Current tax liabilities (net) | C68: ='BS Input'!C66 -> 20725 | D68: ='BS Input'!D66 -> 17972 | E68: ='BS Input'!E66 -> 33031 | F68: ='BS Input'!F66 -> 20035 | G68: ='BS Input'!G66 -> 31400 | H68: ='BS items'!I60 -> 40247.525 | I68: ='BS items'!J60 -> 44200.386 | J68: ='BS items'!K60 -> 50922.453 | K68: ='BS items'!L60 -> 51996.569 | L68: ='BS items'!M60 -> 59367.545 | M68: ='BS items'!N60 -> 64795.617 | N68: ='BS items'!O60 -> 69276.709 | O68: ='BS items'!P60 -> 73662.361 | ... Q68: ='BS items'!R60 -> 80980.483
B69: ='BS Input'!B67 -> Other current liabilities | C69: ='BS Input'!C67 -> 41139 | D69: ='BS Input'!D67 -> 51143 | E69: ='BS Input'!E67 -> 59089 | F69: ='BS Input'!F67 -> 77522 | G69: ='BS Input'!G67 -> 77341 | H69: ='BS items'!I56 -> 98055.297 | I69: ='BS items'!J56 -> 110397.41 | J69: ='BS items'!K56 -> 123149.39 | K69: ='BS items'!L56 -> 136099.98 | L69: ='BS items'!M56 -> 149006.42 | M69: ='BS items'!N56 -> 161600.9 | N69: ='BS items'!O56 -> 173599.12 | O69: ='BS items'!P56 -> 184710.66 | ... Q69: ='BS items'!R56 -> 203151.92
B70: ='BS Input'!B68 -> Total current liabilities | C70: =SUM(C61:C69) -> 1140260 | D70: =SUM(D61:D69) -> 1219638 | E70: =SUM(E61:E69) -> 1386678 | F70: =SUM(F61:F69) -> 1804402 | G70: =SUM(G61:G69) -> 1745057 | H70: =SUM(H61:H69) -> 2314871.5 | I70: =SUM(I61:I69) -> 2591106.4 | J70: =SUM(J61:J69) -> 2879152.6 | ... Q70: =SUM(Q61:Q69) -> 4674163.8
B71: ='BS Input'!B69 -> Total liabilities | C71: =C58+C70 -> 2717210 | D71: =D58+D70 -> 3401889 | E71: =E58+E70 -> 3389671 | F71: =F58+F70 -> 3608927 | G71: =G58+G70 -> 3561882 | H71: =H58+H70 -> 4585321.3 | I71: =I58+I70 -> 5142277 | J71: =J58+J70 -> 5720366.6 | ... Q71: =Q58+Q70 -> 9335033
B72: ='BS Input'!B70 -> Total equity and liabilities | C72: =C71+C47 -> 3636560 | D72: =D71+D47 -> 4466332 | E72: =E71+E47 -> 4445310 | F72: =F71+F47 -> 5143604 | G72: =G71+G47 -> 5521516 | H72: =H71+H47 -> 6834471.3 | I72: =I71+I47 -> 7745147.7 | J72: =J71+J47 -> 8742514.6 | ... Q72: =Q71+Q47 -> 16551390
B74: Check | C74: =C40=C72 -> TRUE | D74: =D40=D72 -> TRUE | E74: =E40=E72 -> TRUE | F74: =F40=F72 -> TRUE | G74: =G40=G72 -> TRUE | H74: =H40=H72 -> TRUE | I74: =I40=I72 -> TRUE | J74: =J40=J72 -> TRUE | ... Q74: =Q40=Q72 -> TRUE

Sheet Cash Flows
A1: Bharti Airtel Ltd
Q6: (INR in millions)
B7: Income Statement
B8: Particulars | C8: =FAS!C7 -> 2022 | D8: =FAS!D7 -> 2023 | E8: =FAS!E7 -> 2024 | F8: =FAS!F7 -> 2025 | G8: =FAS!G7 -> 2026 | H8: =FAS!H7 -> 2027 | I8: =FAS!I7 -> 2028 | J8: =FAS!J7 -> 2029 | ... Q8: =FAS!Q7 -> 2036
C9: Audited | D9: Audited | E9: Audited | F9: Audited | G9: Audited | H9: Estimated | I9: Projected | J9: Projected | K9: Projected | L9: Projected | M9: Projected | N9: Projected | O9: Projected | P9: Projected | Q9: Projected
B10: Profit before tax | C10: 124831 | D10: 165607 | E10: 126790 | F10: 383985 | G10: 451727 | H10: ='Income Statement'!H38 -> 504699.89 | I10: ='Income Statement'!I38 -> 615244.57 | J10: ='Income Statement'!J38 -> 737647.47 | K10: ='Income Statement'!K38 -> 893271.84 | L10: ='Income Statement'!L38 -> 990049.16 | M10: ='Income Statement'!M38 -> 1119631.8 | N10: ='Income Statement'!N38 -> 1233969.7 | O10: ='Income Statement'!O38 -> 1341645.6 | ... Q10: ='Income Statement'!Q38 -> 1509924.8
B11: Adjustments for:
B12: Depreciation and amortisation expenses | C12: 330907 | D12: 364318 | E12: 395376 | F12: 455703 | G12: 527108 | H12: ='Income Statement'!H27 -> 537650.16 | I12: ='Income Statement'!I27 -> 548403.16 | J12: ='Income Statement'!J27 -> 559371.23 | K12: ='Income Statement'!K27 -> 570558.65 | L12: ='Income Statement'!L27 -> 581969.82 | M12: ='Income Statement'!M27 -> 593609.22 | N12: ='Income Statement'!N27 -> 605481.4 | O12: ='Income Statement'!O27 -> 617591.03 | ... Q12: ='Income Statement'!Q27 -> 642541.71
B13: Finance costs | C13: 165241 | D13: 188434 | E13: 219337 | F13: 216258 | G13: 214485 | H13: ='Income Statement'!H31 -> 332763.81 | I13: ='Income Statement'!I31 -> 374648.42 | J13: ='Income Statement'!J31 -> 417923.97 | K13: ='Income Statement'!K31 -> 461873.55 | L13: ='Income Statement'!L31 -> 505673.29 | M13: ='Income Statement'!M31 -> 548414.34 | N13: ='Income Statement'!N31 -> 589131.92 | O13: ='Income Statement'!O31 -> 626840.42 | ... Q13: ='Income Statement'!Q31 -> 689423.31
B14: Net gain on FVTPL instruments | C14: -1067 | D14: -2474 | E14: -2645 | F14: -2048 | G14: -3369 | H14: =G14 -> -3369 | I14: =H14 -> -3369 | J14: =I14 -> -3369 | K14: =J14 -> -3369 | L14: =K14 -> -3369 | M14: =L14 -> -3369 | N14: =M14 -> -3369 | O14: =N14 -> -3369 | ... Q14: =P14 -> -3369
B15: Dividend income | C15: - | D15: - | E15: - | F15: - | G15: -272 | H15: =G15 -> -272 | I15: =H15 -> -272 | J15: =I15 -> -272 | K15: =J15 -> -272 | L15: =K15 -> -272 | M15: =L15 -> -272 | N15: =M15 -> -272 | O15: =N15 -> -272 | ... Q15: =P15 -> -272
B16: Interest income | C16: -2206 | D16: -3080 | E16: -6493 | F16: -5306 | G16: -11158 | H16: =G16 -> -11158 | I16: =H16 -> -11158 | J16: =I16 -> -11158 | K16: =J16 -> -11158 | L16: =K16 -> -11158 | M16: =L16 -> -11158 | N16: =M16 -> -11158 | O16: =N16 -> -11158 | ... Q16: =P16 -> -11158
B17: Net (gain)/loss on derivative financial instruments | C17: 947 | D17: 3013 | E17: 6319 | F17: 420 | G17: -2017 | H17: =G17 -> -2017 | I17: =H17 -> -2017 | J17: =I17 -> -2017 | K17: =J17 -> -2017 | L17: =K17 -> -2017 | M17: =L17 -> -2017 | N17: =M17 -> -2017 | O17: =N17 -> -2017 | ... Q17: =P17 -> -2017
B18: Share of profit of associates and JVs (net) | C18: -24232 | D18: -7521 | E18: -27094 | F18: -37030 | G18: -3645 | H18: ='Income Statement'!H32 -> -33803.03 | I18: ='Income Statement'!I32 -> -38057.78 | J18: ='Income Statement'!J32 -> -42453.824 | K18: ='Income Statement'!K32 -> -46918.339 | L18: ='Income Statement'!L32 -> -51367.633 | M18: ='Income Statement'!M32 -> -55709.382 | N18: ='Income Statement'!N32 -> -59845.582 | O18: ='Income Statement'!O32 -> -63676.112 | ... Q18: ='Income Statement'!Q32 -> -70033.447
B19: Exceptional items (net) | C19: -11705 | D19: 6698 | E19: 75723 | F19: -72868 | G19: 34175 | H19: ='Income Statement'!H36 -> 7424.1759 | I19: ='Income Statement'!I36 -> 18260.408 | J19: ='Income Statement'!J36 -> 21411.363 | K19: ='Income Statement'!K36 -> -6752.1412 | L19: ='Income Statement'!L36 -> 23234.969 | M19: ='Income Statement'!M36 -> 16848.714 | N19: ='Income Statement'!N36 -> 19090.813 | O19: ='Income Statement'!O36 -> 18264.853 | ... Q19: ='Income Statement'!Q36 -> 22465.982
B20: Employee share based payment expense | C20: 776 | D20: 1115 | E20: 1194 | F20: 1669 | G20: 3157 | H20: =G20 -> 3157 | I20: =H20 -> 3157 | J20: =I20 -> 3157 | K20: =J20 -> 3157 | L20: =K20 -> 3157 | M20: =L20 -> 3157 | N20: =M20 -> 3157 | O20: =N20 -> 3157 | ... Q20: =P20 -> 3157
B21: (Profit)/Loss on sale of PP&E | C21: 74 | D21: 22 | E21: 44 | F21: -1031 | G21: -2985 | H21: =G21 -> -2985 | I21: =H21 -> -2985 | J21: =I21 -> -2985 | K21: =J21 -> -2985 | L21: =K21 -> -2985 | M21: =L21 -> -2985 | N21: =M21 -> -2985 | O21: =N21 -> -2985 | ... Q21: =P21 -> -2985
B22: Provision for doubtful debts / bad debts written off | C22: 3048 | D22: 5664 | E22: 4278 | F22: 3741 | G22: 3586 | H22: =G22 -> 3586 | I22: =H22 -> 3586 | J22: =I22 -> 3586 | K22: =J22 -> 3586 | L22: =K22 -> 3586 | M22: =L22 -> 3586 | N22: =M22 -> 3586 | O22: =N22 -> 3586 | ... Q22: =P22 -> 3586
B23: Other non-cash items | C23: -222 | D23: 485 | E23: 823 | F23: 396 | G23: 2301 | H23: =G23 -> 2301 | I23: =H23 -> 2301 | J23: =I23 -> 2301 | K23: =J23 -> 2301 | L23: =K23 -> 2301 | M23: =L23 -> 2301 | N23: =M23 -> 2301 | O23: =N23 -> 2301 | ... Q23: =P23 -> 2301
B24: Operating cash flows before changes in assets/liabilities | C24: =SUM(C10:C23) -> 586392 | D24: =SUM(D10:D23) -> 722281 | E24: =SUM(E10:E23) -> 793652 | F24: =SUM(F10:F23) -> 943889 | G24: =SUM(G10:G23) -> 1213093 | H24: =SUM(H10:H23) -> 1337978 | I24: =SUM(I10:I23) -> 1507741.8 | J24: =SUM(J10:J23) -> 1683143.2 | ... Q24: =SUM(Q10:Q23) -> 2783565.3
B25: Changes in assets and liabilities
B26: Trade receivables | C26: -7131 | D26: -5583 | E26: -14941 | F26: 29658 | G26: -5654 | H26: =-('Balance Sheet'!H33-'Balance Sheet'!G33) -> -8821.8885 | I26: =-('Balance Sheet'!I33-'Balance Sheet'!H33) -> -11151.718 | J26: =-('Balance Sheet'!J33-'Balance Sheet'!I33) -> -11522.052 | K26: =-('Balance Sheet'!K33-'Balance Sheet'!J33) -> -11701.512 | L26: =-('Balance Sheet'!L33-'Balance Sheet'!K33) -> -11661.619 | M26: =-('Balance Sheet'!M33-'Balance Sheet'!L33) -> -11379.744 | N26: =-('Balance Sheet'!N33-'Balance Sheet'!M33) -> -10840.996 | O26: =-('Balance Sheet'!O33-'Balance Sheet'!N33) -> -10039.836 | ... Q26: =-('Balance Sheet'!Q33-'Balance Sheet'!P33) -> -7681.3541
B27: Trade payables | C27: -4877 | D27: 12671 | E27: 6398 | F27: 8586 | G27: 24977 | H27: ='Balance Sheet'!H64-'Balance Sheet'!G64 -> 132317.31 | I27: ='Balance Sheet'!I64-'Balance Sheet'!H64 -> 73314.765 | J27: ='Balance Sheet'!J64-'Balance Sheet'!I64 -> 75749.457 | K27: ='Balance Sheet'!K64-'Balance Sheet'!J64 -> 76929.276 | L27: ='Balance Sheet'!L64-'Balance Sheet'!K64 -> 76667.01 | M27: ='Balance Sheet'!M64-'Balance Sheet'!L64 -> 74813.88 | N27: ='Balance Sheet'!N64-'Balance Sheet'!M64 -> 71271.987 | O27: ='Balance Sheet'!O64-'Balance Sheet'!N64 -> 66004.916 | ... Q27: ='Balance Sheet'!Q64-'Balance Sheet'!P64 -> 50499.544
B28: Inventories | C28: -1181 | D28: -1157 | E28: -771 | F28: -1416 | G28: -1982 | H28: =-('Balance Sheet'!H30-'Balance Sheet'!G30) -> -518.80561 | I28: =-('Balance Sheet'!I30-'Balance Sheet'!H30) -> -821.64765 | J28: =-('Balance Sheet'!J30-'Balance Sheet'!I30) -> -848.93354 | K28: =-('Balance Sheet'!K30-'Balance Sheet'!J30) -> -862.15592 | L28: =-('Balance Sheet'!L30-'Balance Sheet'!K30) -> -859.21667 | M28: =-('Balance Sheet'!M30-'Balance Sheet'!L30) -> -838.44841 | N28: =-('Balance Sheet'!N30-'Balance Sheet'!M30) -> -798.75398 | O28: =-('Balance Sheet'!O30-'Balance Sheet'!N30) -> -739.72526 | ... Q28: =-('Balance Sheet'!Q30-'Balance Sheet'!P30) -> -565.95465
B29: Provisions | C29: 2736 | D29: 6494 | E29: 17332 | F29: 22699 | G29: 18276 | H29: =('Balance Sheet'!H55+'Balance Sheet'!H67)-('Balance Sheet'!G55+'Balance Sheet'!G67) -> 111974.68 | I29: =('Balance Sheet'!I55+'Balance Sheet'!I67)-('Balance Sheet'!H55+'Balance Sheet'!H67) -> 63562.743 | J29: =('Balance Sheet'!J55+'Balance Sheet'!J67)-('Balance Sheet'!I55+'Balance Sheet'!I67) -> 65673.582 | K29: =('Balance Sheet'!K55+'Balance Sheet'!K67)-('Balance Sheet'!J55+'Balance Sheet'!J67) -> 66696.467 | L29: =('Balance Sheet'!L55+'Balance Sheet'!L67)-('Balance Sheet'!K55+'Balance Sheet'!K67) -> 66469.086 | M29: =('Balance Sheet'!M55+'Balance Sheet'!M67)-('Balance Sheet'!L55+'Balance Sheet'!L67) -> 64862.451 | N29: =('Balance Sheet'!N55+'Balance Sheet'!N67)-('Balance Sheet'!M55+'Balance Sheet'!M67) -> 61791.687 | O29: =('Balance Sheet'!O55+'Balance Sheet'!O67)-('Balance Sheet'!N55+'Balance Sheet'!N67) -> 57225.219 | ... Q29: =('Balance Sheet'!Q55+'Balance Sheet'!Q67)-('Balance Sheet'!P55+'Balance Sheet'!P67) -> 43782.307
B30: Other financial and non-financial liabilities | C30: 11655 | D30: -11991 | E30: 41516 | F30: 48154 | G30: 33760 | H30: =SUM('Balance Sheet'!H53,'Balance Sheet'!H54,'Balance Sheet'!H56,'Balance Sheet'!H57,'Balance Sheet'!H65,'Balance Sheet'!H66,'Balance Sheet'!H68,'Balance Sheet'!H69)-SUM('Balance Sheet'!G53,'Balance Sheet'!G54,'Balance Sheet'!G56,'Balance Sheet'!G57,'Balance Sheet'!G65,'Balance Sheet'!G66,'Balance Sheet'!G68,'Balance Sheet'!G69) -> 174840.56 | I30: =SUM('Balance Sheet'!I53,'Balance Sheet'!I54,'Balance Sheet'!I56,'Balance Sheet'!I57,'Balance Sheet'!I65,'Balance Sheet'!I66,'Balance Sheet'!I68,'Balance Sheet'!I69)-SUM('Balance Sheet'!H53,'Balance Sheet'!H54,'Balance Sheet'!H56,'Balance Sheet'!H57,'Balance Sheet'!H65,'Balance Sheet'!H66,'Balance Sheet'!H68,'Balance Sheet'!H69) -> 98052.322 | J30: =SUM('Balance Sheet'!J53,'Balance Sheet'!J54,'Balance Sheet'!J56,'Balance Sheet'!J57,'Balance Sheet'!J65,'Balance Sheet'!J66,'Balance Sheet'!J68,'Balance Sheet'!J69)-SUM('Balance Sheet'!I53,'Balance Sheet'!I54,'Balance Sheet'!I56,'Balance Sheet'!I57,'Balance Sheet'!I65,'Balance Sheet'!I66,'Balance Sheet'!I68,'Balance Sheet'!I69) -> 103946.45 | K30: =SUM('Balance Sheet'!K53,'Balance Sheet'!K54,'Balance Sheet'!K56,'Balance Sheet'!K57,'Balance Sheet'!K65,'Balance Sheet'!K66,'Balance Sheet'!K68,'Balance Sheet'!K69)-SUM('Balance Sheet'!J53,'Balance Sheet'!J54,'Balance Sheet'!J56,'Balance Sheet'!J57,'Balance Sheet'!J65,'Balance Sheet'!J66,'Balance Sheet'!J68,'Balance Sheet'!J69) -> 99812.799 | L30: =SUM('Balance Sheet'!L53,'Balance Sheet'!L54,'Balance Sheet'!L56,'Balance Sheet'!L57,'Balance Sheet'!L65,'Balance Sheet'!L66,'Balance Sheet'!L68,'Balance Sheet'!L69)-SUM('Balance Sheet'!K53,'Balance Sheet'!K54,'Balance Sheet'!K56,'Balance Sheet'!K57,'Balance Sheet'!K65,'Balance Sheet'!K66,'Balance Sheet'!K68,'Balance Sheet'!K69) -> 105773.04 | M30: =SUM('Balance Sheet'!M53,'Balance Sheet'!M54,'Balance Sheet'!M56,'Balance Sheet'!M57,'Balance Sheet'!M65,'Balance Sheet'!M66,'Balance Sheet'!M68,'Balance Sheet'!M69)-SUM('Balance Sheet'!L53,'Balance Sheet'!L54,'Balance Sheet'!L56,'Balance Sheet'!L57,'Balance Sheet'!L65,'Balance Sheet'!L66,'Balance Sheet'!L68,'Balance Sheet'!L69) -> 101451.65 | N30: =SUM('Balance Sheet'!N53,'Balance Sheet'!N54,'Balance Sheet'!N56,'Balance Sheet'!N57,'Balance Sheet'!N65,'Balance Sheet'!N66,'Balance Sheet'!N68,'Balance Sheet'!N69)-SUM('Balance Sheet'!M53,'Balance Sheet'!M54,'Balance Sheet'!M56,'Balance Sheet'!M57,'Balance Sheet'!M65,'Balance Sheet'!M66,'Balance Sheet'!M68,'Balance Sheet'!M69) -> 95958.649 | O30: =SUM('Balance Sheet'!O53,'Balance Sheet'!O54,'Balance Sheet'!O56,'Balance Sheet'!O57,'Balance Sheet'!O65,'Balance Sheet'!O66,'Balance Sheet'!O68,'Balance Sheet'!O69)-SUM('Balance Sheet'!N53,'Balance Sheet'!N54,'Balance Sheet'!N56,'Balance Sheet'!N57,'Balance Sheet'!N65,'Balance Sheet'!N66,'Balance Sheet'!N68,'Balance Sheet'!N69) -> 89102.926 | ... Q30: =SUM('Balance Sheet'!Q53,'Balance Sheet'!Q54,'Balance Sheet'!Q56,'Balance Sheet'!Q57,'Balance Sheet'!Q65,'Balance Sheet'!Q66,'Balance Sheet'!Q68,'Balance Sheet'!Q69)-SUM('Balance Sheet'!P53,'Balance Sheet'!P54,'Balance Sheet'!P56,'Balance Sheet'!P57,'Balance Sheet'!P65,'Balance Sheet'!P66,'Balance Sheet'!P68,'Balance Sheet'!P69) -> 68742.602
B31: Other financial and non-financial assets | C31: -15674 | D31: -31554 | E31: -25398 | F31: -23868 | G31: 2665 | H31: =-(SUM('Balance Sheet'!H24,'Balance Sheet'!H25,'Balance Sheet'!H26,'Balance Sheet'!H27,'Balance Sheet'!H36,'Balance Sheet'!H37)-SUM('Balance Sheet'!G24,'Balance Sheet'!G25,'Balance Sheet'!G26,'Balance Sheet'!G27,'Balance Sheet'!G36,'Balance Sheet'!G37)) -> -524411.77 | I31: =-(SUM('Balance Sheet'!I24,'Balance Sheet'!I25,'Balance Sheet'!I26,'Balance Sheet'!I27,'Balance Sheet'!I36,'Balance Sheet'!I37)-SUM('Balance Sheet'!H24,'Balance Sheet'!H25,'Balance Sheet'!H26,'Balance Sheet'!H27,'Balance Sheet'!H36,'Balance Sheet'!H37)) -> -159407.63 | J31: =-(SUM('Balance Sheet'!J24,'Balance Sheet'!J25,'Balance Sheet'!J26,'Balance Sheet'!J27,'Balance Sheet'!J36,'Balance Sheet'!J37)-SUM('Balance Sheet'!I24,'Balance Sheet'!I25,'Balance Sheet'!I26,'Balance Sheet'!I27,'Balance Sheet'!I36,'Balance Sheet'!I37)) -> -164701.36 | K31: =-(SUM('Balance Sheet'!K24,'Balance Sheet'!K25,'Balance Sheet'!K26,'Balance Sheet'!K27,'Balance Sheet'!K36,'Balance Sheet'!K37)-SUM('Balance Sheet'!J24,'Balance Sheet'!J25,'Balance Sheet'!J26,'Balance Sheet'!J27,'Balance Sheet'!J36,'Balance Sheet'!J37)) -> -167266.63 | L31: =-(SUM('Balance Sheet'!L24,'Balance Sheet'!L25,'Balance Sheet'!L26,'Balance Sheet'!L27,'Balance Sheet'!L36,'Balance Sheet'!L37)-SUM('Balance Sheet'!K24,'Balance Sheet'!K25,'Balance Sheet'!K26,'Balance Sheet'!K27,'Balance Sheet'!K36,'Balance Sheet'!K37)) -> -166696.39 | M31: =-(SUM('Balance Sheet'!M24,'Balance Sheet'!M25,'Balance Sheet'!M26,'Balance Sheet'!M27,'Balance Sheet'!M36,'Balance Sheet'!M37)-SUM('Balance Sheet'!L24,'Balance Sheet'!L25,'Balance Sheet'!L26,'Balance Sheet'!L27,'Balance Sheet'!L36,'Balance Sheet'!L37)) -> -162667.15 | N31: =-(SUM('Balance Sheet'!N24,'Balance Sheet'!N25,'Balance Sheet'!N26,'Balance Sheet'!N27,'Balance Sheet'!N36,'Balance Sheet'!N37)-SUM('Balance Sheet'!M24,'Balance Sheet'!M25,'Balance Sheet'!M26,'Balance Sheet'!M27,'Balance Sheet'!M36,'Balance Sheet'!M37)) -> -154966.04 | O31: =-(SUM('Balance Sheet'!O24,'Balance Sheet'!O25,'Balance Sheet'!O26,'Balance Sheet'!O27,'Balance Sheet'!O36,'Balance Sheet'!O37)-SUM('Balance Sheet'!N24,'Balance Sheet'!N25,'Balance Sheet'!N26,'Balance Sheet'!N27,'Balance Sheet'!N36,'Balance Sheet'!N37)) -> -143513.89 | ... Q31: =-(SUM('Balance Sheet'!Q24,'Balance Sheet'!Q25,'Balance Sheet'!Q26,'Balance Sheet'!Q27,'Balance Sheet'!Q36,'Balance Sheet'!Q37)-SUM('Balance Sheet'!P24,'Balance Sheet'!P25,'Balance Sheet'!P26,'Balance Sheet'!P27,'Balance Sheet'!P36,'Balance Sheet'!P37)) -> -109800.71
B32: Net cash generated from operations before tax | C32: 571920 | D32: 691161 | E32: 817788 | F32: 1027702 | G32: 1285135 | H32: =H24+SUM(H26:H31) -> 1223358.1 | I32: =I24+SUM(I26:I31) -> 1571290.6 | J32: =J24+SUM(J26:J31) -> 1751440.3 | K32: =K24+SUM(K26:K31) -> 1924884.8 | L32: =L24+SUM(L26:L31) -> 2108494.5 | M32: =M24+SUM(M26:M31) -> 2278280.3 | N32: =N24+SUM(N26:N31) -> 2439487.8 | O32: =O24+SUM(O26:O31) -> 2587948.4 | ... Q32: =Q24+SUM(Q26:Q31) -> 2828541.8
B33: Income tax paid (net) | C33: -21754 | D33: -37915 | E33: -28806 | F33: -44380 | G33: -62839 | H33: =-('Income Statement'!H40) -> -129332.24 | I33: =-('Income Statement'!I40) -> -157659.95 | J33: =-('Income Statement'!J40) -> -192714.63 | K33: =-('Income Statement'!K40) -> -233372.39 | L33: =-('Income Statement'!L40) -> -263606.27 | M33: =-('Income Statement'!M40) -> -298108.38 | N33: =-('Income Statement'!N40) -> -334721.37 | O33: =-('Income Statement'!O40) -> -363929.06 | ... Q33: =-('Income Statement'!Q40) -> -417125.39
B34: Net cash generated from operating activities (a) | C34: =C32+C33 -> 550166 | D34: =D32+D33 -> 653246 | E34: =E32+E33 -> 788982 | F34: =F32+F33 -> 983322 | G34: =G32+G33 -> 1222296 | H34: =H32+H33 -> 1094025.8 | I34: =I32+I33 -> 1413630.7 | J34: =J32+J33 -> 1558725.7 | ... Q34: =Q32+Q33 -> 2411416.4
B36: Cash Flows from Investing Activities
B37: Purchase of PP&E and capital WIP | C37: -265406 | D37: -260566 | E37: -381915 | F37: -379077 | G37: -451756 | H37: =-FAS!H177 -> -1071809.6 | I37: =-FAS!I177 -> -1082562.6 | J37: =-FAS!J177 -> -1093530.7 | K37: =-FAS!K177 -> -1310007.4 | L37: =-FAS!L177 -> -1321418.6 | M37: =-FAS!M177 -> -1333058 | N37: =-FAS!N177 -> -1632335.1 | O37: =-FAS!O177 -> -1644444.8 | ... Q37: =-FAS!Q177 -> -2071762.4
B38: Proceeds from sale of PP&E | C38: 13791 | D38: 885 | E38: 1228 | F38: 3382 | G38: 11680 | H38: 0 | I38: 0 | J38: 0 | K38: 0 | L38: 0 | M38: 0 | N38: 0 | O38: 0 | P38: 0 | Q38: 0
B39: Purchase of intangible assets | C39: -8593 | D39: -4819 | E39: -18600 | F39: -17722 | G39: -15386 | H39: 0 | I39: 0 | J39: 0 | K39: 0 | L39: 0 | M39: 0 | N39: 0 | O39: 0 | P39: 0 | Q39: 0
B40: Payment towards spectrum* | C40: -174482 | D40: -123684 | E40: -121547 | F40: -213487 | G40: -8546 | H40: 0 | I40: 0 | J40: 0 | K40: 0 | L40: 0 | M40: 0 | N40: 0 | O40: 0 | P40: 0 | Q40: 0
B41: Proceeds from sale of spectrum | C41: 10048 | D41: - | E41: - | F41: - | G41: - | H41: 0 | I41: 0 | J41: 0 | K41: 0 | L41: 0 | M41: 0 | N41: 0 | O41: 0 | P41: 0 | Q41: 0
B42: Balancing Adjustment (Plug to reconcile BS) | C42: 998 | D42: - | E42: - | F42: - | G42: - | H42: ='Balance Sheet'!H72-'Balance Sheet'!H28-SUM('Balance Sheet'!H30:H33)-SUM('Balance Sheet'!H35:H38)-(H34+H55+H74+H78+H79) -> 8516.8539 | I42: ='Balance Sheet'!I72-'Balance Sheet'!I28-SUM('Balance Sheet'!I30:I33)-SUM('Balance Sheet'!I35:I38)-(I34+I55+I74+I78+I79) -> 1362.3721 | J42: ='Balance Sheet'!J72-'Balance Sheet'!J28-SUM('Balance Sheet'!J30:J33)-SUM('Balance Sheet'!J35:J38)-(J34+J55+J74+J78+J79) -> 2607.4617 | K42: ='Balance Sheet'!K72-'Balance Sheet'!K28-SUM('Balance Sheet'!K30:K33)-SUM('Balance Sheet'!K35:K38)-(K34+K55+K74+K78+K79) -> 35235.48 | L42: ='Balance Sheet'!L72-'Balance Sheet'!L28-SUM('Balance Sheet'!L30:L33)-SUM('Balance Sheet'!L35:L38)-(L34+L55+L74+L78+L79) -> 9697.6636 | M42: ='Balance Sheet'!M72-'Balance Sheet'!M28-SUM('Balance Sheet'!M30:M33)-SUM('Balance Sheet'!M35:M38)-(M34+M55+M74+M78+M79) -> 20425.669 | N42: ='Balance Sheet'!N72-'Balance Sheet'!N28-SUM('Balance Sheet'!N30:N33)-SUM('Balance Sheet'!N35:N38)-(N34+N55+N74+N78+N79) -> 22319.769 | O42: ='Balance Sheet'!O72-'Balance Sheet'!O28-SUM('Balance Sheet'!O30:O33)-SUM('Balance Sheet'!O35:O38)-(O34+O55+O74+O78+O79) -> 26976.259 | ... Q42: ='Balance Sheet'!Q72-'Balance Sheet'!Q28-SUM('Balance Sheet'!Q30:Q33)-SUM('Balance Sheet'!Q35:Q38)-(Q34+Q55+Q74+Q78+Q79) -> 29132.465
B43: (Purchase)/proceeds sale of current investments (net) | C43: 21298 | D43: -12000 | E43: 19015 | F43: 7100 | G43: -126994 | H43: =-(('Balance Sheet'!H20+'Balance Sheet'!H31)-('Balance Sheet'!G20+'Balance Sheet'!G31)) -> 134296.93 | I43: =-(('Balance Sheet'!I20+'Balance Sheet'!I31)-('Balance Sheet'!H20+'Balance Sheet'!H31)) -> -1774.0047 | J43: =-(('Balance Sheet'!J20+'Balance Sheet'!J31)-('Balance Sheet'!I20+'Balance Sheet'!I31)) -> -1832.9172 | K43: =-(('Balance Sheet'!K20+'Balance Sheet'!K31)-('Balance Sheet'!J20+'Balance Sheet'!J31)) -> -1861.4654 | L43: =-(('Balance Sheet'!L20+'Balance Sheet'!L31)-('Balance Sheet'!K20+'Balance Sheet'!K31)) -> -1855.1193 | M43: =-(('Balance Sheet'!M20+'Balance Sheet'!M31)-('Balance Sheet'!L20+'Balance Sheet'!L31)) -> -1810.2789 | N43: =-(('Balance Sheet'!N20+'Balance Sheet'!N31)-('Balance Sheet'!M20+'Balance Sheet'!M31)) -> -1724.5754 | O43: =-(('Balance Sheet'!O20+'Balance Sheet'!O31)-('Balance Sheet'!N20+'Balance Sheet'!N31)) -> -1597.1275 | ... Q43: =-(('Balance Sheet'!Q20+'Balance Sheet'!Q31)-('Balance Sheet'!P20+'Balance Sheet'!P31)) -> -1221.9425
B44: Proceeds from sale of non-current investments | C44: - | D44: 311 | E44: 69 | F44: 300 | G44: 90 | H44: 0 | I44: 0 | J44: 0 | K44: 0 | L44: 0 | M44: 0 | N44: 0 | O44: 0 | P44: 0 | Q44: 0
B45: Purchase of non-current investments | C45: -89 | D45: -323 | E45: -304 | F45: -734 | G45: -1241 | H45: 0 | I45: 0 | J45: 0 | K45: 0 | L45: 0 | M45: 0 | N45: 0 | O45: 0 | P45: 0 | Q45: 0
B46: Proceeds from sale of tower subsidiary (net) | C46: 5887 | D46: - | E46: - | F46: - | G46: - | H46: 0 | I46: 0 | J46: 0 | K46: 0 | L46: 0 | M46: 0 | N46: 0 | O46: 0 | P46: 0 | Q46: 0
B47: Investment in JV / associates | C47: -26208 | D47: -8106 | E47: -300 | F47: -8788 | G47: - | H47: =-('Balance Sheet'!H18-'Balance Sheet'!G18) -> -312647.21 | I47: =-('Balance Sheet'!I18-'Balance Sheet'!H18) -> -44465.603 | J47: =-('Balance Sheet'!J18-'Balance Sheet'!I18) -> -45942.25 | K47: =-('Balance Sheet'!K18-'Balance Sheet'!J18) -> -46657.814 | L47: =-('Balance Sheet'!L18-'Balance Sheet'!K18) -> -46498.749 | M47: =-('Balance Sheet'!M18-'Balance Sheet'!L18) -> -45374.82 | N47: =-('Balance Sheet'!N18-'Balance Sheet'!M18) -> -43226.653 | O47: =-('Balance Sheet'!O18-'Balance Sheet'!N18) -> -40032.16 | ... Q47: =-('Balance Sheet'!Q18-'Balance Sheet'!P18) -> -30628.11
B48: Repayment of loan given to JV | C48: 8 | D48: - | E48: - | F48: - | G48: 907 | H48: 0 | I48: 0 | J48: 0 | K48: 0 | L48: 0 | M48: 0 | N48: 0 | O48: 0 | P48: 0 | Q48: 0
B49: Acquisition of subsidiary, net of cash | C49: - | D49: - | E49: -6428 | F49: - | G49: - | H49: 0 | I49: 0 | J49: 0 | K49: 0 | L49: 0 | M49: 0 | N49: 0 | O49: 0 | P49: 0 | Q49: 0
B50: Cash disposed off on sale of subsidiaries | C50: - | D50: - | E50: - | F50: -69 | G50: - | H50: 0 | I50: 0 | J50: 0 | K50: 0 | L50: 0 | M50: 0 | N50: 0 | O50: 0 | P50: 0 | Q50: 0
B51: Cash acquired on acquisition of subsidiary | C51: - | D51: - | E51: - | F51: 1023 | G51: - | H51: 0 | I51: 0 | J51: 0 | K51: 0 | L51: 0 | M51: 0 | N51: 0 | O51: 0 | P51: 0 | Q51: 0
B52: Proceeds from sale of investment in JV | C52: - | D52: - | E52: - | F52: 45 | G52: - | H52: 0 | I52: 0 | J52: 0 | K52: 0 | L52: 0 | M52: 0 | N52: 0 | O52: 0 | P52: 0 | Q52: 0
B53: Dividend received | C53: - | D53: 13992 | E53: 1072 | F53: 1090 | G53: 1813 | H53: =G53 -> 1813 | I53: =H53 -> 1813 | J53: =I53 -> 1813 | K53: =J53 -> 1813 | L53: =K53 -> 1813 | M53: =L53 -> 1813 | N53: =M53 -> 1813 | O53: =N53 -> 1813 | ... Q53: =P53 -> 1813
B54: Interest received | C54: 4052 | D54: 3508 | E54: 5671 | F54: 4239 | G54: 4088 | H54: =G54 -> 4088 | I54: =H54 -> 4088 | J54: =I54 -> 4088 | K54: =J54 -> 4088 | L54: =K54 -> 4088 | M54: =L54 -> 4088 | N54: =M54 -> 4088 | O54: =N54 -> 4088 | ... Q54: =P54 -> 4088
B55: Net cash used in investing activities (b) | C55: =SUM(C37:C54) -> -418696 | D55: =SUM(D37:D54) -> -390802 | E55: =SUM(E37:E54) -> -502039 | F55: =SUM(F37:F54) -> -602698 | G55: =SUM(G37:G54) -> -585345 | H55: =SUM(H37:H41,H43:H54) -> -1244258.9 | I55: =SUM(I37:I41,I43:I54) -> -1122901.2 | J55: =SUM(J37:J41,J43:J54) -> -1135404.8 | K55: =SUM(K37:K41,K43:K54) -> -1352625.7 | L55: =SUM(L37:L41,L43:L54) -> -1363871.4 | M55: =SUM(M37:M41,M43:M54) -> -1374342 | N55: =SUM(N37:N41,N43:N54) -> -1671385.4 | O55: =SUM(O37:O41,O43:O54) -> -1680173 | ... Q55: =SUM(Q37:Q41,Q43:Q54) -> -2097711.5
B57: Cash Flows from Financing Activities
B58: Net proceeds from issue of shares | C58: 52226 | D58: 52242 | E58: - | F58: - | G58: 156949 | H58: 0 | I58: 0 | J58: 0 | K58: 0 | L58: 0 | M58: 0 | N58: 0 | O58: 0 | P58: 0 | Q58: 0
B59: Proceeds from borrowings | C59: 254785 | D59: 136077 | E59: 67123 | F59: 235597 | G59: 140131 | H59: =('Balance Sheet'!H50+'Balance Sheet'!H61)-('Balance Sheet'!G50+'Balance Sheet'!G61) -> 375102.99 | I59: =('Balance Sheet'!I50+'Balance Sheet'!I61)-('Balance Sheet'!H50+'Balance Sheet'!H61) -> 200360.24 | J59: =('Balance Sheet'!J50+'Balance Sheet'!J61)-('Balance Sheet'!I50+'Balance Sheet'!I61) -> 207013.95 | K59: =('Balance Sheet'!K50+'Balance Sheet'!K61)-('Balance Sheet'!J50+'Balance Sheet'!J61) -> 210238.25 | L59: =('Balance Sheet'!L50+'Balance Sheet'!L61)-('Balance Sheet'!K50+'Balance Sheet'!K61) -> 209521.51 | M59: =('Balance Sheet'!M50+'Balance Sheet'!M61)-('Balance Sheet'!L50+'Balance Sheet'!L61) -> 204457.13 | N59: =('Balance Sheet'!N50+'Balance Sheet'!N61)-('Balance Sheet'!M50+'Balance Sheet'!M61) -> 194777.58 | O59: =('Balance Sheet'!O50+'Balance Sheet'!O61)-('Balance Sheet'!N50+'Balance Sheet'!N61) -> 180383.32 | ... Q59: =('Balance Sheet'!Q50+'Balance Sheet'!Q61)-('Balance Sheet'!P50+'Balance Sheet'!P61) -> 138009.05
B60: Repayment of borrowings | C60: -337212 | D60: -178227 | E60: -100803 | F60: -178594 | G60: -420773 | H60: 0 | I60: 0 | J60: 0 | K60: 0 | L60: 0 | M60: 0 | N60: 0 | O60: 0 | P60: 0 | Q60: 0
B61: Payment of lease liabilities | C61: -76427 | D61: -75986 | E61: -78552 | F61: -71538 | G61: -67197 | H61: =('Balance Sheet'!H51+'Balance Sheet'!H62)-('Balance Sheet'!G51+'Balance Sheet'!G62) -> 229203.71 | I61: =('Balance Sheet'!I51+'Balance Sheet'!I62)-('Balance Sheet'!H51+'Balance Sheet'!H62) -> 121665.71 | J61: =('Balance Sheet'!J51+'Balance Sheet'!J62)-('Balance Sheet'!I51+'Balance Sheet'!I62) -> 125706.08 | K61: =('Balance Sheet'!K51+'Balance Sheet'!K62)-('Balance Sheet'!J51+'Balance Sheet'!J62) -> 127663.99 | L61: =('Balance Sheet'!L51+'Balance Sheet'!L62)-('Balance Sheet'!K51+'Balance Sheet'!K62) -> 127228.76 | M61: =('Balance Sheet'!M51+'Balance Sheet'!M62)-('Balance Sheet'!L51+'Balance Sheet'!L62) -> 124153.49 | N61: =('Balance Sheet'!N51+'Balance Sheet'!N62)-('Balance Sheet'!M51+'Balance Sheet'!M62) -> 118275.73 | O61: =('Balance Sheet'!O51+'Balance Sheet'!O62)-('Balance Sheet'!N51+'Balance Sheet'!N62) -> 109535.03 | ... Q61: =('Balance Sheet'!Q51+'Balance Sheet'!Q62)-('Balance Sheet'!P51+'Balance Sheet'!P62) -> 83803.899
B62: (Repayment of)/proceeds from short-term borrowings (net) | C62: 63649 | D62: -70972 | E62: 15516 | F62: 36927 | G62: -44087 | H62: 0 | I62: 0 | J62: 0 | K62: 0 | L62: 0 | M62: 0 | N62: 0 | O62: 0 | P62: 0 | Q62: 0
B63: Purchase of treasury shares | C63: -598 | D63: -499 | E63: -1368 | F63: -3675 | G63: -1467 | H63: 0 | I63: 0 | J63: 0 | K63: 0 | L63: 0 | M63: 0 | N63: 0 | O63: 0 | P63: 0 | Q63: 0
B64: Interest and other finance charges paid | C64: -131588 | D64: -66893 | E64: -140263 | F64: -175476 | G64: -148876 | H64: =-('Income Statement'!H31) -> -332763.81 | I64: =-('Income Statement'!I31) -> -374648.42 | J64: =-('Income Statement'!J31) -> -417923.97 | K64: =-('Income Statement'!K31) -> -461873.55 | L64: =-('Income Statement'!L31) -> -505673.29 | M64: =-('Income Statement'!M31) -> -548414.34 | N64: =-('Income Statement'!N31) -> -589131.92 | O64: =-('Income Statement'!O31) -> -626840.42 | ... Q64: =-('Income Statement'!Q31) -> -689423.31
B65: Proceeds from exercise of share options | C65: 7 | D65: 3 | E65: 6 | F65: 14 | G65: 20 | H65: 0 | I65: 0 | J65: 0 | K65: 0 | L65: 0 | M65: 0 | N65: 0 | O65: 0 | P65: 0 | Q65: 0
B66: Dividend paid | C66: -14438 | D66: -35898 | E66: -41845 | F66: -69349 | G66: -113277 | H66: =-('Income Statement'!H47) -> -85851.618 | I66: =-('Income Statement'!I47) -> -103863.99 | J66: =-('Income Statement'!J47) -> -125655.5 | K66: =-('Income Statement'!K47) -> -152019.06 | L66: =-('Income Statement'!L47) -> -183913.9 | M66: =-('Income Statement'!M47) -> -222500.54 | N66: =-('Income Statement'!N47) -> -269182.97 | O66: =-('Income Statement'!O47) -> -325659.75 | ... Q66: =-('Income Statement'!Q47) -> -476647.28
B67: Proceeds from issuance of compulsorily convertible preference shares | C67: 10880 | D67: - | E67: - | F67: - | G67: - | H67: 0 | I67: 0 | J67: 0 | K67: 0 | L67: 0 | M67: 0 | N67: 0 | O67: 0 | P67: 0 | Q67: 0
B68: Net proceeds from issuance of equity shares to NCI | C68: - | D68: - | E68: - | F68: - | G68: 75 | H68: 0 | I68: 0 | J68: 0 | K68: 0 | L68: 0 | M68: 0 | N68: 0 | O68: 0 | P68: 0 | Q68: 0
B69: Redemption of perpetual bonds | C69: - | D69: - | E69: - | F69: -86292 | G69: - | H69: 0 | I69: 0 | J69: 0 | K69: 0 | L69: 0 | M69: 0 | N69: 0 | O69: 0 | P69: 0 | Q69: 0
B70: Buyback of perpetual bonds from NCI | C70: - | D70: - | E70: -1693 | F70: - | G70: - | H70: 0 | I70: 0 | J70: 0 | K70: 0 | L70: 0 | M70: 0 | N70: 0 | O70: 0 | P70: 0 | Q70: 0
B71: Purchase of shares from NCI | C71: -13523 | D71: -641 | E71: -870 | F71: -37348 | G71: -19056 | H71: 0 | I71: 0 | J71: 0 | K71: 0 | L71: 0 | M71: 0 | N71: 0 | O71: 0 | P71: 0 | Q71: 0
B72: Payment/(proceeds) on maturity of derivatives (net) | C72: -704 | D72: -3901 | E72: 573 | F72: -16427 | G72: -5368 | H72: 0 | I72: 0 | J72: 0 | K72: 0 | L72: 0 | M72: 0 | N72: 0 | O72: 0 | P72: 0 | Q72: 0
B73: Proceeds from sale of shares of subsidiary to NCI | C73: 40911 | D73: - | E73: 4391 | F73: 829 | G73: - | H73: 0 | I73: 0 | J73: 0 | K73: 0 | L73: 0 | M73: 0 | N73: 0 | O73: 0 | P73: 0 | Q73: 0
B74: Net cash used in financing activities (c) | C74: =SUM(C58:C73) -> -152032 | D74: =SUM(D58:D73) -> -244695 | E74: =SUM(E58:E73) -> -277785 | F74: =SUM(F58:F73) -> -365332 | G74: =SUM(G58:G73) -> -522926 | H74: =SUM(H58:H73) -> 185691.28 | I74: =SUM(I58:I73) -> -156486.46 | J74: =SUM(J58:J73) -> -210859.44 | ... Q74: =SUM(Q58:Q73) -> -944257.65
B76: Net Increase / (Decrease) in Cash and Cash equivalents (A+B+C) | C76: =SUM(C34,C55,C74) -> -20562 | D76: =SUM(D34,D55,D74) -> 17749 | E76: =SUM(E34,E55,E74) -> 9158 | F76: =SUM(F34,F55,F74) -> 15292 | G76: =SUM(G34,G55,G74) -> 114025 | H76: =SUM(H34,H55,H74,H42) -> 43975.096 | I76: =SUM(I34,I55,I74,I42) -> 135605.36 | J76: =SUM(J34,J55,J74,J42) -> 215068.89 | K76: =SUM(K34,K55,K74,K42) -> 98131.863 | L76: =SUM(L34,L55,L74,L42) -> 137877.58 | M76: =SUM(M34,M55,M74,M42) -> 183951.28 | N76: =SUM(N34,N55,N74,N42) -> -89560.713 | O76: =SUM(O34,O55,O74,O42) -> -91759.295 | ... Q76: =SUM(Q34,Q55,Q74,Q42) -> -601420.26
B78: Effect of exchange rate on cash & cash equivalents | C78: 3919 | D78: -1522 | E78: -8851 | F78: 718 | G78: 23291 | H78: =G78 -> 23291 | I78: =H78 -> 23291 | J78: =I78 -> 23291 | K78: =J78 -> 23291 | L78: =K78 -> 23291 | M78: =L78 -> 23291 | N78: =M78 -> 23291 | O78: =N78 -> 23291 | ... Q78: =P78 -> 23291
B79: Cash & Cash Equivalents at Beginning of the Year | C79: 90630 | D79: =C80 -> 73987 | E79: =D80 -> 90214 | F79: =E80 -> 90521 | G79: =F80 -> 106531 | H79: ='Balance Sheet'!G34 -> 137222 | I79: =H80 -> 204488.1 | J79: =I80 -> 363384.45 | K79: =J80 -> 601744.34 | L79: =K80 -> 723167.21 | M79: =L80 -> 884335.79 | N79: =M80 -> 1091578.1 | O79: =N80 -> 1025308.4 | P79: =O80 -> 956840.06 | Q79: =P80 -> 849987.13
B80: Closing Cash Balance | C80: =SUM(C76:C79) -> 73987 | D80: =SUM(D76:D79) -> 90214 | E80: =SUM(E76:E79) -> 90521 | F80: =SUM(F76:F79) -> 106531 | G80: =SUM(G76:G79) -> 243847 | H80: =SUM(H76:H79) -> 204488.1 | I80: =SUM(I76:I79) -> 363384.45 | J80: =SUM(J76:J79) -> 601744.34 | ... Q80: =SUM(Q76:Q79) -> 271857.88

Sheet Summary
A1: =Assumptions!A1 -> Bharti Airtel Ltd.
A3: Valuation Summary - Football Field
A5: Valuation Summary - Football Field
K6: Market
H7: Comps | I7: DCF | J7: 52-week hi/lo | K7: Consensus
B8: High | H8: =MAX('Comps Data'!G9:G14) -> 1818.8 | I8: ='DCF Valuation'!I60 -> 4160.8714 | J8: 1948.4 | K8: =MAX(I28:I31) -> 2355
B9: High | H9: =H8 -> 1818.8 | I9: =I8 -> 4160.8714 | J9: =J8 -> 1948.4 | K9: =K8 -> 2355
B10: Low | H10: =MIN('Comps Data'!G9:G14) -> 0.85 | I10: ='DCF Valuation'!K60 -> 1675.5349 | J10: 1775.2 | K10: =MIN(I28:I31) -> 2180
B11: Low | H11: =H10 -> 0.85 | I11: =I10 -> 1675.5349 | J11: =J10 -> 1775.2 | K11: =K10 -> 2180
B12: Range (High - Low) | H12: =H8-H10 -> 1817.95 | I12: =I8-I10 -> 2485.3365 | J12: =J8-J10 -> 173.2 | K12: =K8-K10 -> 175
A13: Valuation Summary
A27: Broker Analysis | E27: Date | H27: LTP | I27: Target Price
A28: ICICI Direct Research | E28: 46159 | H28: 1950 | I28: 2350
A29: Axis Securities | E29: 46157 | H29: 1834 | I29: 2200
A30: Geojit BNP Paribas | E30: 46196 | H30: 1912 | I30: 2180
A31: Motilal Oswal | E31: 46060 | H31: 1912 | I31: 2355

Sheet Ratio Analysis
A1: Bharti Airtel Ltd
B7: Ratio Analysis | T7: Interpretation of ratios
B8: Particulars | C8: =FAS!C7 -> 2022 | D8: =FAS!D7 -> 2023 | E8: =FAS!E7 -> 2024 | F8: =FAS!F7 -> 2025 | G8: =FAS!G7 -> 2026 | H8: =FAS!H7 -> 2027 | I8: =FAS!I7 -> 2028 | J8: =FAS!J7 -> 2029 | ... Q8: =FAS!Q7 -> 2036 | R8: Trend
C9: Audited | D9: Audited | E9: Audited | F9: Audited | G9: Audited | H9: Estimated | I9: Projected | J9: Projected | K9: Projected | L9: Projected | M9: Projected | N9: Projected | O9: Projected | P9: Projected | Q9: Projected
B11: Profitability Ratios
B12: EBITDA Margin | C12: ='Income Statement'!C25/'Income Statement'!C13 -> 0.49596519 | D12: ='Income Statement'!D25/'Income Statement'!D13 -> 0.51548671 | E12: ='Income Statement'!E25/'Income Statement'!E13 -> 0.52653783 | F12: ='Income Statement'!F25/'Income Statement'!F13 -> 0.54269877 | G12: ='Income Statement'!G25/'Income Statement'!G13 -> 0.57295357 | H12: ='Income Statement'!H25/'Income Statement'!H13 -> 0.53072841 | I12: ='Income Statement'!I25/'Income Statement'!I13 -> 0.53072841 | J12: ='Income Statement'!J25/'Income Statement'!J13 -> 0.53072841 | ... Q12: ='Income Statement'!Q25/'Income Statement'!Q13 -> 0.53072841 | T12: Airtel's EBITDA margin increased consistently from 49.60% in FY22 to 57.30% in FY26, indicating a significant improvement in operating profitability. This expansion was primarily driven by sustained tariff hikes, growth in high-value 4G/5G subscribers, increasing Average Revenue Per User (ARPU), and operating leverage, which enabled revenue to grow faster than operating expenses. The improvement also reflects better cost efficiency and the company's ability to generate higher operating earnings from its telecom operations. From FY27 onwards, the margin is conservatively projected at 53.07%, assuming the benefits of recent margin expansion gradually normalize as the business enters a mature growth phase. Although the forecast does not assume further margin expansion, maintaining a margin above 53% demonstrates Airtel's strong operating efficiency and supports stable cash flow generation and long-term profitability.
B13: Operating Margin | C13: ='Income Statement'!C29/'Income Statement'!C13 -> 0.21333485 | D13: ='Income Statement'!D29/'Income Statement'!D13 -> 0.25541078 | E13: ='Income Statement'!E29/'Income Statement'!E13 -> 0.2654219 | F13: ='Income Statement'!F29/'Income Statement'!F13 -> 0.28163903 | G13: ='Income Statement'!G29/'Income Statement'!G13 -> 0.32639959 | H13: ='Income Statement'!H29/'Income Statement'!H13 -> 0.3191626 | I13: ='Income Statement'!I29/'Income Statement'!I13 -> 0.33905678 | J13: ='Income Statement'!J29/'Income Statement'!J13 -> 0.35546767 | ... Q13: ='Income Statement'!Q29/'Income Statement'!Q13 -> 0.40868983 | T13: Airtel's Operating Margin improved significantly from 21.33% in FY22 to 32.64% in FY26, reflecting a substantial enhancement in operating profitability. The improvement was primarily driven by strong EBITDA growth, higher ARPU, tariff revisions, subscriber premiumisation, and improved cost efficiencies, while depreciation grew at a slower pace relative to revenue. Although the margin is projected to decline marginally to 31.92% in FY27, it is expected to recover steadily and reach 40.87% by FY36, indicating continued operational efficiency as the company's network investments mature and incremental revenue contributes more directly to operating profit. This trend suggests Airtel is well-positioned to strengthen its earnings quality and generate higher operating cash flows over the long term, provided future capital expenditure and depreciation assumptions remain consistent with the projected business expansion.
